[{"theme":"food","keyword":"徐力剛","subkeyword":"加贈","weight":53.49},{"theme":"food","keyword":"徐力剛","subkeyword":"情人節","weight":52.63},{"theme":"food","keyword":"徐力剛","subkeyword":"夜宿","weight":52.15},{"theme":"food","keyword":"徐力剛","subkeyword":"饕最","weight":50.0},{"theme":"food","keyword":"徐力剛","subkeyword":"雞湯","weight":47.65},{"theme":"food","keyword":"徐力剛","subkeyword":"米其林","weight":47.45},{"theme":"food","keyword":"徐力剛","subkeyword":"起司","weight":47.34},{"theme":"food","keyword":"徐力剛","subkeyword":"澎湃","weight":47.17},{"theme":"food","keyword":"徐力剛","subkeyword":"壽司","weight":46.8},{"theme":"food","keyword":"徐力剛","subkeyword":"大肚","weight":46.21},{"theme":"food","keyword":"徐力剛","subkeyword":"扇貝","weight":45.16},{"theme":"food","keyword":"徐力剛","subkeyword":"中西","weight":44.15},{"theme":"food","keyword":"徐力剛","subkeyword":"拚場","weight":42.9},{"theme":"food","keyword":"徐力剛","subkeyword":"限量","weight":41.36},{"theme":"food","keyword":"徐力剛","subkeyword":"巧克力","weight":41.2},{"theme":"food","keyword":"徐力剛","subkeyword":"華山","weight":41.08},{"theme":"food","keyword":"徐力剛","subkeyword":"鮭雙享祭","weight":34.83},{"theme":"food","keyword":"徐力剛","subkeyword":"臺北","weight":34.82},{"theme":"food","keyword":"徐力剛","subkeyword":"禮盒","weight":34.72},{"theme":"food","keyword":"徐力剛","subkeyword":"登場","weight":34.67},{"theme":"food","keyword":"徐力剛","subkeyword":"火鍋","weight":34.59},{"theme":"food","keyword":"徐力剛","subkeyword":"加碼","weight":34.56},{"theme":"food","keyword":"徐力剛","subkeyword":"星級","weight":34.44},{"theme":"food","keyword":"徐力剛","subkeyword":"牛禮搶","weight":32.96},{"theme":"food","keyword":"徐力剛","subkeyword":"商機","weight":32.77},{"theme":"food","keyword":"徐力剛","subkeyword":"炸雞","weight":12.8},{"theme":"food","keyword":"徐力剛","subkeyword":"開賣","weight":12.45},{"theme":"food","keyword":"徐力剛","subkeyword":"牛禮","weight":12.45},{"theme":"food","keyword":"徐力剛","subkeyword":"美福食集","weight":12.45},{"theme":"food","keyword":"徐力剛","subkeyword":"4500","weight":12.45},{"theme":"food","keyword":"徐力剛","subkeyword":"GODIVA","weight":12.45},{"theme":"food","keyword":"徐力剛","subkeyword":"最夯","weight":12.45},{"theme":"food","keyword":"徐力剛","subkeyword":"雙享","weight":12.45},{"theme":"food","keyword":"徐力剛","subkeyword":"元起","weight":12.45},{"theme":"food","keyword":"徐力剛","subkeyword":"1600","weight":12.45},{"theme":"food","keyword":"徐力剛","subkeyword":"GO","weight":12.45},{"theme":"food","keyword":"徐力剛","subkeyword":"戀戀","weight":12.19},{"theme":"food","keyword":"徐力剛","subkeyword":"懶人","weight":12.08},{"theme":"food","keyword":"徐力剛","subkeyword":"首飾盒","weight":11.47},{"theme":"food","keyword":"徐力剛","subkeyword":"外帶","weight":11.13},{"theme":"food","keyword":"米其林","subkeyword":"米其林","weight":75.95},{"theme":"food","keyword":"米其林","subkeyword":"星級","weight":45.63},{"theme":"food","keyword":"米其林","subkeyword":"福源","weight":45.59},{"theme":"food","keyword":"米其林","subkeyword":"黑糖","weight":36.29},{"theme":"food","keyword":"米其林","subkeyword":"巷弄","weight":35.85},{"theme":"food","keyword":"米其林","subkeyword":"酸香","weight":35.41},{"theme":"food","keyword":"米其林","subkeyword":"珍奶","weight":35.38},{"theme":"food","keyword":"米其林","subkeyword":"外脆","weight":35.27},{"theme":"food","keyword":"米其林","subkeyword":"食記","weight":31.33},{"theme":"food","keyword":"米其林","subkeyword":"文華","weight":30.01},{"theme":"food","keyword":"米其林","subkeyword":"業績","weight":29.88},{"theme":"food","keyword":"米其林","subkeyword":"情人節","weight":29.81},{"theme":"food","keyword":"米其林","subkeyword":"木瓜","weight":27.88},{"theme":"food","keyword":"米其林","subkeyword":"中西","weight":27.83},{"theme":"food","keyword":"米其林","subkeyword":"韌帶","weight":26.95},{"theme":"food","keyword":"米其林","subkeyword":"冠軍","weight":26.63},{"theme":"food","keyword":"米其林","subkeyword":"飯店","weight":22.79},{"theme":"food","keyword":"米其林","subkeyword":"國父","weight":22.68},{"theme":"food","keyword":"米其林","subkeyword":"果肉","weight":22.62},{"theme":"food","keyword":"米其林","subkeyword":"圍爐","weight":22.62},{"theme":"food","keyword":"米其林","subkeyword":"日本","weight":22.62},{"theme":"food","keyword":"米其林","subkeyword":"口味","weight":22.47},{"theme":"food","keyword":"米其林","subkeyword":"紀念館","weight":22.26},{"theme":"food","keyword":"米其林","subkeyword":"推薦","weight":22.18},{"theme":"food","keyword":"米其林","subkeyword":"外帶","weight":22.06},{"theme":"food","keyword":"米其林","subkeyword":"PopDaily","weight":17.08},{"theme":"food","keyword":"米其林","subkeyword":"最夯","weight":17.08},{"theme":"food","keyword":"米其林","subkeyword":"波波黛莉","weight":17.08},{"theme":"food","keyword":"米其林","subkeyword":"發胖","weight":13.79},{"theme":"food","keyword":"米其林","subkeyword":"甜蜜","weight":12.38},{"theme":"food","keyword":"米其林","subkeyword":"自助餐","weight":8.78},{"theme":"food","keyword":"米其林","subkeyword":"米其林酥塔","weight":8.54},{"theme":"food","keyword":"米其林","subkeyword":"珍珠奶茶","weight":8.54},{"theme":"food","keyword":"米其林","subkeyword":"新北","weight":8.54},{"theme":"food","keyword":"米其林","subkeyword":"Karen","weight":8.54},{"theme":"food","keyword":"米其林","subkeyword":"Yo","weight":8.54},{"theme":"food","keyword":"米其林","subkeyword":"美點","weight":8.54},{"theme":"food","keyword":"米其林","subkeyword":"拚場","weight":8.54},{"theme":"food","keyword":"米其林","subkeyword":"款長","weight":8.54},{"theme":"food","keyword":"米其林","subkeyword":"盲試","weight":8.54},{"theme":"food","keyword":"米其林","subkeyword":"AR","weight":8.54},{"theme":"food","keyword":"銘謝惠","subkeyword":"全家","weight":138.41},{"theme":"food","keyword":"銘謝惠","subkeyword":"金牛福袋","weight":137.94},{"theme":"food","keyword":"銘謝惠","subkeyword":"商品","weight":110.98},{"theme":"food","keyword":"銘謝惠","subkeyword":"福袋","weight":81.82},{"theme":"food","keyword":"銘謝惠","subkeyword":"小物","weight":81.65},{"theme":"food","keyword":"銘謝惠","subkeyword":"可愛","weight":64.84},{"theme":"food","keyword":"銘謝惠","subkeyword":"授權","weight":64.04},{"theme":"food","keyword":"國父紀念館","subkeyword":"牛船","weight":66.16},{"theme":"food","keyword":"國父紀念館","subkeyword":"靜岡","weight":63.98},{"theme":"food","keyword":"國父紀念館","subkeyword":"米其林","weight":63.91},{"theme":"food","keyword":"國父紀念館","subkeyword":"巷弄","weight":63.48},{"theme":"food","keyword":"國父紀念館","subkeyword":"美食","weight":55.25},{"theme":"food","keyword":"國父紀念館","subkeyword":"京昌園","weight":54.83},{"theme":"food","keyword":"國父紀念館","subkeyword":"高品質","weight":52.03},{"theme":"food","keyword":"國父紀念館","subkeyword":"入港","weight":51.9},{"theme":"food","keyword":"國父紀念館","subkeyword":"燒肉","weight":51.65},{"theme":"food","keyword":"國父紀念館","subkeyword":"牛肉","weight":50.39},{"theme":"food","keyword":"國父紀念館","subkeyword":"紀念館","weight":50.39},{"theme":"food","keyword":"國父紀念館","subkeyword":"老店","weight":50.24},{"theme":"food","keyword":"國父紀念館","subkeyword":"部位","weight":49.16},{"theme":"food","keyword":"國父紀念館","subkeyword":"波波黛莉","weight":48.47},{"theme":"food","keyword":"國父紀念館","subkeyword":"PopDaily","weight":48.47},{"theme":"food","keyword":"國父紀念館","subkeyword":"壽司","weight":45.32},{"theme":"food","keyword":"國父紀念館","subkeyword":"國父","weight":44.84},{"theme":"food","keyword":"國父紀念館","subkeyword":"發胖","weight":39.13},{"theme":"food","keyword":"國父紀念館","subkeyword":"推薦","weight":38.4},{"theme":"food","keyword":"國父紀念館","subkeyword":"臺北","weight":28.24},{"theme":"food","keyword":"國父紀念館","subkeyword":"滿足","weight":27.34},{"theme":"food","keyword":"國父紀念館","subkeyword":"糖思","weight":16.16},{"theme":"food","keyword":"國父紀念館","subkeyword":"Miss","weight":16.16},{"theme":"food","keyword":"國父紀念館","subkeyword":"Sugar","weight":16.16},{"theme":"food","keyword":"國父紀念館","subkeyword":"食記","weight":16.16},{"theme":"food","keyword":"國父紀念館","subkeyword":"60","weight":16.16},{"theme":"food","keyword":"國父紀念館","subkeyword":"念念不忘","weight":13.06},{"theme":"food","keyword":"國父紀念館","subkeyword":"美味","weight":12.13},{"theme":"food","keyword":"卡娜赫拉","subkeyword":"福袋","weight":89.85},{"theme":"food","keyword":"卡娜赫拉","subkeyword":"禮盒","weight":77.55},{"theme":"food","keyword":"卡娜赫拉","subkeyword":"全家","weight":65.23},{"theme":"food","keyword":"卡娜赫拉","subkeyword":"小物","weight":51.38},{"theme":"food","keyword":"卡娜赫拉","subkeyword":"公仔","weight":46.39},{"theme":"food","keyword":"卡娜赫拉","subkeyword":"授權","weight":43.81},{"theme":"food","keyword":"卡娜赫拉","subkeyword":"物桶","weight":43.26},{"theme":"food","keyword":"卡娜赫拉","subkeyword":"三麗鷗","weight":43.14},{"theme":"food","keyword":"卡娜赫拉","subkeyword":"限定","weight":41.81},{"theme":"food","keyword":"卡娜赫拉","subkeyword":"獨家","weight":41.1},{"theme":"food","keyword":"卡娜赫拉","subkeyword":"全台","weight":39.74},{"theme":"food","keyword":"卡娜赫拉","subkeyword":"新春","weight":38.19},{"theme":"food","keyword":"卡娜赫拉","subkeyword":"可愛","weight":38.11},{"theme":"food","keyword":"卡娜赫拉","subkeyword":"整理","weight":37.31},{"theme":"food","keyword":"卡娜赫拉","subkeyword":"迪士尼","weight":32.48},{"theme":"food","keyword":"卡娜赫拉","subkeyword":"日本","weight":23.33},{"theme":"food","keyword":"卡娜赫拉","subkeyword":"超狂","weight":19.92},{"theme":"food","keyword":"卡娜赫拉","subkeyword":"20","weight":19.92},{"theme":"food","keyword":"卡娜赫拉","subkeyword":"11","weight":19.92},{"theme":"food","keyword":"卡娜赫拉","subkeyword":"賓士車","weight":19.92},{"theme":"food","keyword":"卡娜赫拉","subkeyword":"CP","weight":19.92},{"theme":"food","keyword":"卡娜赫拉","subkeyword":"2021","weight":19.92},{"theme":"food","keyword":"卡娜赫拉","subkeyword":"卡娜赫拉","weight":19.92},{"theme":"food","keyword":"卡娜赫拉","subkeyword":"商品","weight":18.01},{"theme":"food","keyword":"卡娜赫拉","subkeyword":"牛年","weight":16.16},{"theme":"food","keyword":"卡娜赫拉","subkeyword":"春節","weight":12.57},{"theme":"food","keyword":"科博館","subkeyword":"美食","weight":77.57},{"theme":"food","keyword":"科博館","subkeyword":"韓式","weight":74.48},{"theme":"food","keyword":"科博館","subkeyword":"好吃","weight":71.87},{"theme":"food","keyword":"科博館","subkeyword":"打卡","weight":50.16},{"theme":"food","keyword":"科博館","subkeyword":"起司","weight":45.75},{"theme":"food","keyword":"科博館","subkeyword":"冰花","weight":44.35},{"theme":"food","keyword":"科博館","subkeyword":"牛肉麵","weight":43.13},{"theme":"food","keyword":"科博館","subkeyword":"博館","weight":42.61},{"theme":"food","keyword":"科博館","subkeyword":"銷魂","weight":41.93},{"theme":"food","keyword":"科博館","subkeyword":"鮮蝦","weight":39.11},{"theme":"food","keyword":"科博館","subkeyword":"阿裡郎","weight":38.81},{"theme":"food","keyword":"科博館","subkeyword":"小館","weight":35.8},{"theme":"food","keyword":"科博館","subkeyword":"堅果","weight":34.65},{"theme":"food","keyword":"科博館","subkeyword":"小巷","weight":34.63},{"theme":"food","keyword":"科博館","subkeyword":"炸雞","weight":34.35},{"theme":"food","keyword":"科博館","subkeyword":"中科","weight":33.41},{"theme":"food","keyword":"科博館","subkeyword":"部隊","weight":31.83},{"theme":"food","keyword":"科博館","subkeyword":"臺中","weight":31.1},{"theme":"food","keyword":"科博館","subkeyword":"平價","weight":30.36},{"theme":"food","keyword":"科博館","subkeyword":"彈出","weight":27.36},{"theme":"food","keyword":"科博館","subkeyword":"面家","weight":26.62},{"theme":"food","keyword":"科博館","subkeyword":"限量","weight":26.61},{"theme":"food","keyword":"科博館","subkeyword":"二眷","weight":26.33},{"theme":"food","keyword":"科博館","subkeyword":"餐廳","weight":26.04},{"theme":"food","keyword":"科博館","subkeyword":"肋排","weight":18.11},{"theme":"food","keyword":"科博館","subkeyword":"波波黛莉","weight":18.11},{"theme":"food","keyword":"科博館","subkeyword":"PopDaily","weight":18.11},{"theme":"food","keyword":"科博館","subkeyword":"餃咬開","weight":18.11},{"theme":"food","keyword":"科博館","subkeyword":"面家二眷","weight":18.11},{"theme":"food","keyword":"科博館","subkeyword":"軟嫩","weight":18.11},{"theme":"food","keyword":"科博館","subkeyword":"發胖","weight":14.62},{"theme":"food","keyword":"李芃葳","subkeyword":"原酒","weight":78.92},{"theme":"food","keyword":"李芃葳","subkeyword":"饗宴","weight":54.44},{"theme":"food","keyword":"李芃葳","subkeyword":"中西","weight":54.44},{"theme":"food","keyword":"李芃葳","subkeyword":"港式","weight":48.57},{"theme":"food","keyword":"李芃葳","subkeyword":"懶人","weight":48.14},{"theme":"food","keyword":"李芃葳","subkeyword":"米其林","weight":46.92},{"theme":"food","keyword":"李芃葳","subkeyword":"額滿","weight":46.68},{"theme":"food","keyword":"李芃葳","subkeyword":"圍爐","weight":46.27},{"theme":"food","keyword":"李芃葳","subkeyword":"拚場","weight":45.37},{"theme":"food","keyword":"李芃葳","subkeyword":"講座","weight":43.55},{"theme":"food","keyword":"李芃葳","subkeyword":"禮盒","weight":43.39},{"theme":"food","keyword":"李芃葳","subkeyword":"火鍋","weight":42.9},{"theme":"food","keyword":"李芃葳","subkeyword":"星級","weight":42.89},{"theme":"food","keyword":"李芃葳","subkeyword":"夢幻","weight":34.66},{"theme":"food","keyword":"李芃葳","subkeyword":"外帶","weight":32.83},{"theme":"food","keyword":"李芃葳","subkeyword":"火速","weight":28.44},{"theme":"food","keyword":"李芃葳","subkeyword":"參加","weight":28.3},{"theme":"food","keyword":"李芃葳","subkeyword":"業績","weight":26.98},{"theme":"food","keyword":"李芃葳","subkeyword":"文華","weight":21.99},{"theme":"food","keyword":"李芃葳","subkeyword":"東成西就","weight":21.06},{"theme":"food","keyword":"李芃葳","subkeyword":"8800","weight":18.11},{"theme":"food","keyword":"李芃葳","subkeyword":"最夯","weight":18.11},{"theme":"food","keyword":"李芃葳","subkeyword":"一湯","weight":18.11},{"theme":"food","keyword":"李芃葳","subkeyword":"三菜","weight":18.11},{"theme":"food","keyword":"李芃葳","subkeyword":"27","weight":18.11},{"theme":"food","keyword":"李芃葳","subkeyword":"即贈","weight":18.11},{"theme":"food","keyword":"李芃葳","subkeyword":"冬菇","weight":17.3},{"theme":"food","keyword":"李芃葳","subkeyword":"笑呵呵","weight":16.38},{"theme":"food","keyword":"李芃葳","subkeyword":"左右逢源","weight":16.07},{"theme":"food","keyword":"李芃葳","subkeyword":"名人","weight":13.24},{"theme":"food","keyword":"義大利麵","subkeyword":"情人節","weight":70.82},{"theme":"food","keyword":"義大利麵","subkeyword":"餐廳","weight":70.02},{"theme":"food","keyword":"義大利麵","subkeyword":"食久","weight":66.08},{"theme":"food","keyword":"義大利麵","subkeyword":"文華","weight":65.54},{"theme":"food","keyword":"義大利麵","subkeyword":"美食","weight":62.52},{"theme":"food","keyword":"義大利麵","subkeyword":"寵物","weight":61.34},{"theme":"food","keyword":"義大利麵","subkeyword":"茶室","weight":51.08},{"theme":"food","keyword":"義大利麵","subkeyword":"插畫","weight":47.26},{"theme":"food","keyword":"義大利麵","subkeyword":"品味","weight":45.56},{"theme":"food","keyword":"義大利麵","subkeyword":"臺北","weight":43.68},{"theme":"food","keyword":"義大利麵","subkeyword":"甜蜜","weight":41.26},{"theme":"food","keyword":"義大利麵","subkeyword":"美點","weight":28.46},{"theme":"food","keyword":"義大利麵","subkeyword":"PopDaily","weight":28.46},{"theme":"food","keyword":"義大利麵","subkeyword":"波波黛莉","weight":28.46},{"theme":"food","keyword":"義大利麵","subkeyword":"共度","weight":25.16},{"theme":"food","keyword":"義大利麵","subkeyword":"臺中","weight":24.44},{"theme":"food","keyword":"義大利麵","subkeyword":"繽紛","weight":23.88},{"theme":"food","keyword":"義大利麵","subkeyword":"發胖","weight":22.98},{"theme":"food","keyword":"義大利麵","subkeyword":"友善","weight":22.95},{"theme":"food","keyword":"義大利麵","subkeyword":"東方","weight":14.27},{"theme":"food","keyword":"黃士原","subkeyword":"壽司","weight":73.64},{"theme":"food","keyword":"黃士原","subkeyword":"大葉","weight":70.4},{"theme":"food","keyword":"黃士原","subkeyword":"天母","weight":63.54},{"theme":"food","keyword":"黃士原","subkeyword":"高島","weight":62.07},{"theme":"food","keyword":"黃士原","subkeyword":"庫洛","weight":58.48},{"theme":"food","keyword":"黃士原","subkeyword":"蒸籠","weight":56.18},{"theme":"food","keyword":"黃士原","subkeyword":"桃園","weight":56.1},{"theme":"food","keyword":"黃士原","subkeyword":"大肚","weight":55.49},{"theme":"food","keyword":"黃士原","subkeyword":"魔法","weight":55.24},{"theme":"food","keyword":"黃士原","subkeyword":"上桌","weight":54.06},{"theme":"food","keyword":"黃士原","subkeyword":"動漫","weight":52.89},{"theme":"food","keyword":"黃士原","subkeyword":"插旗","weight":52.37},{"theme":"food","keyword":"黃士原","subkeyword":"點心","weight":50.97},{"theme":"food","keyword":"黃士原","subkeyword":"22","weight":47.82},{"theme":"food","keyword":"黃士原","subkeyword":"主題","weight":46.97},{"theme":"food","keyword":"黃士原","subkeyword":"開跑","weight":42.54},{"theme":"food","keyword":"黃士原","subkeyword":"限期","weight":38.38},{"theme":"food","keyword":"黃士原","subkeyword":"鮭雙享祭","weight":37.37},{"theme":"food","keyword":"黃士原","subkeyword":"買一送一","weight":27.8},{"theme":"food","keyword":"黃士原","subkeyword":"雙享","weight":23.91},{"theme":"food","keyword":"黃士原","subkeyword":"遠百及","weight":23.91},{"theme":"food","keyword":"黃士原","subkeyword":"乙女草莓祭","weight":23.91},{"theme":"food","keyword":"黃士原","subkeyword":"Caf","weight":23.91},{"theme":"food","keyword":"黃士原","subkeyword":"MyAnime","weight":23.91},{"theme":"food","keyword":"黃士原","subkeyword":"登場","weight":16.72},{"theme":"food","keyword":"蕭筠","subkeyword":"有加","weight":75.96},{"theme":"food","keyword":"蕭筠","subkeyword":"紅茶","weight":75.68},{"theme":"food","keyword":"蕭筠","subkeyword":"伯爵","weight":72.83},{"theme":"food","keyword":"蕭筠","subkeyword":"鬆餅","weight":69.71},{"theme":"food","keyword":"蕭筠","subkeyword":"鮮奶","weight":67.79},{"theme":"food","keyword":"蕭筠","subkeyword":"可可","weight":63.81},{"theme":"food","keyword":"蕭筠","subkeyword":"爆漿","weight":63.39},{"theme":"food","keyword":"蕭筠","subkeyword":"微兜","weight":63.28},{"theme":"food","keyword":"蕭筠","subkeyword":"黑糖","weight":61.17},{"theme":"food","keyword":"蕭筠","subkeyword":"珍珠","weight":59.12},{"theme":"food","keyword":"蕭筠","subkeyword":"限時","weight":56.79},{"theme":"food","keyword":"蕭筠","subkeyword":"飲品","weight":53.26},{"theme":"food","keyword":"蕭筠","subkeyword":"回應","weight":46.81},{"theme":"food","keyword":"蕭筠","subkeyword":"回來","weight":35.54},{"theme":"food","keyword":"蕭筠","subkeyword":"瓦帕","weight":33.21},{"theme":"food","keyword":"蕭筠","subkeyword":"迷客","weight":33.21},{"theme":"food","keyword":"蕭筠","subkeyword":"客夏","weight":26.25},{"theme":"food","keyword":"蕭筠","subkeyword":"竟然","weight":16.65},{"theme":"food","keyword":"蕭筠","subkeyword":"得到","weight":12.8},{"theme":"food","keyword":"歐盟","subkeyword":"黑糖","weight":110.04},{"theme":"food","keyword":"歐盟","subkeyword":"紅茶","weight":104.98},{"theme":"food","keyword":"歐盟","subkeyword":"鮮奶","weight":103.15},{"theme":"food","keyword":"歐盟","subkeyword":"珍珠","weight":92.97},{"theme":"food","keyword":"歐盟","subkeyword":"迷客","weight":70.32},{"theme":"food","keyword":"歐盟","subkeyword":"回應","weight":69.85},{"theme":"food","keyword":"歐盟","subkeyword":"有加","weight":53.84},{"theme":"food","keyword":"歐盟","subkeyword":"飲品","weight":44.89},{"theme":"food","keyword":"歐盟","subkeyword":"竟然","weight":35.26},{"theme":"food","keyword":"歐盟","subkeyword":"客夏","weight":26.17},{"theme":"food","keyword":"麥當勞","subkeyword":"有加","weight":68.69},{"theme":"food","keyword":"麥當勞","subkeyword":"紅茶","weight":68.41},{"theme":"food","keyword":"麥當勞","subkeyword":"伯爵","weight":66.29},{"theme":"food","keyword":"麥當勞","subkeyword":"鮮奶","weight":59.22},{"theme":"food","keyword":"麥當勞","subkeyword":"鬆餅","weight":58.9},{"theme":"food","keyword":"麥當勞","subkeyword":"可可","weight":57.02},{"theme":"food","keyword":"麥當勞","subkeyword":"爆漿","weight":54.09},{"theme":"food","keyword":"麥當勞","subkeyword":"微兜","weight":53.99},{"theme":"food","keyword":"麥當勞","subkeyword":"珍珠","weight":52.91},{"theme":"food","keyword":"麥當勞","subkeyword":"黑糖","weight":51.21},{"theme":"food","keyword":"麥當勞","subkeyword":"限時","weight":48.04},{"theme":"food","keyword":"麥當勞","subkeyword":"飲品","weight":45.49},{"theme":"food","keyword":"麥當勞","subkeyword":"回應","weight":41.01},{"theme":"food","keyword":"麥當勞","subkeyword":"回來","weight":31.59},{"theme":"food","keyword":"麥當勞","subkeyword":"披薩","weight":27.8},{"theme":"food","keyword":"麥當勞","subkeyword":"客夏","weight":26.25},{"theme":"food","keyword":"麥當勞","subkeyword":"199","weight":23.91},{"theme":"food","keyword":"麥當勞","subkeyword":"PLU","weight":23.91},{"theme":"food","keyword":"麥當勞","subkeyword":"迷客","weight":23.91},{"theme":"food","keyword":"麥當勞","subkeyword":"瓦帕","weight":23.91},{"theme":"food","keyword":"麥當勞","subkeyword":"拿坡里","weight":23.91},{"theme":"food","keyword":"麥當勞","subkeyword":"炸雞腿","weight":23.91},{"theme":"food","keyword":"麥當勞","subkeyword":"21","weight":23.91},{"theme":"food","keyword":"麥當勞","subkeyword":"情報","weight":15.16},{"theme":"food","keyword":"麥當勞","subkeyword":"竟然","weight":11.99},{"theme":"food","keyword":"麥當勞","subkeyword":"得到","weight":9.22},{"theme":"food","keyword":"沙拉","subkeyword":"天菜","weight":120.32},{"theme":"food","keyword":"沙拉","subkeyword":"信義","weight":50.19},{"theme":"food","keyword":"沙拉","subkeyword":"店員","weight":49.4},{"theme":"food","keyword":"沙拉","subkeyword":"臺北","weight":44.95},{"theme":"food","keyword":"沙拉","subkeyword":"Tie","weight":35.16},{"theme":"food","keyword":"沙拉","subkeyword":"Food","weight":35.16},{"theme":"food","keyword":"沙拉","subkeyword":"PopDaily","weight":35.16},{"theme":"food","keyword":"沙拉","subkeyword":"波波黛莉","weight":35.16},{"theme":"food","keyword":"沙拉","subkeyword":"大家","weight":34.72},{"theme":"food","keyword":"沙拉","subkeyword":"食物","weight":29.96},{"theme":"food","keyword":"沙拉","subkeyword":"發胖","weight":28.39},{"theme":"food","keyword":"沙拉","subkeyword":"之外","weight":17.28},{"theme":"food","keyword":"沙拉","subkeyword":"除了","weight":15.16},{"theme":"food","keyword":"沙拉","subkeyword":"選擇","weight":15.15},{"theme":"food","keyword":"沙拉","subkeyword":"問題","weight":11.66},{"theme":"food","keyword":"信義安和站","subkeyword":"美食","weight":87.9},{"theme":"food","keyword":"信義安和站","subkeyword":"臺北","weight":69.58},{"theme":"food","keyword":"信義安和站","subkeyword":"義大利","weight":62.41},{"theme":"food","keyword":"信義安和站","subkeyword":"主廚","weight":59.3},{"theme":"food","keyword":"信義安和站","subkeyword":"萌系","weight":58.36},{"theme":"food","keyword":"信義安和站","subkeyword":"掌燒","weight":58.07},{"theme":"food","keyword":"信義安和站","subkeyword":"甜點","weight":56.26},{"theme":"food","keyword":"信義安和站","subkeyword":"大安","weight":52.62},{"theme":"food","keyword":"信義安和站","subkeyword":"PopDaily","weight":49.81},{"theme":"food","keyword":"信義安和站","subkeyword":"波波黛莉","weight":49.81},{"theme":"food","keyword":"信義安和站","subkeyword":"發胖","weight":40.22},{"theme":"food","keyword":"信義安和站","subkeyword":"食記","weight":39.08},{"theme":"food","keyword":"信義安和站","subkeyword":"披薩","weight":28.96},{"theme":"food","keyword":"信義安和站","subkeyword":"FOX","weight":24.91},{"theme":"food","keyword":"信義安和站","subkeyword":"Catpaw","weight":24.91},{"theme":"food","keyword":"信義安和站","subkeyword":"通化夜市","weight":24.91},{"theme":"food","keyword":"信義安和站","subkeyword":"TAMED","weight":24.91},{"theme":"food","keyword":"信義安和站","subkeyword":"酥脆","weight":22.62},{"theme":"food","keyword":"信義安和站","subkeyword":"比薩","weight":20.26},{"theme":"food","keyword":"台中大遠百","subkeyword":"燒肉","weight":77.11},{"theme":"food","keyword":"台中大遠百","subkeyword":"日本","weight":67.88},{"theme":"food","keyword":"台中大遠百","subkeyword":"咖啡廳","weight":55.32},{"theme":"food","keyword":"台中大遠百","subkeyword":"喧囂","weight":50.19},{"theme":"food","keyword":"台中大遠百","subkeyword":"三樓","weight":49.65},{"theme":"food","keyword":"台中大遠百","subkeyword":"臺中","weight":48.87},{"theme":"food","keyword":"台中大遠百","subkeyword":"遠離","weight":47.74},{"theme":"food","keyword":"台中大遠百","subkeyword":"咖啡","weight":42.17},{"theme":"food","keyword":"台中大遠百","subkeyword":"食記","weight":42.14},{"theme":"food","keyword":"台中大遠百","subkeyword":"城市","weight":40.02},{"theme":"food","keyword":"台中大遠百","subkeyword":"搶吃","weight":38.18},{"theme":"food","keyword":"台中大遠百","subkeyword":"和牛","weight":35.87},{"theme":"food","keyword":"台中大遠百","subkeyword":"祭出","weight":33.21},{"theme":"food","keyword":"台中大遠百","subkeyword":"買一送一","weight":33.1},{"theme":"food","keyword":"台中大遠百","subkeyword":"控吃","weight":29.16},{"theme":"food","keyword":"台中大遠百","subkeyword":"伴日","weight":28.46},{"theme":"food","keyword":"台中大遠百","subkeyword":"牛角","weight":25.75},{"theme":"food","keyword":"台中大遠百","subkeyword":"好吃","weight":24.52},{"theme":"food","keyword":"台中大遠百","subkeyword":"甜點","weight":21.52},{"theme":"food","keyword":"台中大遠百","subkeyword":"優惠","weight":21.49},{"theme":"food","keyword":"台中大遠百","subkeyword":"PopDaily","weight":14.23},{"theme":"food","keyword":"台中大遠百","subkeyword":"A4","weight":14.23},{"theme":"food","keyword":"台中大遠百","subkeyword":"波波黛莉","weight":14.23},{"theme":"food","keyword":"台中大遠百","subkeyword":"發胖","weight":11.49},{"theme":"food","keyword":"台中大遠百","subkeyword":"專賣店","weight":11.15},{"theme":"food","keyword":"台中大遠百","subkeyword":"一個月","weight":7.81},{"theme":"food","keyword":"台灣大道","subkeyword":"咖啡廳","weight":109.73},{"theme":"food","keyword":"台灣大道","subkeyword":"喧囂","weight":99.01},{"theme":"food","keyword":"台灣大道","subkeyword":"三樓","weight":97.95},{"theme":"food","keyword":"台灣大道","subkeyword":"遠離","weight":92.25},{"theme":"food","keyword":"台灣大道","subkeyword":"食記","weight":88.84},{"theme":"food","keyword":"台灣大道","subkeyword":"城市","weight":75.19},{"theme":"food","keyword":"台灣大道","subkeyword":"伴日","weight":66.42},{"theme":"food","keyword":"台灣大道","subkeyword":"咖啡","weight":65.41},{"theme":"food","keyword":"台灣大道","subkeyword":"臺中","weight":57.02},{"theme":"food","keyword":"新光三越","subkeyword":"咖啡廳","weight":89.94},{"theme":"food","keyword":"新光三越","subkeyword":"喧囂","weight":81.74},{"theme":"food","keyword":"新光三越","subkeyword":"三樓","weight":80.9},{"theme":"food","keyword":"新光三越","subkeyword":"遠離","weight":78.17},{"theme":"food","keyword":"新光三越","subkeyword":"咖啡","weight":68.42},{"theme":"food","keyword":"新光三越","subkeyword":"食記","weight":66.83},{"theme":"food","keyword":"新光三越","subkeyword":"城市","weight":65.93},{"theme":"food","keyword":"新光三越","subkeyword":"福袋","weight":64.1},{"theme":"food","keyword":"新光三越","subkeyword":"全台","weight":59.73},{"theme":"food","keyword":"新光三越","subkeyword":"新春","weight":58.15},{"theme":"food","keyword":"新光三越","subkeyword":"整理","weight":53.46},{"theme":"food","keyword":"新光三越","subkeyword":"伴日","weight":44.28},{"theme":"food","keyword":"新光三越","subkeyword":"臺中","weight":38.01},{"theme":"food","keyword":"新光三越","subkeyword":"全家","weight":37.11},{"theme":"food","keyword":"新光三越","subkeyword":"2021","weight":22.14},{"theme":"food","keyword":"新光三越","subkeyword":"CP","weight":22.14},{"theme":"food","keyword":"新光三越","subkeyword":"賓士車","weight":22.14},{"theme":"food","keyword":"新光三越","subkeyword":"最高","weight":9.52},{"theme":"food","keyword":"文山草堂","subkeyword":"菜單","weight":117.75},{"theme":"food","keyword":"文山草堂","subkeyword":"平價","weight":111.17},{"theme":"food","keyword":"文山草堂","subkeyword":"料理","weight":105.41},{"theme":"food","keyword":"文山草堂","subkeyword":"食記","weight":79.7},{"theme":"food","keyword":"文山草堂","subkeyword":"新北石碇","weight":79.7},{"theme":"food","keyword":"文山草堂","subkeyword":"文山草堂","weight":79.7},{"theme":"food","keyword":"文山草堂","subkeyword":"Fw","weight":39.85},{"theme":"food","keyword":"文山草堂","subkeyword":"真正","weight":35.31},{"theme":"food","keyword":"迪士尼","subkeyword":"禮盒","weight":86.45},{"theme":"food","keyword":"迪士尼","subkeyword":"福袋","weight":76.01},{"theme":"food","keyword":"迪士尼","subkeyword":"小物","weight":75.84},{"theme":"food","keyword":"迪士尼","subkeyword":"可愛","weight":63.33},{"theme":"food","keyword":"迪士尼","subkeyword":"全家","weight":60.09},{"theme":"food","keyword":"迪士尼","subkeyword":"授權","weight":58.67},{"theme":"food","keyword":"迪士尼","subkeyword":"公仔","weight":51.15},{"theme":"food","keyword":"迪士尼","subkeyword":"物桶","weight":47.67},{"theme":"food","keyword":"迪士尼","subkeyword":"三麗鷗","weight":47.54},{"theme":"food","keyword":"迪士尼","subkeyword":"限定","weight":46.2},{"theme":"food","keyword":"迪士尼","subkeyword":"獨家","weight":45.41},{"theme":"food","keyword":"迪士尼","subkeyword":"商品","weight":40.22},{"theme":"food","keyword":"迪士尼","subkeyword":"日本","weight":34.8},{"theme":"food","keyword":"迪士尼","subkeyword":"卡娜赫拉","weight":22.14},{"theme":"food","keyword":"迪士尼","subkeyword":"20","weight":22.14},{"theme":"food","keyword":"迪士尼","subkeyword":"11","weight":22.14},{"theme":"food","keyword":"迪士尼","subkeyword":"金牛福袋","weight":22.14},{"theme":"food","keyword":"迪士尼","subkeyword":"超狂","weight":22.14},{"theme":"food","keyword":"迪士尼","subkeyword":"牛年","weight":17.96},{"theme":"food","keyword":"迪士尼","subkeyword":"春節","weight":13.97},{"theme":"food","keyword":"中山店","subkeyword":"板橋","weight":75.13},{"theme":"food","keyword":"中山店","subkeyword":"燒肉","weight":53.63},{"theme":"food","keyword":"中山店","subkeyword":"臺北","weight":38.95},{"theme":"food","keyword":"中山店","subkeyword":"買一送一","weight":34.75},{"theme":"food","keyword":"中山店","subkeyword":"日本","weight":33.62},{"theme":"food","keyword":"中山店","subkeyword":"福袋","weight":33.22},{"theme":"food","keyword":"中山店","subkeyword":"和牛","weight":28.5},{"theme":"food","keyword":"中山店","subkeyword":"全品","weight":27.89},{"theme":"food","keyword":"中山店","subkeyword":"火味","weight":27.58},{"theme":"food","keyword":"中山店","subkeyword":"點爭","weight":26.38},{"theme":"food","keyword":"中山店","subkeyword":"王沖","weight":25.63},{"theme":"food","keyword":"中山店","subkeyword":"整理","weight":23.13},{"theme":"food","keyword":"中山店","subkeyword":"吐司","weight":22.01},{"theme":"food","keyword":"中山店","subkeyword":"加碼","weight":21.58},{"theme":"food","keyword":"中山店","subkeyword":"限定","weight":21.1},{"theme":"food","keyword":"中山店","subkeyword":"首創","weight":20.83},{"theme":"food","keyword":"中山店","subkeyword":"早餐","weight":19.94},{"theme":"food","keyword":"中山店","subkeyword":"推薦","weight":19.88},{"theme":"food","keyword":"中山店","subkeyword":"中山","weight":19.74},{"theme":"food","keyword":"中山店","subkeyword":"飲品","weight":19.69},{"theme":"food","keyword":"中山店","subkeyword":"甜點","weight":19.63},{"theme":"food","keyword":"中山店","subkeyword":"新春","weight":17.55},{"theme":"food","keyword":"中山店","subkeyword":"全台","weight":17.42},{"theme":"food","keyword":"中山店","subkeyword":"四平","weight":16.77},{"theme":"food","keyword":"中山店","subkeyword":"商圈","weight":16.72},{"theme":"food","keyword":"中山店","subkeyword":"好吃","weight":16.39},{"theme":"food","keyword":"中山店","subkeyword":"壽司","weight":15.96},{"theme":"food","keyword":"中山店","subkeyword":"搶吃","weight":10.67},{"theme":"food","keyword":"中山店","subkeyword":"PopDaily","weight":9.96},{"theme":"food","keyword":"中山店","subkeyword":"Kiwes","weight":9.96},{"theme":"food","keyword":"中山店","subkeyword":"50","weight":9.96},{"theme":"food","keyword":"中山店","subkeyword":"鮮大胃","weight":9.96},{"theme":"food","keyword":"中山店","subkeyword":"Toast","weight":9.96},{"theme":"food","keyword":"中山店","subkeyword":"大胃","weight":9.96},{"theme":"food","keyword":"中山店","subkeyword":"控吃","weight":9.96},{"theme":"food","keyword":"中山店","subkeyword":"A4","weight":9.96},{"theme":"food","keyword":"中山店","subkeyword":"賓士車","weight":9.96},{"theme":"food","keyword":"中山店","subkeyword":"CP","weight":9.96},{"theme":"food","keyword":"中山店","subkeyword":"Coffee","weight":9.96},{"theme":"food","keyword":"中山店","subkeyword":"2021","weight":9.96},{"theme":"food","keyword":"中山店","subkeyword":"波波黛莉","weight":9.96},{"theme":"food","keyword":"中山店","subkeyword":"中山店","weight":9.96},{"theme":"food","keyword":"陳倍玉","subkeyword":"禮盒","weight":87.85},{"theme":"food","keyword":"陳倍玉","subkeyword":"霜淇淋","weight":60.75},{"theme":"food","keyword":"陳倍玉","subkeyword":"草莓","weight":56.0},{"theme":"food","keyword":"陳倍玉","subkeyword":"重乳","weight":53.27},{"theme":"food","keyword":"陳倍玉","subkeyword":"公仔","weight":52.02},{"theme":"food","keyword":"陳倍玉","subkeyword":"加碼","weight":48.89},{"theme":"food","keyword":"陳倍玉","subkeyword":"物桶","weight":48.4},{"theme":"food","keyword":"陳倍玉","subkeyword":"三麗鷗","weight":48.27},{"theme":"food","keyword":"陳倍玉","subkeyword":"限定","weight":46.71},{"theme":"food","keyword":"陳倍玉","subkeyword":"獨家","weight":45.9},{"theme":"food","keyword":"陳倍玉","subkeyword":"咖啡","weight":45.36},{"theme":"food","keyword":"陳倍玉","subkeyword":"限時","weight":44.73},{"theme":"food","keyword":"陳倍玉","subkeyword":"回歸","weight":42.71},{"theme":"food","keyword":"陳倍玉","subkeyword":"全家","weight":37.69},{"theme":"food","keyword":"陳倍玉","subkeyword":"日本","weight":35.04},{"theme":"food","keyword":"陳倍玉","subkeyword":"第二杯","weight":23.29},{"theme":"food","keyword":"陳倍玉","subkeyword":"超狂","weight":22.99},{"theme":"food","keyword":"陳倍玉","subkeyword":"20","weight":22.99},{"theme":"food","keyword":"陳倍玉","subkeyword":"11","weight":22.99},{"theme":"food","keyword":"陳倍玉","subkeyword":"59","weight":22.99},{"theme":"food","keyword":"陳倍玉","subkeyword":"皮美翻","weight":22.99},{"theme":"food","keyword":"陳倍玉","subkeyword":"卡娜赫拉","weight":22.99},{"theme":"food","keyword":"陳倍玉","subkeyword":"粉色","weight":19.37},{"theme":"food","keyword":"陳倍玉","subkeyword":"牛年","weight":18.65},{"theme":"food","keyword":"陳倍玉","subkeyword":"春節","weight":14.51},{"theme":"food","keyword":"林沛縈","subkeyword":"香芋","weight":62.3},{"theme":"food","keyword":"林沛縈","subkeyword":"黃景","weight":58.07},{"theme":"food","keyword":"林沛縈","subkeyword":"台菜","weight":56.78},{"theme":"food","keyword":"林沛縈","subkeyword":"炊粉","weight":54.43},{"theme":"food","keyword":"林沛縈","subkeyword":"龍端","weight":54.07},{"theme":"food","keyword":"林沛縈","subkeyword":"金鯧","weight":53.76},{"theme":"food","keyword":"林沛縈","subkeyword":"懶人","weight":52.0},{"theme":"food","keyword":"林沛縈","subkeyword":"港式","weight":51.55},{"theme":"food","keyword":"林沛縈","subkeyword":"米其林","weight":50.19},{"theme":"food","keyword":"林沛縈","subkeyword":"中西","weight":50.0},{"theme":"food","keyword":"林沛縈","subkeyword":"蒸雞","weight":49.99},{"theme":"food","keyword":"林沛縈","subkeyword":"圍爐","weight":49.57},{"theme":"food","keyword":"林沛縈","subkeyword":"拚場","weight":48.39},{"theme":"food","keyword":"林沛縈","subkeyword":"冠軍","weight":38.58},{"theme":"food","keyword":"林沛縈","subkeyword":"冷凍","weight":35.54},{"theme":"food","keyword":"林沛縈","subkeyword":"禮盒","weight":34.94},{"theme":"food","keyword":"林沛縈","subkeyword":"火鍋","weight":34.81},{"theme":"food","keyword":"林沛縈","subkeyword":"糯米","weight":34.79},{"theme":"food","keyword":"林沛縈","subkeyword":"星級","weight":34.67},{"theme":"food","keyword":"林沛縈","subkeyword":"加菜","weight":34.14},{"theme":"food","keyword":"林沛縈","subkeyword":"外帶","weight":33.77},{"theme":"food","keyword":"林沛縈","subkeyword":"業績","weight":33.1},{"theme":"food","keyword":"林沛縈","subkeyword":"婆媽","weight":31.24},{"theme":"food","keyword":"林沛縈","subkeyword":"王子","weight":26.88},{"theme":"food","keyword":"林沛縈","subkeyword":"東成西就","weight":17.38},{"theme":"food","keyword":"林沛縈","subkeyword":"一湯","weight":14.94},{"theme":"food","keyword":"林沛縈","subkeyword":"三菜","weight":14.94},{"theme":"food","keyword":"林沛縈","subkeyword":"年味","weight":14.94},{"theme":"food","keyword":"林沛縈","subkeyword":"煮婦","weight":14.94},{"theme":"food","keyword":"林沛縈","subkeyword":"hen","weight":14.94},{"theme":"food","keyword":"林沛縈","subkeyword":"最夯","weight":14.94},{"theme":"food","keyword":"林沛縈","subkeyword":"冬菇","weight":14.27},{"theme":"food","keyword":"林沛縈","subkeyword":"笑呵呵","weight":13.51},{"theme":"food","keyword":"林沛縈","subkeyword":"速成","weight":13.3},{"theme":"food","keyword":"好市多","subkeyword":"冷凍","weight":71.04},{"theme":"food","keyword":"好市多","subkeyword":"霜淇淋","weight":70.42},{"theme":"food","keyword":"好市多","subkeyword":"麻辣鍋","weight":68.2},{"theme":"food","keyword":"好市多","subkeyword":"草莓","weight":64.83},{"theme":"food","keyword":"好市多","subkeyword":"重乳","weight":62.08},{"theme":"food","keyword":"好市多","subkeyword":"青花","weight":58.78},{"theme":"food","keyword":"好市多","subkeyword":"加碼","weight":56.92},{"theme":"food","keyword":"好市多","subkeyword":"咖啡","weight":52.74},{"theme":"food","keyword":"好市多","subkeyword":"限時","weight":52.47},{"theme":"food","keyword":"好市多","subkeyword":"經典","weight":52.41},{"theme":"food","keyword":"好市多","subkeyword":"回歸","weight":49.63},{"theme":"food","keyword":"好市多","subkeyword":"全家","weight":44.17},{"theme":"food","keyword":"好市多","subkeyword":"購物","weight":33.05},{"theme":"food","keyword":"好市多","subkeyword":"第二杯","weight":27.52},{"theme":"food","keyword":"好市多","subkeyword":"59","weight":27.17},{"theme":"food","keyword":"好市多","subkeyword":"皮美翻","weight":27.17},{"theme":"food","keyword":"好市多","subkeyword":"波波黛莉","weight":27.17},{"theme":"food","keyword":"好市多","subkeyword":"PopDaily","weight":27.17},{"theme":"food","keyword":"好市多","subkeyword":"王品","weight":27.17},{"theme":"food","keyword":"好市多","subkeyword":"好市多","weight":27.17},{"theme":"food","keyword":"好市多","subkeyword":"粉色","weight":22.89},{"theme":"food","keyword":"好市多","subkeyword":"發胖","weight":21.94},{"theme":"food","keyword":"萊爾富","subkeyword":"霜淇淋","weight":83.21},{"theme":"food","keyword":"萊爾富","subkeyword":"草莓","weight":76.41},{"theme":"food","keyword":"萊爾富","subkeyword":"重乳","weight":73.31},{"theme":"food","keyword":"萊爾富","subkeyword":"加碼","weight":67.01},{"theme":"food","keyword":"萊爾富","subkeyword":"咖啡","weight":61.88},{"theme":"food","keyword":"萊爾富","subkeyword":"限時","weight":61.83},{"theme":"food","keyword":"萊爾富","subkeyword":"回歸","weight":58.11},{"theme":"food","keyword":"萊爾富","subkeyword":"全家","weight":51.71},{"theme":"food","keyword":"萊爾富","subkeyword":"第二杯","weight":33.64},{"theme":"food","keyword":"萊爾富","subkeyword":"年福袋","weight":33.21},{"theme":"food","keyword":"萊爾富","subkeyword":"...","weight":33.21},{"theme":"food","keyword":"萊爾富","subkeyword":"皮美翻","weight":33.21},{"theme":"food","keyword":"萊爾富","subkeyword":"59","weight":33.21},{"theme":"food","keyword":"萊爾富","subkeyword":"2021","weight":33.21},{"theme":"food","keyword":"萊爾富","subkeyword":"萊爾","weight":31.09},{"theme":"food","keyword":"萊爾富","subkeyword":"平平淡淡","weight":30.91},{"theme":"food","keyword":"萊爾富","subkeyword":"粉色","weight":27.98},{"theme":"food","keyword":"萊爾富","subkeyword":"商品","weight":14.68},{"theme":"food","keyword":"google","subkeyword":"懷舊","weight":76.84},{"theme":"food","keyword":"google","subkeyword":"老屋","weight":76.16},{"theme":"food","keyword":"google","subkeyword":"食記","weight":73.3},{"theme":"food","keyword":"google","subkeyword":"菜單","weight":63.03},{"theme":"food","keyword":"google","subkeyword":"料理","weight":57.93},{"theme":"food","keyword":"google","subkeyword":"平價","weight":52.79},{"theme":"food","keyword":"google","subkeyword":"桃園","weight":43.29},{"theme":"food","keyword":"google","subkeyword":"下午茶","weight":43.04},{"theme":"food","keyword":"google","subkeyword":"體驗","weight":38.54},{"theme":"food","keyword":"google","subkeyword":"肉鬆","weight":37.99},{"theme":"food","keyword":"google","subkeyword":"咖啡廳","weight":37.57},{"theme":"food","keyword":"google","subkeyword":"木造","weight":35.82},{"theme":"food","keyword":"google","subkeyword":"新北石碇","weight":32.31},{"theme":"food","keyword":"google","subkeyword":"文山草堂","weight":32.31},{"theme":"food","keyword":"google","subkeyword":"住宿","weight":29.69},{"theme":"food","keyword":"google","subkeyword":"嘉義","weight":28.18},{"theme":"food","keyword":"google","subkeyword":"享受","weight":27.88},{"theme":"food","keyword":"google","subkeyword":"新家","weight":22.15},{"theme":"food","keyword":"google","subkeyword":"新家香","weight":16.16},{"theme":"food","keyword":"google","subkeyword":"波波黛莉","weight":16.16},{"theme":"food","keyword":"google","subkeyword":"PopDaily","weight":16.16},{"theme":"food","keyword":"google","subkeyword":"70","weight":16.16},{"theme":"food","keyword":"google","subkeyword":"Fw","weight":16.16},{"theme":"food","keyword":"google","subkeyword":"真正","weight":14.31},{"theme":"food","keyword":"google","subkeyword":"發胖","weight":13.04},{"theme":"food","keyword":"google","subkeyword":"搖身一變","weight":12.33},{"theme":"food","keyword":"google","subkeyword":"不論是","weight":11.05},{"theme":"food","keyword":"Iacopo Frassi","subkeyword":"原酒","weight":86.88},{"theme":"food","keyword":"Iacopo Frassi","subkeyword":"文華","weight":84.75},{"theme":"food","keyword":"Iacopo Frassi","subkeyword":"饗宴","weight":66.23},{"theme":"food","keyword":"Iacopo Frassi","subkeyword":"額滿","weight":55.97},{"theme":"food","keyword":"Iacopo Frassi","subkeyword":"情人節","weight":48.65},{"theme":"food","keyword":"Iacopo Frassi","subkeyword":"火速","weight":47.92},{"theme":"food","keyword":"Iacopo Frassi","subkeyword":"講座","weight":47.79},{"theme":"food","keyword":"Iacopo Frassi","subkeyword":"參加","weight":41.35},{"theme":"food","keyword":"Iacopo Frassi","subkeyword":"夢幻","weight":39.47},{"theme":"food","keyword":"Iacopo Frassi","subkeyword":"臺北","weight":37.91},{"theme":"food","keyword":"Iacopo Frassi","subkeyword":"甜蜜","weight":36.1},{"theme":"food","keyword":"Iacopo Frassi","subkeyword":"品味","weight":34.37},{"theme":"food","keyword":"Iacopo Frassi","subkeyword":"東方","weight":24.98},{"theme":"food","keyword":"Iacopo Frassi","subkeyword":"即贈","weight":24.91},{"theme":"food","keyword":"Iacopo Frassi","subkeyword":"8800","weight":24.91},{"theme":"food","keyword":"Iacopo Frassi","subkeyword":"27","weight":24.91},{"theme":"food","keyword":"Iacopo Frassi","subkeyword":"美點","weight":24.91},{"theme":"food","keyword":"Iacopo Frassi","subkeyword":"共度","weight":22.02},{"theme":"food","keyword":"Iacopo Frassi","subkeyword":"繽紛","weight":20.89},{"theme":"food","keyword":"Iacopo Frassi","subkeyword":"單一","weight":14.91},{"theme":"food","keyword":"7-ELEVEN","subkeyword":"禮盒","weight":117.09},{"theme":"food","keyword":"7-ELEVEN","subkeyword":"限定","weight":77.63},{"theme":"food","keyword":"7-ELEVEN","subkeyword":"新春","weight":53.63},{"theme":"food","keyword":"7-ELEVEN","subkeyword":"酒廠","weight":53.58},{"theme":"food","keyword":"7-ELEVEN","subkeyword":"搶市","weight":50.11},{"theme":"food","keyword":"7-ELEVEN","subkeyword":"公仔","weight":49.73},{"theme":"food","keyword":"7-ELEVEN","subkeyword":"物桶","weight":45.39},{"theme":"food","keyword":"7-ELEVEN","subkeyword":"三麗鷗","weight":45.31},{"theme":"food","keyword":"7-ELEVEN","subkeyword":"買氣","weight":44.73},{"theme":"food","keyword":"7-ELEVEN","subkeyword":"包裝","weight":39.9},{"theme":"food","keyword":"7-ELEVEN","subkeyword":"日本","weight":29.6},{"theme":"food","keyword":"7-ELEVEN","subkeyword":"獨家","weight":28.24},{"theme":"food","keyword":"7-ELEVEN","subkeyword":"超狂","weight":27.17},{"theme":"food","keyword":"7-ELEVEN","subkeyword":"20","weight":27.17},{"theme":"food","keyword":"7-ELEVEN","subkeyword":"卡娜赫拉","weight":27.17},{"theme":"food","keyword":"7-ELEVEN","subkeyword":"11","weight":27.17},{"theme":"food","keyword":"7-ELEVEN","subkeyword":"年節","weight":22.61},{"theme":"food","keyword":"7-ELEVEN","subkeyword":"牛年","weight":22.04},{"theme":"food","keyword":"7-ELEVEN","subkeyword":"春節","weight":17.14},{"theme":"food","keyword":"台北","subkeyword":"臺北","weight":64.06},{"theme":"food","keyword":"台北","subkeyword":"美食","weight":34.92},{"theme":"food","keyword":"台北","subkeyword":"PopDaily","weight":20.83},{"theme":"food","keyword":"台北","subkeyword":"波波黛莉","weight":20.83},{"theme":"food","keyword":"台北","subkeyword":"食記","weight":17.69},{"theme":"food","keyword":"台北","subkeyword":"發胖","weight":16.82},{"theme":"food","keyword":"台北","subkeyword":"禮盒","weight":13.07},{"theme":"food","keyword":"台北","subkeyword":"外帶","weight":11.91},{"theme":"food","keyword":"台北","subkeyword":"中山","weight":11.57},{"theme":"food","keyword":"台北","subkeyword":"壽司","weight":11.2},{"theme":"food","keyword":"台北","subkeyword":"燒肉","weight":10.48},{"theme":"food","keyword":"台北","subkeyword":"下午茶","weight":10.21},{"theme":"food","keyword":"台北","subkeyword":"推薦","weight":10.02},{"theme":"food","keyword":"台北","subkeyword":"日本","weight":9.78},{"theme":"food","keyword":"台北","subkeyword":"炸雞","weight":9.36},{"theme":"food","keyword":"台北","subkeyword":"國賓","weight":9.31},{"theme":"food","keyword":"台北","subkeyword":"米其林","weight":9.29},{"theme":"food","keyword":"台北","subkeyword":"火鍋","weight":8.9},{"theme":"food","keyword":"台北","subkeyword":"咖啡","weight":7.78},{"theme":"food","keyword":"台北","subkeyword":"麻辣鍋","weight":7.78},{"theme":"food","keyword":"台北","subkeyword":"紅茶","weight":7.27},{"theme":"food","keyword":"台北","subkeyword":"口味","weight":6.77},{"theme":"food","keyword":"台北","subkeyword":"限量","weight":6.41},{"theme":"food","keyword":"台北","subkeyword":"情人節","weight":6.19},{"theme":"food","keyword":"台北","subkeyword":"國王","weight":6.14},{"theme":"food","keyword":"台北","subkeyword":"強勢","weight":6.11},{"theme":"food","keyword":"台北","subkeyword":"料理","weight":6.0},{"theme":"food","keyword":"台北","subkeyword":"巷弄","weight":6.0},{"theme":"food","keyword":"台北","subkeyword":"吐司","weight":3.07},{"theme":"food","keyword":"台北","subkeyword":"LA","weight":2.78},{"theme":"food","keyword":"台北","subkeyword":"新北","weight":2.78},{"theme":"food","keyword":"台北","subkeyword":"板橋","weight":2.33},{"theme":"food","keyword":"台北","subkeyword":"元起","weight":2.08},{"theme":"food","keyword":"台北","subkeyword":"天母","weight":1.53},{"theme":"food","keyword":"台北","subkeyword":"甜蜜","weight":1.51},{"theme":"food","keyword":"台北","subkeyword":"黑糖","weight":1.49},{"theme":"food","keyword":"國父紀念館站","subkeyword":"牛船","weight":71.35},{"theme":"food","keyword":"國父紀念館站","subkeyword":"靜岡","weight":69.06},{"theme":"food","keyword":"國父紀念館站","subkeyword":"部位","weight":61.17},{"theme":"food","keyword":"國父紀念館站","subkeyword":"京昌園","weight":60.03},{"theme":"food","keyword":"國父紀念館站","subkeyword":"美食","weight":59.19},{"theme":"food","keyword":"國父紀念館站","subkeyword":"燒肉","weight":56.62},{"theme":"food","keyword":"國父紀念館站","subkeyword":"入港","weight":56.61},{"theme":"food","keyword":"國父紀念館站","subkeyword":"高品質","weight":56.12},{"theme":"food","keyword":"國父紀念館站","subkeyword":"老店","weight":54.7},{"theme":"food","keyword":"國父紀念館站","subkeyword":"牛肉","weight":54.04},{"theme":"food","keyword":"國父紀念館站","subkeyword":"波波黛莉","weight":42.7},{"theme":"food","keyword":"國父紀念館站","subkeyword":"PopDaily","weight":42.7},{"theme":"food","keyword":"國父紀念館站","subkeyword":"滿足","weight":37.9},{"theme":"food","keyword":"國父紀念館站","subkeyword":"發胖","weight":34.47},{"theme":"food","keyword":"國父紀念館站","subkeyword":"臺北","weight":31.86},{"theme":"food","keyword":"國父紀念館站","subkeyword":"糖思","weight":21.35},{"theme":"food","keyword":"國父紀念館站","subkeyword":"Miss","weight":21.35},{"theme":"food","keyword":"國父紀念館站","subkeyword":"Sugar","weight":21.35},{"theme":"food","keyword":"國父紀念館站","subkeyword":"食記","weight":21.35},{"theme":"food","keyword":"國父紀念館站","subkeyword":"60","weight":21.35},{"theme":"food","keyword":"國父紀念館站","subkeyword":"念念不忘","weight":17.26},{"theme":"food","keyword":"國父紀念館站","subkeyword":"美味","weight":16.02},{"theme":"food","keyword":"國父紀念館站","subkeyword":"令人","weight":11.25},{"theme":"food","keyword":"國父紀念館站","subkeyword":"多種","weight":10.06},{"theme":"food","keyword":"國父紀念館站","subkeyword":"一次","weight":8.33},{"theme":"food","keyword":"毛毛","subkeyword":"臺東","weight":85.11},{"theme":"food","keyword":"毛毛","subkeyword":"打卡","weight":73.65},{"theme":"food","keyword":"毛毛","subkeyword":"秘密","weight":63.33},{"theme":"food","keyword":"毛毛","subkeyword":"甜點","weight":62.93},{"theme":"food","keyword":"毛毛","subkeyword":"餐廳","weight":56.07},{"theme":"food","keyword":"毛毛","subkeyword":"咖啡店","weight":53.18},{"theme":"food","keyword":"毛毛","subkeyword":"波波黛莉","weight":49.81},{"theme":"food","keyword":"毛毛","subkeyword":"PopDaily","weight":49.81},{"theme":"food","keyword":"毛毛","subkeyword":"茶園","weight":49.21},{"theme":"food","keyword":"毛毛","subkeyword":"堅果","weight":48.85},{"theme":"food","keyword":"毛毛","subkeyword":"小巷","weight":48.82},{"theme":"food","keyword":"毛毛","subkeyword":"好吃","weight":46.93},{"theme":"food","keyword":"毛毛","subkeyword":"發胖","weight":40.22},{"theme":"food","keyword":"毛毛","subkeyword":"美食","weight":40.17},{"theme":"food","keyword":"毛毛","subkeyword":"坐落","weight":39.42},{"theme":"food","keyword":"毛毛","subkeyword":"鹿野","weight":38.09},{"theme":"food","keyword":"毛毛","subkeyword":"必吃","weight":24.91},{"theme":"food","keyword":"毛毛","subkeyword":"閒閒","weight":24.91},{"theme":"food","keyword":"毛毛","subkeyword":"甜甜","weight":22.43},{"theme":"food","keyword":"毛毛","subkeyword":"臺中","weight":21.38},{"theme":"food","keyword":"板橋店","subkeyword":"燒肉","weight":124.45},{"theme":"food","keyword":"板橋店","subkeyword":"日本","weight":67.23},{"theme":"food","keyword":"板橋店","subkeyword":"買一送一","weight":60.44},{"theme":"food","keyword":"板橋店","subkeyword":"搶吃","weight":47.79},{"theme":"food","keyword":"板橋店","subkeyword":"祭出","weight":44.61},{"theme":"food","keyword":"板橋店","subkeyword":"控吃","weight":42.16},{"theme":"food","keyword":"板橋店","subkeyword":"板車","weight":40.65},{"theme":"food","keyword":"板橋店","subkeyword":"和牛","weight":38.54},{"theme":"food","keyword":"板橋店","subkeyword":"牛角","weight":35.32},{"theme":"food","keyword":"板橋店","subkeyword":"好吃","weight":33.71},{"theme":"food","keyword":"板橋店","subkeyword":"環球","weight":32.96},{"theme":"food","keyword":"板橋店","subkeyword":"優惠","weight":28.35},{"theme":"food","keyword":"板橋店","subkeyword":"新北","weight":25.99},{"theme":"food","keyword":"板橋店","subkeyword":"成真咖啡","weight":25.99},{"theme":"food","keyword":"板橋店","subkeyword":"A4","weight":25.99},{"theme":"food","keyword":"板橋店","subkeyword":"食記","weight":25.99},{"theme":"food","keyword":"板橋店","subkeyword":"Fw","weight":25.99},{"theme":"food","keyword":"板橋店","subkeyword":"板橋","weight":21.85},{"theme":"food","keyword":"板橋店","subkeyword":"一個月","weight":14.26},{"theme":"food","keyword":"板橋店","subkeyword":"連續","weight":11.34},{"theme":"food","keyword":"日本畜產品出口促進協議會","subkeyword":"燒肉","weight":134.56},{"theme":"food","keyword":"日本畜產品出口促進協議會","subkeyword":"買一送一","weight":77.23},{"theme":"food","keyword":"日本畜產品出口促進協議會","subkeyword":"日本","weight":75.87},{"theme":"food","keyword":"日本畜產品出口促進協議會","subkeyword":"牛角","weight":61.23},{"theme":"food","keyword":"日本畜產品出口促進協議會","subkeyword":"優惠","weight":46.72},{"theme":"food","keyword":"日本畜產品出口促進協議會","subkeyword":"A4","weight":44.28},{"theme":"food","keyword":"日本畜產品出口促進協議會","subkeyword":"搶吃","weight":42.85},{"theme":"food","keyword":"日本畜產品出口促進協議會","subkeyword":"和牛","weight":41.78},{"theme":"food","keyword":"日本畜產品出口促進協議會","subkeyword":"肉量","weight":38.48},{"theme":"food","keyword":"日本畜產品出口促進協議會","subkeyword":"祭出","weight":35.82},{"theme":"food","keyword":"日本畜產品出口促進協議會","subkeyword":"控吃","weight":35.06},{"theme":"food","keyword":"日本畜產品出口促進協議會","subkeyword":"升級","weight":33.76},{"theme":"food","keyword":"日本畜產品出口促進協議會","subkeyword":"好吃","weight":27.87},{"theme":"food","keyword":"日本畜產品出口促進協議會","subkeyword":"準備","weight":22.16},{"theme":"food","keyword":"日本畜產品出口促進協議會","subkeyword":"肉肉控","weight":22.14},{"theme":"food","keyword":"日本畜產品出口促進協議會","subkeyword":"必沖","weight":22.14},{"theme":"food","keyword":"日本畜產品出口促進協議會","subkeyword":"肉肉","weight":13.59},{"theme":"food","keyword":"日本畜產品出口促進協議會","subkeyword":"一個月","weight":12.15},{"theme":"food","keyword":"日本畜產品出口促進協議會","subkeyword":"連續","weight":9.66},{"theme":"food","keyword":"唐吉訶德","subkeyword":"唐吉訶德","weight":99.41},{"theme":"food","keyword":"唐吉訶德","subkeyword":"樓層","weight":73.93},{"theme":"food","keyword":"唐吉訶德","subkeyword":"零食","weight":69.36},{"theme":"food","keyword":"唐吉訶德","subkeyword":"曝光","weight":69.05},{"theme":"food","keyword":"唐吉訶德","subkeyword":"店景","weight":68.92},{"theme":"food","keyword":"唐吉訶德","subkeyword":"獨家","weight":65.24},{"theme":"food","keyword":"唐吉訶德","subkeyword":"臺北","weight":59.71},{"theme":"food","keyword":"唐吉訶德","subkeyword":"開幕","weight":51.02},{"theme":"food","keyword":"唐吉訶德","subkeyword":"西門","weight":50.85},{"theme":"food","keyword":"唐吉訶德","subkeyword":"商品","weight":43.75},{"theme":"food","keyword":"唐吉訶德","subkeyword":"臺灣","weight":29.12},{"theme":"food","keyword":"唐吉訶德","subkeyword":"10","weight":28.46},{"theme":"food","keyword":"唐吉訶德","subkeyword":"39","weight":28.46},{"theme":"food","keyword":"唐吉訶德","subkeyword":"驚安","weight":28.46},{"theme":"food","keyword":"唐吉訶德","subkeyword":"必買","weight":28.46},{"theme":"food","keyword":"唐吉訶德","subkeyword":"19","weight":28.46},{"theme":"food","keyword":"唐吉訶德","subkeyword":"超飽","weight":28.46},{"theme":"food","keyword":"唐吉訶德","subkeyword":"元起","weight":28.46},{"theme":"food","keyword":"唐吉訶德","subkeyword":"大必","weight":28.46},{"theme":"food","keyword":"唐吉訶德","subkeyword":"公開","weight":13.37},{"theme":"food","keyword":"文華東方酒店","subkeyword":"原酒","weight":77.89},{"theme":"food","keyword":"文華東方酒店","subkeyword":"文華","weight":76.9},{"theme":"food","keyword":"文華東方酒店","subkeyword":"饗宴","weight":60.02},{"theme":"food","keyword":"文華東方酒店","subkeyword":"自助餐","weight":50.88},{"theme":"food","keyword":"文華東方酒店","subkeyword":"米其林","weight":50.37},{"theme":"food","keyword":"文華東方酒店","subkeyword":"額滿","weight":50.35},{"theme":"food","keyword":"文華東方酒店","subkeyword":"圍爐","weight":49.91},{"theme":"food","keyword":"文華東方酒店","subkeyword":"火速","weight":44.08},{"theme":"food","keyword":"文華東方酒店","subkeyword":"飯店","weight":43.66},{"theme":"food","keyword":"文華東方酒店","subkeyword":"情人節","weight":43.63},{"theme":"food","keyword":"文華東方酒店","subkeyword":"講座","weight":43.63},{"theme":"food","keyword":"文華東方酒店","subkeyword":"出去","weight":40.15},{"theme":"food","keyword":"文華東方酒店","subkeyword":"夢幻","weight":35.16},{"theme":"food","keyword":"文華東方酒店","subkeyword":"臺北","weight":33.98},{"theme":"food","keyword":"文華東方酒店","subkeyword":"業績","weight":30.84},{"theme":"food","keyword":"文華東方酒店","subkeyword":"參加","weight":30.77},{"theme":"food","keyword":"文華東方酒店","subkeyword":"品味","weight":30.04},{"theme":"food","keyword":"文華東方酒店","subkeyword":"甜蜜","weight":27.95},{"theme":"food","keyword":"文華東方酒店","subkeyword":"東方","weight":19.34},{"theme":"food","keyword":"文華東方酒店","subkeyword":"即贈","weight":19.28},{"theme":"food","keyword":"文華東方酒店","subkeyword":"最夯","weight":19.28},{"theme":"food","keyword":"文華東方酒店","subkeyword":"美點","weight":19.28},{"theme":"food","keyword":"文華東方酒店","subkeyword":"27","weight":19.28},{"theme":"food","keyword":"文華東方酒店","subkeyword":"8800","weight":19.28},{"theme":"food","keyword":"文華東方酒店","subkeyword":"共度","weight":17.05},{"theme":"food","keyword":"文華東方酒店","subkeyword":"繽紛","weight":16.18},{"theme":"food","keyword":"文華東方酒店","subkeyword":"單一","weight":11.54},{"theme":"food","keyword":"晶華","subkeyword":"自助餐","weight":93.9},{"theme":"food","keyword":"晶華","subkeyword":"米其林","weight":92.9},{"theme":"food","keyword":"晶華","subkeyword":"圍爐","weight":91.87},{"theme":"food","keyword":"晶華","subkeyword":"烤雞","weight":91.45},{"theme":"food","keyword":"晶華","subkeyword":"香草","weight":84.63},{"theme":"food","keyword":"晶華","subkeyword":"飯店","weight":77.91},{"theme":"food","keyword":"晶華","subkeyword":"出去","weight":70.12},{"theme":"food","keyword":"晶華","subkeyword":"業績","weight":67.75},{"theme":"food","keyword":"晶華","subkeyword":"最夯","weight":42.7},{"theme":"food","keyword":"晶華","subkeyword":"7-11","weight":42.7},{"theme":"food","keyword":"晶華","subkeyword":"21","weight":42.7},{"theme":"food","keyword":"晶華","subkeyword":"Plus","weight":42.7},{"theme":"food","keyword":"晶華","subkeyword":"黃飯","weight":42.7},{"theme":"food","keyword":"晶華","subkeyword":"商品","weight":18.88},{"theme":"food","keyword":"謝孟芝","subkeyword":"火鍋","weight":73.96},{"theme":"food","keyword":"謝孟芝","subkeyword":"中西","weight":72.19},{"theme":"food","keyword":"謝孟芝","subkeyword":"米其林","weight":66.63},{"theme":"food","keyword":"謝孟芝","subkeyword":"懶人","weight":66.14},{"theme":"food","keyword":"謝孟芝","subkeyword":"拚場","weight":63.01},{"theme":"food","keyword":"謝孟芝","subkeyword":"禮盒","weight":60.84},{"theme":"food","keyword":"謝孟芝","subkeyword":"星級","weight":60.11},{"theme":"food","keyword":"謝孟芝","subkeyword":"情人","weight":52.78},{"theme":"food","keyword":"謝孟芝","subkeyword":"外帶","weight":46.85},{"theme":"food","keyword":"謝孟芝","subkeyword":"業績","weight":45.45},{"theme":"food","keyword":"謝孟芝","subkeyword":"雙節","weight":42.11},{"theme":"food","keyword":"謝孟芝","subkeyword":"微醺","weight":30.27},{"theme":"food","keyword":"謝孟芝","subkeyword":"微兜","weight":29.89},{"theme":"food","keyword":"謝孟芝","subkeyword":"doux","weight":29.89},{"theme":"food","keyword":"謝孟芝","subkeyword":"petit","weight":29.89},{"theme":"food","keyword":"謝孟芝","subkeyword":"最夯","weight":29.89},{"theme":"food","keyword":"謝孟芝","subkeyword":"套餐","weight":23.29},{"theme":"food","keyword":"謝孟芝","subkeyword":"粉紅","weight":22.72},{"theme":"food","keyword":"謝孟芝","subkeyword":"甜蜜","weight":21.66},{"theme":"food","keyword":"謝孟芝","subkeyword":"浪漫","weight":20.94},{"theme":"food","keyword":"山海樓","subkeyword":"中西","weight":80.11},{"theme":"food","keyword":"山海樓","subkeyword":"懶人","weight":76.13},{"theme":"food","keyword":"山海樓","subkeyword":"米其林","weight":75.39},{"theme":"food","keyword":"山海樓","subkeyword":"八寶","weight":74.64},{"theme":"food","keyword":"山海樓","subkeyword":"山海","weight":73.99},{"theme":"food","keyword":"山海樓","subkeyword":"拚場","weight":73.27},{"theme":"food","keyword":"山海樓","subkeyword":"蹄膀","weight":71.51},{"theme":"food","keyword":"山海樓","subkeyword":"全家","weight":69.85},{"theme":"food","keyword":"山海樓","subkeyword":"禮盒","weight":67.72},{"theme":"food","keyword":"山海樓","subkeyword":"星級","weight":66.83},{"theme":"food","keyword":"山海樓","subkeyword":"火鍋","weight":66.74},{"theme":"food","keyword":"山海樓","subkeyword":"外帶","weight":55.98},{"theme":"food","keyword":"山海樓","subkeyword":"業績","weight":49.96},{"theme":"food","keyword":"山海樓","subkeyword":"最夯","weight":39.85},{"theme":"food","keyword":"山海樓","subkeyword":"商品","weight":34.54},{"theme":"food","keyword":"Google","subkeyword":"禮盒","weight":72.36},{"theme":"food","keyword":"Google","subkeyword":"小嫻","weight":52.71},{"theme":"food","keyword":"Google","subkeyword":"海鮮","weight":50.71},{"theme":"food","keyword":"Google","subkeyword":"玩法","weight":50.2},{"theme":"food","keyword":"Google","subkeyword":"南國","weight":49.12},{"theme":"food","keyword":"Google","subkeyword":"控必收","weight":45.77},{"theme":"food","keyword":"Google","subkeyword":"超強","weight":42.97},{"theme":"food","keyword":"Google","subkeyword":"公仔","weight":41.51},{"theme":"food","keyword":"Google","subkeyword":"物桶","weight":39.43},{"theme":"food","keyword":"Google","subkeyword":"漢堡","weight":39.39},{"theme":"food","keyword":"Google","subkeyword":"三麗鷗","weight":39.3},{"theme":"food","keyword":"Google","subkeyword":"專賣店","weight":39.17},{"theme":"food","keyword":"Google","subkeyword":"午餐","weight":35.83},{"theme":"food","keyword":"Google","subkeyword":"起來","weight":35.77},{"theme":"food","keyword":"Google","subkeyword":"帶路","weight":33.75},{"theme":"food","keyword":"Google","subkeyword":"限定","weight":30.74},{"theme":"food","keyword":"Google","subkeyword":"金剛","weight":30.61},{"theme":"food","keyword":"Google","subkeyword":"獨家","weight":30.52},{"theme":"food","keyword":"Google","subkeyword":"北屯","weight":29.64},{"theme":"food","keyword":"Google","subkeyword":"發掘","weight":29.62},{"theme":"food","keyword":"Google","subkeyword":"重演","weight":28.5},{"theme":"food","keyword":"Google","subkeyword":"日本","weight":25.84},{"theme":"food","keyword":"Google","subkeyword":"總部","weight":20.75},{"theme":"food","keyword":"Google","subkeyword":"得到","weight":17.38},{"theme":"food","keyword":"Google","subkeyword":"打工","weight":16.09},{"theme":"food","keyword":"Google","subkeyword":"墾丁","weight":15.01},{"theme":"food","keyword":"Google","subkeyword":"一整隻","weight":14.55},{"theme":"food","keyword":"Google","subkeyword":"卡娜赫拉","weight":13.58},{"theme":"food","keyword":"Google","subkeyword":"超狂","weight":13.58},{"theme":"food","keyword":"Google","subkeyword":"20","weight":13.58},{"theme":"food","keyword":"Google","subkeyword":"11","weight":13.58},{"theme":"food","keyword":"Google","subkeyword":"波波黛莉","weight":13.58},{"theme":"food","keyword":"Google","subkeyword":"PopDaily","weight":13.58},{"theme":"food","keyword":"Google","subkeyword":"軟殼","weight":13.58},{"theme":"food","keyword":"Google","subkeyword":"區早","weight":13.58},{"theme":"food","keyword":"Google","subkeyword":"臺中","weight":11.66},{"theme":"food","keyword":"Google","subkeyword":"牛年","weight":11.02},{"theme":"food","keyword":"Google","subkeyword":"發胖","weight":10.97},{"theme":"food","keyword":"侯布雄","subkeyword":"外脆","weight":116.42},{"theme":"food","keyword":"侯布雄","subkeyword":"盲試","weight":106.9},{"theme":"food","keyword":"侯布雄","subkeyword":"酸香","weight":104.07},{"theme":"food","keyword":"侯布雄","subkeyword":"名廚","weight":101.95},{"theme":"food","keyword":"侯布雄","subkeyword":"星級","weight":93.94},{"theme":"food","keyword":"侯布雄","subkeyword":"冠軍","weight":92.27},{"theme":"food","keyword":"侯布雄","subkeyword":"韌帶","weight":90.45},{"theme":"food","keyword":"侯布雄","subkeyword":"麵包","weight":71.84},{"theme":"food","keyword":"侯布雄","subkeyword":"款長","weight":66.42},{"theme":"food","keyword":"Le Pain Quotidien","subkeyword":"外脆","weight":116.42},{"theme":"food","keyword":"Le Pain Quotidien","subkeyword":"盲試","weight":106.9},{"theme":"food","keyword":"Le Pain Quotidien","subkeyword":"酸香","weight":104.07},{"theme":"food","keyword":"Le Pain Quotidien","subkeyword":"名廚","weight":101.95},{"theme":"food","keyword":"Le Pain Quotidien","subkeyword":"星級","weight":93.94},{"theme":"food","keyword":"Le Pain Quotidien","subkeyword":"冠軍","weight":92.27},{"theme":"food","keyword":"Le Pain Quotidien","subkeyword":"韌帶","weight":90.45},{"theme":"food","keyword":"Le Pain Quotidien","subkeyword":"麵包","weight":71.84},{"theme":"food","keyword":"Le Pain Quotidien","subkeyword":"款長","weight":66.42},{"theme":"food","keyword":"米其林三星餐廳Lameloise","subkeyword":"外脆","weight":116.42},{"theme":"food","keyword":"米其林三星餐廳Lameloise","subkeyword":"盲試","weight":106.9},{"theme":"food","keyword":"米其林三星餐廳Lameloise","subkeyword":"酸香","weight":104.07},{"theme":"food","keyword":"米其林三星餐廳Lameloise","subkeyword":"名廚","weight":101.95},{"theme":"food","keyword":"米其林三星餐廳Lameloise","subkeyword":"星級","weight":93.94},{"theme":"food","keyword":"米其林三星餐廳Lameloise","subkeyword":"冠軍","weight":92.27},{"theme":"food","keyword":"米其林三星餐廳Lameloise","subkeyword":"韌帶","weight":90.45},{"theme":"food","keyword":"米其林三星餐廳Lameloise","subkeyword":"麵包","weight":71.84},{"theme":"food","keyword":"米其林三星餐廳Lameloise","subkeyword":"款長","weight":66.42},{"theme":"food","keyword":"米其林三星","subkeyword":"酸香","weight":87.36},{"theme":"food","keyword":"米其林三星","subkeyword":"外脆","weight":77.37},{"theme":"food","keyword":"米其林三星","subkeyword":"自助餐","weight":73.5},{"theme":"food","keyword":"米其林三星","subkeyword":"米其林","weight":72.68},{"theme":"food","keyword":"米其林三星","subkeyword":"盲試","weight":72.45},{"theme":"food","keyword":"米其林三星","subkeyword":"名廚","weight":69.54},{"theme":"food","keyword":"米其林三星","subkeyword":"韌帶","weight":69.46},{"theme":"food","keyword":"米其林三星","subkeyword":"星級","weight":65.1},{"theme":"food","keyword":"米其林三星","subkeyword":"冠軍","weight":63.74},{"theme":"food","keyword":"米其林三星","subkeyword":"圍爐","weight":58.64},{"theme":"food","keyword":"米其林三星","subkeyword":"飯店","weight":55.98},{"theme":"food","keyword":"米其林三星","subkeyword":"出去","weight":52.69},{"theme":"food","keyword":"米其林三星","subkeyword":"業績","weight":50.67},{"theme":"food","keyword":"米其林三星","subkeyword":"麵包","weight":47.06},{"theme":"food","keyword":"米其林三星","subkeyword":"款長","weight":37.36},{"theme":"food","keyword":"米其林三星","subkeyword":"最夯","weight":37.36},{"theme":"food","keyword":"Nicolas","subkeyword":"外脆","weight":116.42},{"theme":"food","keyword":"Nicolas","subkeyword":"盲試","weight":106.9},{"theme":"food","keyword":"Nicolas","subkeyword":"酸香","weight":104.07},{"theme":"food","keyword":"Nicolas","subkeyword":"名廚","weight":101.95},{"theme":"food","keyword":"Nicolas","subkeyword":"星級","weight":93.94},{"theme":"food","keyword":"Nicolas","subkeyword":"冠軍","weight":92.27},{"theme":"food","keyword":"Nicolas","subkeyword":"韌帶","weight":90.45},{"theme":"food","keyword":"Nicolas","subkeyword":"麵包","weight":71.84},{"theme":"food","keyword":"Nicolas","subkeyword":"款長","weight":66.42},{"theme":"food","keyword":"Maison Eric Kayser","subkeyword":"外脆","weight":116.42},{"theme":"food","keyword":"Maison Eric Kayser","subkeyword":"盲試","weight":106.9},{"theme":"food","keyword":"Maison Eric Kayser","subkeyword":"酸香","weight":104.07},{"theme":"food","keyword":"Maison Eric Kayser","subkeyword":"名廚","weight":101.95},{"theme":"food","keyword":"Maison Eric Kayser","subkeyword":"星級","weight":93.94},{"theme":"food","keyword":"Maison Eric Kayser","subkeyword":"冠軍","weight":92.27},{"theme":"food","keyword":"Maison Eric Kayser","subkeyword":"韌帶","weight":90.45},{"theme":"food","keyword":"Maison Eric Kayser","subkeyword":"麵包","weight":71.84},{"theme":"food","keyword":"Maison Eric Kayser","subkeyword":"款長","weight":66.42},{"theme":"food","keyword":"阿源","subkeyword":"時差","weight":109.66},{"theme":"food","keyword":"阿源","subkeyword":"知識","weight":91.58},{"theme":"food","keyword":"阿源","subkeyword":"生活","weight":88.62},{"theme":"food","keyword":"阿源","subkeyword":"規律","weight":88.4},{"theme":"food","keyword":"阿源","subkeyword":"癥狀","weight":80.73},{"theme":"food","keyword":"阿源","subkeyword":"嚴重","weight":44.39},{"theme":"food","keyword":"梅花紅葉競美 繽紛公園","subkeyword":"時差","weight":109.66},{"theme":"food","keyword":"梅花紅葉競美 繽紛公園","subkeyword":"知識","weight":91.58},{"theme":"food","keyword":"梅花紅葉競美 繽紛公園","subkeyword":"生活","weight":88.62},{"theme":"food","keyword":"梅花紅葉競美 繽紛公園","subkeyword":"規律","weight":88.4},{"theme":"food","keyword":"梅花紅葉競美 繽紛公園","subkeyword":"癥狀","weight":80.73},{"theme":"food","keyword":"梅花紅葉競美 繽紛公園","subkeyword":"嚴重","weight":44.39},{"theme":"food","keyword":"香港食環署","subkeyword":"結業","weight":114.05},{"theme":"food","keyword":"香港食環署","subkeyword":"落淚","weight":107.33},{"theme":"food","keyword":"香港食環署","subkeyword":"名店","weight":105.04},{"theme":"food","keyword":"香港食環署","subkeyword":"老闆","weight":91.06},{"theme":"food","keyword":"香港食環署","subkeyword":"感謝","weight":86.01},{"theme":"food","keyword":"香港食環署","subkeyword":"羊腩","weight":74.72},{"theme":"food","keyword":"香港食環署","subkeyword":"不舍","weight":60.69},{"theme":"food","keyword":"香港食環署","subkeyword":"大家","weight":52.03},{"theme":"food","keyword":"金禧樓","subkeyword":"結業","weight":114.05},{"theme":"food","keyword":"金禧樓","subkeyword":"落淚","weight":107.33},{"theme":"food","keyword":"金禧樓","subkeyword":"名店","weight":105.04},{"theme":"food","keyword":"金禧樓","subkeyword":"老闆","weight":91.06},{"theme":"food","keyword":"金禧樓","subkeyword":"感謝","weight":86.01},{"theme":"food","keyword":"金禧樓","subkeyword":"羊腩","weight":74.72},{"theme":"food","keyword":"金禧樓","subkeyword":"不舍","weight":60.69},{"theme":"food","keyword":"金禧樓","subkeyword":"大家","weight":52.03},{"theme":"food","keyword":"華山町","subkeyword":"夜宿","weight":93.61},{"theme":"food","keyword":"華山町","subkeyword":"華山","weight":87.31},{"theme":"food","keyword":"華山町","subkeyword":"炸雞","weight":84.96},{"theme":"food","keyword":"華山町","subkeyword":"加碼","weight":82.23},{"theme":"food","keyword":"華山町","subkeyword":"臺北","weight":76.75},{"theme":"food","keyword":"華山町","subkeyword":"熱潮","weight":67.74},{"theme":"food","keyword":"華山町","subkeyword":"GO","weight":49.81},{"theme":"food","keyword":"華山町","subkeyword":"1600","weight":49.81},{"theme":"food","keyword":"華山町","subkeyword":"元起","weight":49.81},{"theme":"food","keyword":"華山町","subkeyword":"比薩","weight":40.53},{"theme":"food","keyword":"華山町","subkeyword":"每晚","weight":40.28},{"theme":"food","keyword":"華山町","subkeyword":"國旅","weight":38.69},{"theme":"food","keyword":"天成文旅-華山町","subkeyword":"夜宿","weight":93.61},{"theme":"food","keyword":"天成文旅-華山町","subkeyword":"華山","weight":87.31},{"theme":"food","keyword":"天成文旅-華山町","subkeyword":"炸雞","weight":84.96},{"theme":"food","keyword":"天成文旅-華山町","subkeyword":"加碼","weight":82.23},{"theme":"food","keyword":"天成文旅-華山町","subkeyword":"臺北","weight":76.75},{"theme":"food","keyword":"天成文旅-華山町","subkeyword":"熱潮","weight":67.74},{"theme":"food","keyword":"天成文旅-華山町","subkeyword":"GO","weight":49.81},{"theme":"food","keyword":"天成文旅-華山町","subkeyword":"1600","weight":49.81},{"theme":"food","keyword":"天成文旅-華山町","subkeyword":"元起","weight":49.81},{"theme":"food","keyword":"天成文旅-華山町","subkeyword":"比薩","weight":40.53},{"theme":"food","keyword":"天成文旅-華山町","subkeyword":"每晚","weight":40.28},{"theme":"food","keyword":"天成文旅-華山町","subkeyword":"國旅","weight":38.69}]