[{"theme":"food","keyword":"萊爾富 美食","title":"[商品] 萊爾富福袋A - cvs | PTT旅遊美食區","url":"https:\/\/ptttravelfood.com\/cvs\/M.1610800389.A.529.html","description":" 【商品名稱\/價格】： 萊爾富福袋\/168元【便利商店\/廠商名稱】：萊爾富【規格\/\n內容物\/熱量】： 【評分】：68 (未滿60分為不推薦) 【心得】： 其實本來是想去\n附近買 ...","image":null},{"theme":"food","keyword":"萊爾富 美食","title":"桃桃's旅人手札","url":"https:\/\/momotravel.tw\/","description":" 今年7-11福袋、全家福袋、萊爾富福袋，推出的福袋大獎都是汽車；OK福袋最便宜\n只要100元，大獎是價值15萬的鑽石項鍊，也是相當不錯的。 而在四大超商 ...","image":"https:\/\/momotravel.tw\/wp-content\/uploads\/cropped-20190221160652_31.png"},{"theme":"food","keyword":"萊爾富 美食","title":"Maruko與美食有個約會","url":"https:\/\/maruko.tw\/","description":" Maruko(丸子)一個喜愛美食與日本旅遊的大孩子，我喜歡用照片記錄生活點滴與\n美好事物，更喜愛烹飪、分享料理。更多請看：關於我合作｜邀 ...","image":"https:\/\/maruko.tw\/wp-content\/uploads\/2020\/12\/IMG_0028.png"},{"theme":"food","keyword":"萊爾富 美食","title":"[商品] 萊爾富脆筍豬肉包&麻油豬豚菇包- 看板CVS | PTT美食旅遊區","url":"https:\/\/pttfoodtravel.com\/CVS\/1W0QUel8","description":" 【商品名稱\/價格】：脆筍豬肉包&麻油豬豚菇包\/30元(區域型商品請註明試吃試用品\n請標示價格0元) 【便利商店\/廠商名稱】：萊爾富\/奇美【規格\/內容物\/熱量】：（如\n ...","image":"https:\/\/i.imgur.com\/YxJCLck.jpg"},{"theme":"food","keyword":"萊爾富 美食","title":"萌芽悠遊網- 景點悠遊 公路探險 美食饗宴- 萌芽網頁","url":"https:\/\/mnya.tw\/yo","description":" 沙茶牛肉炒麵75元／399公克／571大卡宵夜吃7-ELEVEN […] 2021\/01\/04 萌芽\n站長 26. 美食悠遊 , 台灣 , 微波冷凍 , 超 ...","image":null},{"theme":"food","keyword":"萊爾富 美食","title":"萊爾富4168北市101店台北外送| 菜單| Uber Eats","url":"https:\/\/www.ubereats.com\/tw\/taipei\/food-delivery\/%25E8%2590%258A%25E7%2588%25BE%25E5%25AF%258C4168%25E5%258C%2597%25E5%25B8%2582101%25E5%25BA%2597\/TBrlT3RYRTa_vtqUyg7G4Q\/067b7212-2462-505c-8b60-58cc267900ca","description":" 使用Uber 帳戶即可向台北的萊爾富4168北市101店訂購外送美食。瀏覽菜單、查看\n熱門餐點，並可追蹤訂單進度。","image":"https:\/\/d1ralsognjng37.cloudfront.net\/31416653-6251-46e2-8e54-cbc2e7b56e09.jpeg"},{"theme":"food","keyword":"萊爾富 美食","title":"買福袋「抽保時捷」！2021「四大超商超市福袋」必買，0.5克拉鑽 ...","url":"https:\/\/udn.com\/news\/story\/7934\/5176938","description":" 2021-01-15 16:18 聯合新聞網\/ 旅遊美食特約作者萊點特別. 這回三大超商與全 ... 此\n次萊爾富針對新春開運祭出了「開運福袋」與「發財卡」。開運福袋售價僅168 ...","image":"https:\/\/pgw.udn.com.tw\/gw\/photo.php?u=https:\/\/uc.udn.com.tw\/photo\/2021\/01\/15\/1\/11205014.png&s=Y&x=0&y=0&sw=1279&sh=831&exp=3600"},{"theme":"food","keyword":"萊爾富 美食","title":"大家源小電鍋的價格推薦- 2021年1月| 比價比個夠BigGo","url":"https:\/\/biggo.com.tw\/s\/%E5%A4%A7%E5%AE%B6%E6%BA%90+%E5%B0%8F%E9%9B%BB%E9%8D%8B\/","description":" 萊爾富運費只要35元. 大家源304不鏽鋼雙層防燙美食鍋小電鍋美食鍋電. 3. 大家源\n304不鏽鋼雙層防燙美食鍋小電鍋美食鍋電鍋迷你電鍋一人份快煮鍋單身萬用鍋.","image":"https:\/\/img.biggo.com.tw\/sy8kQNcl-buFToUN3iwhADoWcOlyDuBXieakIq8dlvwA\/https:\/\/tshop.r10s.com\/52a\/921\/6f6e\/45f5\/e1e9\/e142\/73e2\/116be7ab93c4544488dc07.jpg"},{"theme":"food","keyword":"萊爾富 美食","title":"[新北美食]滴滴鮮雞精，精選補身體元氣與抗寒冷窩心補品，年節送禮 ...","url":"https:\/\/bravejim.pixnet.net\/blog\/post\/230252673-%5B%E6%96%B0%E5%8C%97%E7%BE%8E%E9%A3%9F%5D%E6%BB%B4%E6%BB%B4%E9%AE%AE%E9%9B%9E%E7%B2%BE","description":" 大賣場(大潤發、愛買、家樂福)、連鎖超市(全聯社、美聯社)、便利商店(7-11、OK\n、萊爾富、全家)、老協珍門市等實體通路. 備註: 本雞精經過實體測試與認證，請 ...","image":"https:\/\/pic.pimg.tw\/bravejim\/1610122487-246753056-g_n.jpg?v=1610122499"},{"theme":"food","keyword":"萊爾富 美食","title":"【總公司】行銷企劃專員｜萊爾富國際股份有限公司｜台北市內湖區 ...","url":"https:\/\/www.104.com.tw\/job\/6rkwf","description":" 【工作內容】台北市內湖區- 一、從商業價值及公司競爭角度出發，進行市場營運或\n產品調研的活動案調查二、根據市場情報調查資訊，從…。薪資： ...","image":"https:\/\/static.104.com.tw\/logo\/104logo_200x200_fbogT2.png"},{"theme":"food","keyword":"萊爾富 美食","title":"2021新春福袋｜全家、7-11、OK、萊爾富、四大超商福袋開賣囉!!開 ...","url":"https:\/\/itainan.com.tw\/2021lucky-bag\/","description":" 四大超商全家、7-11、OK、萊爾富每年推出的新年福袋總是讓大家好生期待，福袋\n裡面慣例會有一些餅乾零食，不過重點是有機會抽中大獎。 2021牛年四大超商 ...","image":"https:\/\/img.itainan.com.tw\/uploads\/20210114145702_52.jpg"},{"theme":"food","keyword":"萊爾富 美食","title":"Eatchen - #sis ‍♀️吃超商#新品#韓國冰棒- 萊爾富- 玉米雪糕 西瓜 ...","url":"https:\/\/pt-pt.facebook.com\/sis.1109\/posts\/675123719927052:0","description":" 西瓜冰棒口感特別的清爽兩款都好吃到4\/7聽說售完為止！ - 地址：全台萊爾富 - #\n台灣#台灣美食#美食#台中#台中美食#萊爾富#萊爾富新品#韓國冰品#玉米雪糕# ...","image":"https:\/\/lookaside.fbsbx.com\/lookaside\/crawler\/media\/?media_id=675123719927052"},{"theme":"food","keyword":"萊爾富 美食","title":"【蝦皮折扣碼-1月】蝦皮購物\/蝦皮商城\/蝦皮直送2021最新優惠券 ...","url":"https:\/\/www.callingtaiwan.com.tw\/%E3%80%90%E8%9D%A6%E7%9A%AE%E6%8A%98%E6%89%A3%E7%A2%BC%E3%80%91%E8%9D%A6%E7%9A%AE%E8%B3%BC%E7%89%A9-%E8%9D%A6%E7%9A%AE%E5%95%86%E5%9F%8E-%E8%9D%A6%E7%9A%AE24h-2021%E6%9C%80%E6%96%B0%E5%84%AA%E6%83%A0\/","description":" 2021\/01\/31, 【蝦皮購物】萊爾富− 消費滿199 元免運費, 前往領取. 2021\/01\/31 ... \n【蝦皮美食外送優惠】蝦皮美食外送免運券\/外送區域\/訂餐教學>>. 【屈臣氏 ...","image":"https:\/\/www.callingtaiwan.com.tw\/wp-content\/uploads\/2020\/04\/蝦皮免運券文章圖-01.png"},{"theme":"food","keyword":"萊爾富 美食","title":"萊爾富超商Hi-Life - 【萊點冬味 早餐新品+10元喝飲料】 水果有「哈 ...","url":"https:\/\/www.facebook.com\/hihilife\/posts\/10157957355636474\/","description":" 萊點冬味 早餐新品+10元喝飲料】 水果有「哈」味🤩早餐就萊點「冬」味吧！ \n麻油雞飯糰 叉燒油雞海苔飯捲新上市✨ 12\/3前➡加10元喝指定飲料 快到小萊 ...","image":"https:\/\/lookaside.fbsbx.com\/lookaside\/crawler\/media\/?media_id=10157957355231474"},{"theme":"food","keyword":"萊爾富 美食","title":"【總公司】.NET程式設計師~歡迎新鮮人~｜萊爾富國際股份有限公司 ...","url":"https:\/\/m.104.com.tw\/job\/4dchs","description":" 【工作內容】台北市內湖區- 1. 前端網頁系統程式開發(具Windows網頁開發能力) 2. \n後端資料庫程式(T-SQL)開發…。薪資：月薪32000~42000元。職務類別：MIS ...","image":"https:\/\/static.104.com.tw\/logo\/104logo_200x200_fbogT2.png"},{"theme":"food","keyword":"萊爾富 美食","title":"學生事務處","url":"https:\/\/sao.tpcu.edu.tw\/","description":" 萊爾富超商. 等一等茶飲. 娃子美而美. 小慶慶滷味店. 雞魯幫. 嘗嚐食坊. 冰菓冰果. 阿\n關丼飯. 吉立自助餐. 饗蘸美食. 財經早餐店. 鮮味屋. 城市廚房 ...","image":null},{"theme":"food","keyword":"台北咖啡廳 美食","title":"台北忠孝館|SOGO百貨","url":"https:\/\/www.sogo.com.tw\/tp1","description":" 營業時間與交通資訊 Traffic Parking Service. 106台北市忠孝東路四段45號. 搭乘捷\n運 ... 11F美食餐廳. 週日~週四\/ 11:00~21:30(最後點餐21:00) | 週五、週六及例假 ...","image":null},{"theme":"food","keyword":"台北咖啡廳 美食","title":"Palette 彩匯自助餐廳- 台北美福大飯店｜超值優惠- KLOOK客路台灣","url":"https:\/\/www.klook.com\/zh-TW\/activity\/47044-mayfull-palette-taipei\/","description":" 台北中山區推薦必吃五星級飯店buffet，彩匯自助餐廳被網友選為台北必吃五星飯店\nbuffet冠軍，招牌牛肉、精選海鮮、精緻甜點等美食，滿足老饕的味蕾！","image":"https:\/\/res.klook.com\/images\/fl_lossy.progressive,q_65\/c_fill,w_1200,h_630,f_auto\/w_80,x_15,y_15,g_south_west,l_klook_water\/activities\/yvgl6zlu26na7dct5xag\/\/台北美福飯店｜彩匯自助餐廳｜捷運劍南路站.jpg"},{"theme":"food","keyword":"台北咖啡廳 美食","title":"[食記]台北新北基隆Archives - 周花花，甲飽沒","url":"https:\/\/tenjo.tw\/category\/taipei-eat\/","description":" 老房新生的概念在各個城市發酵，任何形式的新舊共存我都是喜歡的板橋樹林地區\n的《微間素生》，以設計結合... 2021.01.13. 【內湖瑞光路美食】永寶餐廳菜單 ...","image":null},{"theme":"food","keyword":"台北咖啡廳 美食","title":"水晶安蹄不務正業過生活","url":"https:\/\/auntie.tw\/","description":" 【台北】南港harbor market 商店結合咖啡廳文青風素食餐廳 · 【台北美食推薦】\nOOH CHA CHA 自然食天然的蔬食料理點到太多豆子個人不愛啦！(早午餐下午茶).","image":"https:\/\/auntie.tw\/wp-content\/uploads\/cropped-flash.png"},{"theme":"food","keyword":"台北咖啡廳 美食","title":"【全部餐廳】信用卡推薦｜2021年1月優惠排行前五張卡、台北君悅 ...","url":"https:\/\/icard.ai\/home\/cards?request=%5B%7B%22id%22%3A%22channel_concept%2F5d6cd9f38a0112506b5ed699%22%2C%22channels%22%3A%5B%7B%22id%22%3A%22channel%2F5e32892e25aff61105dd065a%22%2C%22name%22%3A%22%E5%8F%B0%E5%8C%97%E5%90%9B%E6%82%85%E9%85%92%E5%BA%97%E6%AD%A1%E9%A3%B2%E5%BB%8A+%22%7D%2C%7B%22id%22%3A%22channel%2F5d6756976fce34b66795590c%22%2C%22name%22%3A%22ZIGA+ZAGA+%E5%8F%B0%E5%8C%97%E5%90%9B%E6%82%85%E9%85%92%E5%BA%97%22%7D%2C%7B%22id%22%3A%22channel%2F5e32884925aff61105dd0657%22%2C%22name%22%3A%22%E5%8F%B0%E5%8C%97%E5%90%9B%E6%82%85%E9%85%92%E5%BA%97%E8%BF%8E%E8%B3%93%E5%BB%8A%22%7D%2C%7B%22id%22%3A%22channel%2F5d50cc14f3d9b9354065661f%22%2C%22name%22%3A%22%E5%8F%B0%E5%8C%97%E5%90%9B%E6%82%85%E9%85%92%E5%BA%97%E5%BD%A9%E6%97%A5%E6%9C%AC%E6%96%99%E7%90%86%22%7D%2C%7B%22id%22%3A%22channel%2F5e32896525aff61105dd065d%22%2C%22name%22%3A%22%E5%8F%B0%E5%8C%97%E5%90%9B%E6%82%85%E9%85%92%E5%BA%97%E9%9B%B2%E9%8C%A6%E4%B8%AD%E9%A4%90%E5%BB%B3%22%7D%2C%7B%22id%22%3A%22channel%2F5e32898d25aff61105dd0660%22%2C%22name%22%3A%22%E5%8F%B0%E5%8C%97%E5%90%9B%E6%82%85%E9%85%92%E5%BA%97%E5%AF%B6%E8%89%BE%E8%A5%BF%E9%A4%90%E5%BB%B3%22%7D%5D%7D%5D","description":" 看這篇就夠了！iCard.AI即時更新全部餐廳最完整信用卡優惠，推薦含台北君悅酒店\n歡飲廊、ZIGA ZAGA 台北君悅酒店、台北君悅酒店迎賓廊、台北君悅酒店彩日本 ...","image":"\/_next\/static\/a63240c6e36562abf90a623c172fe6d2.png"},{"theme":"food","keyword":"台北咖啡廳 美食","title":"Maruko與美食有個約會","url":"https:\/\/maruko.tw\/","description":" 【2021外帶年菜推薦】飯BAR Station 微風信義店｜台北最時髦的中餐廳七層絲 ... \n【板橋美食】2020新北歡樂耶誕城｜10家板橋捷運站週邊,縣民小吃,美食餐廳推薦.","image":"https:\/\/maruko.tw\/wp-content\/uploads\/2020\/12\/IMG_0028.png"},{"theme":"food","keyword":"台北咖啡廳 美食","title":"大妹吃太飽","url":"https:\/\/damei17.com\/","description":" 台北咖啡館 文湖線美食(棕線). 說起北門咖啡廳你會想起什麼？是否和我一樣的會\n想起MKCR 山小孩咖啡呢？2020 年在都市裡的邊角開了二店，這裡沒有北門那樣\n的 ...","image":"https:\/\/damei17.com\/wp-content\/uploads\/2020\/02\/cropped-talk-1.png"},{"theme":"food","keyword":"台北咖啡廳 美食","title":"「捷運：忠孝復興站」Ombré 餐廳@ 陳凱莉～台北人捷運美食、吃好 ...","url":"https:\/\/blog.xuite.net\/kellychen6012003\/twblog1\/348912876-%E3%80%8C%E6%8D%B7%E9%81%8B%EF%BC%9A%E5%BF%A0%E5%AD%9D%E5%BE%A9%E8%88%88%E7%AB%99%E3%80%8DOmbr%C3%A9+%E9%A4%90%E5%BB%B3","description":" https:\/\/www.facebook.com\/Ombr%C3%A9-1600457326899008\/timeline\/ 台北市\n大安區忠孝東路四段101巷29號1樓 02 8773 5503 此餐廳本店是Savour Cafe 咖啡\n ...","image":"https:\/\/blog.xuite.net\/kellychen6012003\/twblog1\/348912876\/cover600.jpg"},{"theme":"food","keyword":"台北咖啡廳 美食","title":"瑪格。圖寫生活","url":"https:\/\/margaret.tw\/","description":" 我是瑪格(Margaret Lai)已婚，育有兩個孩子。曾擔任精品業行銷顧問多年，2008\n年2月開始在無名小站寫網誌，長期關注人文藝術、生活美學、美食旅行、繪畫 ...","image":"https:\/\/margaret.tw\/wp-content\/uploads\/90x90.png"},{"theme":"food","keyword":"台北咖啡廳 美食","title":"木白甜點咖啡店- Home | Facebook","url":"https:\/\/www.facebook.com\/Woodxwhite\/","description":" 木白甜點咖啡店, 台北市. ... 木白甜點咖啡店#木白甜點#木白#woodxwhite #行天宮\n甜點#捷運行天宮1號出口#行天宮美食#行天宮咖啡#taipeicafe #taipeifood ...","image":"https:\/\/lookaside.fbsbx.com\/lookaside\/crawler\/media\/?media_id=890951091030686"},{"theme":"food","keyword":"台北咖啡廳 美食","title":"發胖貼文人氣排行榜｜PopDaily 波波黛莉","url":"https:\/\/www.popdaily.com.tw\/explore\/food","description":" 三分半海鮮火鍋#信義區美食#市政府美食#信義區火鍋#台北美食#台北火鍋#美食 ... \nla vie bonbon #角落生物#台北甜點#台北咖啡廳@laviebonbon 聯名可愛的角落 ...","image":"https:\/\/static.popdaily.com.tw\/landingpage\/img\/fbshare.png"},{"theme":"food","keyword":"台北咖啡廳 美食","title":"老派少女| SK Daily・SARA - 生活・食事・到處走走","url":"https:\/\/sk-daily.com\/","description":" 老派少女SARA。生活・食事・到處走走，咖啡跟報紙是每日生活必需品，其他\n時間都在咖啡廳裡看書。HI HI ~ Welcome to SARA's daily life:))I talk about my life,\n ...","image":"https:\/\/sk-daily.com\/wp-content\/uploads\/2020\/09\/resized-image-Promo-3.jpeg"},{"theme":"food","keyword":"台北咖啡廳 美食","title":"大食女in Wonderland :: 痞客邦::","url":"https:\/\/joyaijia.pixnet.net\/blog","description":" Mar 26 2019 16:09 11. 置頂 微風南山美食懶人包！把微風南山當廚房在走的我，\n蒐錄近40家餐廳！看這篇就對了！ Jan 25 2017 19:12 10. 置頂 台北不限時\/有wifi\/\n ...","image":null},{"theme":"food","keyword":"台北咖啡廳 美食","title":"內湖美食｜Vasa瓦薩pizza (內科店) 超Q彈手工披薩，內湖的聚會好所在!","url":"https:\/\/beri.tw\/vasa-pizza\/","description":" 由於莓姬我常在內科遊蕩，其實已經觀望這家餐廳許久，從捷運西湖站2號出口下來\n，可以看到這家店的招牌在...","image":"https:\/\/beri.tw\/wp-content\/uploads\/mix1_Fotor.jpg"},{"theme":"food","keyword":"台北咖啡廳 美食","title":"飛天璇的口袋– 台中美食餐廳x 國內國外旅遊x 親子生活分享x 全台 ...","url":"https:\/\/flyblog.cc\/","description":" 聯絡信箱：carriewang1230@gmail.com台中餐廳美食\/ 國內國外旅遊\/ 親子育兒\n生活\/ 外語導遊領隊 | 飛天璇的口袋.","image":"https:\/\/flyblog.cc\/wp-content\/uploads\/2020\/06\/logo130x130.png"},{"theme":"food","keyword":"台北咖啡廳 美食","title":"阿華田的美食日記","url":"https:\/\/huablog.tw\/","description":" 台北美食 · 【新北美食】板橋巷弄新開幕平價大份量『角落utopia』. 板橋巷弄新\n開幕 ... 【新竹美食】關新東路新開幕『Laid Back Cafe』不限時咖啡廳，舒適寬敞\n的 ...","image":"http:\/\/img.huablog.tw\/uploads\/20180927163916_37-270x270.png"},{"theme":"food","keyword":"台北咖啡廳 美食","title":"靜怡&大顆呆の親子.旅遊.美食 :: 痞客邦::","url":"https:\/\/eeooa0314.pixnet.net\/blog","description":" 台北溫泉餐廳懶人包▷ 北投陽明山7家必泡溫泉▷ 用餐免費泡湯、人氣必吃砂鍋粥\n紗帽山平價溫泉、行義路老字號溫泉! May 28 2020 11:54 3 ...","image":null},{"theme":"food","keyword":"好市多 美食","title":"Kirkland Signature 科克蘭鹽烤夏威夷果仁680公克| Costco 好市多 ...","url":"https:\/\/www.costco.com.tw\/Food\/Snacks\/Nuts-Chips-Rice-Crackers-Jerky\/Kirkland-Signature-Dry-Roasted-Macadamia-680G\/p\/126979","description":" 成份單純：烤夏威夷果仁，海鹽無添加人工色素和香料原產地：澳洲.","image":"https:\/\/www.costco.com.tw\/medias\/sys_master\/images\/hba\/hc9\/31381839478814.jpg"},{"theme":"food","keyword":"好市多 美食","title":"好市多新品「鮭魚親子丼」太誘人網友加碼邪惡吃法| 賣場情報站 ...","url":"https:\/\/www.worldjournal.com\/wj\/story\/121554\/5178911","description":" 美式賣場好市多（Costco）經常不定時推出新商品，吸引不少消費者的目光，近日\n一 ... 美食 賣場情報站 ... 好市多新商品「鮭魚親子丼」，網友吃完大讚划算好吃。","image":"https:\/\/pgw.worldjournal.com\/gw\/photo.php?u=https:\/\/uc.udn.com.tw\/photo\/wj\/realtime\/2021\/01\/16\/11216127.jpg&s=Y&x=0&y=6&sw=720&sh=480&exp=3600"},{"theme":"food","keyword":"好市多 美食","title":"美食達人- udn部落格","url":"http:\/\/blog.udn.com\/blogs\/food","description":" 民以食為天，吃飯皇帝大！ 到處嚐鮮是你生活樂趣，窩在家裡不斷研發美食新口味\n，人生就是立志在創作更多美食體驗嗎？美食達人Blogs，等你入列！有意加入 ...","image":null},{"theme":"food","keyword":"好市多 美食","title":"Re: [問卦] costco美食街點什麼最專業？ - 看板Gossiping - PTT網頁版","url":"https:\/\/www.pttweb.cc\/bbs\/Gossiping\/M.1610812928.A.5E2","description":"好市多就是要在賣場內買綜合壽司、凱撒沙拉、烤大隻雞腿、青醬起司雞肉三明治帶到外面美食區。. 然後在美食區家點熱狗、雞腿堡、濃湯、聖代、漢堡、披薩。. 這樣全部點一份，算是肥宅一人份，可樂則是熱狗送的，別人乾杯，你可以隨意。. 如果吃不飽，可以問五樓推薦什麼酒或餅乾、乳酪。. 大概是這樣。. --. ※ 發信站: 批踢踢實業坊(ptt.cc), 來自: 118.166.33.57 (臺灣). ※ 文章網址: https:\/\/www.ptt.cc\/bbs\/Gossiping\/M.1610812928.A.5E2.html. ","image":null},{"theme":"food","keyword":"好市多 美食","title":"Re: [問卦] costco美食街點什麼最專業？ - 八卦| PTT八卦政治","url":"https:\/\/pttgopolitics.com\/gossiping\/M.1610812928.A.5E2.html","description":" 好市多就是要在賣場內買綜合壽司、凱撒沙拉、烤大隻雞腿、青醬起司雞肉三明治\n帶到外面美食區。 然後在美食區家點熱狗、雞腿堡、濃湯、聖代、漢堡、披薩。","image":null},{"theme":"food","keyword":"好市多 美食","title":"[問題] 好市多的牛肉有種特別的味道？ - cookclub | PTT旅遊美食區","url":"https:\/\/ptttravelfood.com\/cookclub\/M.1610811681.A.683.html","description":" 小弟是烹飪新手一開始買牛肉都是在所在地區的早市購買因為同事推薦好市多的\n牛肉便宜又大碗所以今天馬上殺去好市多買了一條choice等級的嫩肩里肌大約兩週\n前 ...","image":null},{"theme":"food","keyword":"好市多 美食","title":"難抵潮流變化好市多終止所有店內相片沖洗服務| 洛杉磯| 相片洗印 ...","url":"https:\/\/www.epochtimes.com\/b5\/21\/1\/16\/n12691717.htm","description":" 好市多（Costco）近日宣布，將在2月14日關閉旗下約800家商店中所有的相片洗印 \n... 好市多美食廣場的菜單也做了部分調整，價格便宜的組合式披薩片、巴西莓果 ...","image":"https:\/\/i.epochtimes.com\/assets\/uploads\/2021\/01\/GettyImages-1187384017-700x359.jpg"},{"theme":"food","keyword":"好市多 美食","title":"[問題] 好市多的牛肉有種特別的味道？ - 看板cookclub | PTT美食旅遊區","url":"https:\/\/pttfoodtravel.com\/cookclub\/1W0maXQ3","description":" 小弟是烹飪新手一開始買牛肉都是在所在地區的早市購買因為同事推薦好市多的\n牛肉便宜又大碗所以今天馬上殺去好市多買了一條choice等級的嫩肩里肌大約兩週\n前 ...","image":null},{"theme":"food","keyword":"好市多 美食","title":"【台南景點】七股鹽山上竟然長香菇？雖然很可愛，但總感覺哪裡不 ...","url":"https:\/\/decing.tw\/2016-12-30-228\/","description":" 這次的香菇屋固然可愛，但覺得如果把經費花在其他刀口上，應該會更好^^ ... 帶著\n一顆名為【初衷】的心，領著大家一起看見台灣和世界風景，吃遍道地美食與小吃\n ...","image":"https:\/\/decing.tw\/wp-content\/uploads\/20210115210720_86.jpg"},{"theme":"food","keyword":"好市多 美食","title":"【新北新莊美食】韓哥哥銅盤烤肉。部隊鍋火鍋吃到飽，韓式料理 ...","url":"http:\/\/klrosie12.pixnet.net\/blog\/post\/556581758","description":" 可見這四種好禮有多吸引人啊! IMG_7569.JPG. 天使紅蝦肉質Q彈、鮮美多汁。 \n廣島牡蠣飽滿圓潤、滋味 ...","image":"https:\/\/pic.pimg.tw\/klrosie12\/1610615423-3451815614-g_l.jpg"},{"theme":"food","keyword":"好市多 美食","title":"找優惠- GoodLife 好生活- 麥當勞,家樂福,大潤發,好市多,量販店,台鐵 ...","url":"https:\/\/goodlife.tw\/","description":" 找優惠- GoodLife 好生活- 麥當勞,家樂福,大潤發,好市多,量販店,台鐵,高鐵,7-11,\n星巴克,信用卡.","image":"https:\/\/assets.goodlife.tw\/assets\/main_layout\/fb-thumb-d834ff547f2510780040136d8b66859f.jpg"},{"theme":"food","keyword":"好市多 美食","title":"好市多「神級食物」上市！他吃到差點吐：肉超多上架被掃空 ...","url":"https:\/\/www.ettoday.net\/news\/20210115\/1899879.htm","description":" 美式賣場好市多有許多忠實顧客，產品也會推陳出新。一名男子到好市多選購商品\n，意外看見了新出的丼飯，買回家一吃驚為天人，趕緊上網推薦。 (好市多,鮭魚, ...","image":"https:\/\/cdn2.ettoday.net\/images\/5399\/d5399767.jpg"},{"theme":"food","keyword":"好市多 美食","title":"哪個國家是「美食沙漠」去旅遊寧可吃泡麵？網一面倒點名英國| 鄉民 ...","url":"https:\/\/udn.com\/news\/story\/120911\/5175920","description":" 那麼還有哪國也是根本沒有美食，頂多是代表性的食物而已？」 此文一出，大部分\n網友卻都一面倒表示英國更慘，完全 ...","image":"https:\/\/pgw.udn.com.tw\/gw\/photo.php?u=https:\/\/uc.udn.com.tw\/photo\/2021\/01\/15\/1\/11200717.jpg&s=Y&x=121&y=86&sw=500&sh=333&exp=3600"},{"theme":"food","keyword":"好市多 美食","title":"【高雄美食】2021最新高雄必吃美食總整理(火鍋、小吃、早午餐系列 ...","url":"https:\/\/www.bring-you.info\/zh-tw\/kaohsiung-cuisine","description":" 高雄真的很多美食，尤其是小吃、火鍋的部分，這裡整理了多家高雄美食，從西式 \n... 覺得有特色又好吃的店，並不一定全都是CP值高的店，但絕對都是好吃推薦的 ...","image":"https:\/\/www.bring-you.info\/wp-content\/uploads\/2015\/04\/高雄美食好吃比薩-16.jpg"},{"theme":"food","keyword":"好市多 美食","title":"台灣好市多.名產美食代購","url":"https:\/\/www.backpackers.com.tw\/forum\/showthread.php?t=10453425","description":" 涉及金錢交易，特別是機票、哩程、換匯、團購等大額交易，請小心詐騙。參考\n手機認證、註冊日期、過往發文以評估對方信用狀態，並請儘量面交。 2. Line等\n通訊 ...","image":null},{"theme":"food","keyword":"好市多 美食","title":"好市多股份有限公司【徵才職缺簡介】104人力銀行","url":"https:\/\/www.104.com.tw\/company\/18jr3ltc","description":" 【徵才職缺】Assistant Traffic Manager、Inventory Control Specialist、好市多\n物流中心服務員【公司簡介】17 個工作職缺、資本額：44億、員工數：5500人。","image":"https:\/\/static.104.com.tw\/logo\/104logo_200x200_fbogT2.png"},{"theme":"food","keyword":"星巴克 美食","title":"藍色起士的美食主義- 台中美食| 旅遊| 咖啡甜點","url":"https:\/\/blue74.net\/","description":" 活在當下.過的精彩.用力的吃.努力的玩.想學什麼就去學.想做什麼就去做.生命就該\n浪費在美好的人事物上.","image":"https:\/\/img.blue74.net\/uploads\/20170629132843_89-270x270.png"},{"theme":"food","keyword":"星巴克 美食","title":"瑋瑋美食萬歲- 首頁| Facebook","url":"https:\/\/zh-tw.facebook.com\/vivaweiblog\/","description":" 2021.01.15 苗栗大湖美食旅遊｜『一家草莓園』在地人推薦的隱藏版草莓園~滿園\n都是大草莓～品質和價格不會讓你失望! 苗栗地區｜部落客吃喝玩樂, 苗栗大湖(美食\/\n ...","image":"https:\/\/lookaside.fbsbx.com\/lookaside\/crawler\/media\/?media_id=348985955303269"},{"theme":"food","keyword":"星巴克 美食","title":"星巴克草莓季|草莓巧克力塔-發胖板｜PopDaily 波波黛莉","url":"https:\/\/www.popdaily.com.tw\/forum\/food\/877869","description":" 做公益還能吃美食？行善x衣服x美食一把罩~買衣服還送原燒抵用券發現一個覺得滿\n有意義的公益活動~~和男友一人買一件衣服幫助需要幫忙的兒童再也不是只有 ...","image":"https:\/\/www.popdaily.com.tw\/shaper\/u\/202101\/7a47ddbd-e492-4e79-84cc-6eee8cb1343e.jpg?resize-w=1200&resize-h=630"},{"theme":"food","keyword":"星巴克 美食","title":"ㄚ綾綾單眼皮大眼睛- 美食旅遊部落客","url":"https:\/\/y00.tw\/","description":" 美食｜旅遊｜生活｜用照片和文字記錄記錄幸福的生活。","image":"https:\/\/y00.tw\/wp-content\/uploads\/20171013143509_26.png"},{"theme":"food","keyword":"星巴克 美食","title":"林智堅- 【三位大廚來帶路不出國也能吃異國美食】 晚餐吃飽沒？萬惡 ...","url":"https:\/\/www.facebook.com\/permalink.php?id=116135965179713&story_fbid=3529387743854501","description":" 新竹科學園區不只為新竹市帶來龐大的就業機會，同樣也帶來全球各地的美食， ... \n【新竹市立動物園專屬星巴克杯來了】 市民朋友早安，冬天的早晨，一起喝杯熱 ...","image":"https:\/\/lookaside.fbsbx.com\/lookaside\/crawler\/media\/?media_id=3529387397187869"},{"theme":"food","keyword":"星巴克 美食","title":"香蕉草莓的雪國生活","url":"https:\/\/niigata.tw\/","description":" 日本旅遊| 京都賞楓賞櫻| 日本購物| 新潟好吃好玩.","image":"https:\/\/niigata.tw\/wp-content\/uploads\/20171201181707_56.png"},{"theme":"food","keyword":"星巴克 美食","title":"GIORGIO ARMANI","url":"http:\/\/www.bellavita.com.tw\/catalogue\/goodslist.php?d=157","description":" 主題餐廳 · 美食廣場. GIORGIO ARMANI 1F ︱ 02 8789 0886. 新品推薦. GIORGIO \nARMANI CNY草寫Giorgio Armani字體毛衣. GIORGIO ARMANI 前釦環皺褶七分 ...","image":null},{"theme":"food","keyword":"星巴克 美食","title":"台中美食Archives – 剎有其食","url":"https:\/\/safood.tw\/categories\/taichung-food","description":" 台中飲料菜單懶人包| 50嵐、清心福全、喫茶小舖、一芳、茶湯會、大苑子、一沐日\n、台灣第一味、85度c、星巴克、珍煮丹、圓石、麻古茶坊、可不可熟成 ...","image":null},{"theme":"food","keyword":"星巴克 美食","title":"星巴克- 香港- Klook客路香港","url":"https:\/\/www.klook.com\/zh-HK\/activity\/49192-starbucks-hong-kong\/","description":" 於Kook購買Starbucks現金券，享受折扣優惠。 - Klook客路 ... 星巴克HKD50 電子\n現金禮券(只適用於油尖旺及金鐘分店). HK$ 40 50 ... 香港美食推薦. 賀年糕點早鳥 ...","image":"https:\/\/res.klook.com\/images\/fl_lossy.progressive,q_65\/c_fill,w_1200,h_630,f_auto\/w_80,x_15,y_15,g_south_west,l_klook_water\/activities\/gd9xz6lq6aal9n00qb2f\/\/星巴克HKD50電子現金禮券(只適用於油尖旺及金鐘分店).jpg"},{"theme":"food","keyword":"星巴克 美食","title":"星巴克世賢店。以折紙為設計概念的純白不規則建築｜嘉義市唯一現 ...","url":"https:\/\/margaret.tw\/chiayi-starbucks-shixian\/","description":" 星巴克世賢門市以「折紙」設計概念，打造純白色不規則形建築，矗立在阿里山 ... \n越來越興旺，忝為「偽嘉義人」應該盡點心，最近被私訊問行程、美食的機率很 ...","image":"https:\/\/margaret.tw\/wp-content\/uploads\/2021\/01\/nEO_IMG_DSC04609.jpg"},{"theme":"food","keyword":"周姈姈 美食","title":"缺錢才會開！台南新開「最直白的迷你餐車」 超萌肚臍堡咬下爆餡 ...","url":"https:\/\/travel.ettoday.net\/article\/1897188.htm","description":" (負債女孩, 台南美食, 銅板美食, 台南餐車, 達人美食, 美食情報, 台南。愛麗絲的吃不\n停人生Tainan Eat, ) ... 記者周姈姈／綜合報導. 台南一台迷你餐車，招牌寫著「缺 ...","image":"https:\/\/cdn2.ettoday.net\/images\/5392\/d5392388.jpg"},{"theme":"food","keyword":"周姈姈 美食","title":"秒飛日本！南投預約制日式庭園餐廳蛋糕夾了爆汁麝香葡萄超邪惡 ...","url":"https:\/\/www.ettoday.net\/news\/20210116\/1898827.htm","description":" 記者周姈姈／綜合報導. 一秒到日本！南投埔里一間預約制日式庭園餐廳，只營業中\n、下午時間，整個園區瀰漫濃厚的日本風格，光是入口處的大門就韻味十足， ...","image":"https:\/\/cdn2.ettoday.net\/images\/5396\/d5396874.jpg"},{"theme":"food","keyword":"周姈姈 美食","title":"高雄最轟動火烤兩吃開了！和牛壽司、蟹膏粥無限嗑未來要開24小時 ...","url":"https:\/\/will-news.info\/2021\/01\/15\/%E9%AB%98%E9%9B%84%E6%9C%80%E8%BD%9F%E5%8B%95%E7%81%AB%E7%83%A4%E5%85%A9%E5%90%83%E9%96%8B%E4%BA%86%EF%BC%81%E5%92%8C%E7%89%9B%E5%A3%BD%E5%8F%B8%E3%80%81%E8%9F%B9%E8%86%8F%E7%B2%A5%E7%84%A1%E9%99%90\/","description":" 記者周姈姈／綜合報導. 轟動高雄人的「韓八韓日燒肉鍋物」開幕了 ... 韓八提供8種\n肉品，想吃多少都可以。（圖／《捲捲&土豆拿鐵美食\/旅遊\/生活》提供，下同）.","image":"https:\/\/will-news.info\/wp-content\/uploads\/2021\/01\/d5396108.jpg"},{"theme":"food","keyword":"周姈姈 美食","title":"[新聞] 台北福華今晚6點送走俄舞團44人！業者： | PTT 熱門文章Hito","url":"https:\/\/ptthito.com\/hatepolitics\/m-1608202621-a-a57\/","description":" 完整新聞內容︰記者周姈姈／台北報導中央流行疫情指揮中心16日公布4名莫斯科\n古典芭蕾舞團成員確診，而今日經過二採後，剩餘的48名成員其中又多了4位確診 ...","image":null},{"theme":"food","keyword":"麻古茶坊 美食","title":"LIFESTYLE","url":"https:\/\/www.marieclaire.com.tw\/lifestyle","description":" LIFESTYLE 美食. 芋頭控必喝！麻古茶坊推「芋泥波波布蕾」喝得到芋頭顆粒搭配\n布丁、芋圓、小珍珠，每一口都是滿滿驚喜. 芋頭控預備備！麻古茶坊推「芋泥波 ...","image":"https:\/\/i.marieclaire.com.tw\/assets\/www\/images\/mctw_logo.jpg"},{"theme":"food","keyword":"麻古茶坊 美食","title":"麻古茶坊「芋泥波波布蕾」滿滿5層料！芋頭手搖＋布蕾，喝的甜點太 ...","url":"https:\/\/udn.com\/news\/story\/7186\/5178721","description":" 芋頭手搖＋布蕾，喝的甜點太療癒. 2021-01-16 13:02 聯合新聞網\/ 旅遊美食綜合\n報導.","image":"https:\/\/pgw.udn.com.tw\/gw\/photo.php?u=https:\/\/uc.udn.com.tw\/photo\/2021\/01\/16\/1\/11215467.jpg&s=Y&x=0&y=0&sw=1280&sh=853&exp=3600"},{"theme":"food","keyword":"麻古茶坊 美食","title":"凱西跳跳糖の美食旅遊","url":"https:\/\/jumpingsugar.com\/","description":" 美食、旅遊、攝影、特賣會分享. ... 【台北美食】完鍋子熱炒市民大道特色熱炒店! \n... 台北內湖飲料店懶人包！50嵐、麻古茶坊、珍煮丹、珍蜜堂、康青龍、國民茶鋪\n、 ...","image":"https:\/\/i2.zi.org.tw\/jumpingsugar\/2020\/06\/1592926348-9cf3bb395019389e9c1cadfa664e72e4-270x270.jpg"},{"theme":"food","keyword":"麻古茶坊 美食","title":"麻古茶坊「芋泥波波布蕾」滿滿5層料！芋頭手搖＋布蕾，喝的甜點太 ...","url":"https:\/\/style.udn.com\/style\/story\/11350\/5178721?from=udn-referralnews_ch2002artbottom","description":" 麻古茶坊繼「芋泥波波鮮奶」後再升級，首創芋頭手搖搭布蕾組合「芋泥波波布蕾\n」，芋泥、鮮奶、珍珠. ... 2021-01-16 13:02聯合新聞網旅遊美食綜合報導 ...","image":"https:\/\/pgw.udn.com.tw\/gw\/photo.php?u=https:\/\/uc.udn.com.tw\/photo\/2021\/01\/16\/1\/11215467.jpg&s=Y&x=0&y=0&sw=1280&sh=853&sl=W&fw=800"},{"theme":"food","keyword":"麻古茶坊 美食","title":"搶喝！麻古茶坊「芋泥波波」第二彈狂咬珍珠、小芋圓還有濃郁布蕾 ...","url":"https:\/\/www.ettoday.net\/news\/20210116\/1899495.htm","description":" 以芝芝系列讓人欲罷不能的人氣手搖飲品牌「麻古茶坊」，繼上月推出罪惡「芋泥\n波波鮮奶」後，這次又打造全新芋頭飲品「芋泥波波布蕾」了，綿密的芋泥搭配Q \n... 麻古茶坊芋頭系列第二彈「芋泥波波布蕾」開喝。 ... 關鍵字： 美食情報 麻古茶\n坊.","image":"https:\/\/cdn2.ettoday.net\/images\/5399\/d5399343.jpg"},{"theme":"food","keyword":"麻古茶坊 美食","title":"麻古茶坊「芋泥波波布蕾」滿滿5層料！芋頭手搖＋布蕾，喝的甜點太 ...","url":"https:\/\/ciaolife.com.tw\/archives\/98506","description":" 潮Life│潮蝦趴│潮話題│四腳潮天│潮親子│潮自我│潮天宮│潮澎湃│潮生活.","image":"https:\/\/ciaolife.com.tw\/wp-content\/uploads\/2021\/01\/11215467.jpgsYx0y0sw1280sh853exp3600.jpeg"},{"theme":"food","keyword":"麻古茶坊 美食","title":"麻古茶坊菜單｜Taipei City 推薦餐廳| foodpanda 外送","url":"https:\/\/www.foodpanda.com.tw\/chain\/cl1qw\/ma-gu-cha-fang","description":" 麻古茶坊在foodpanda點的到，更多Taipei City 推薦美食，線上訂立即送，下載\nfoodpanda APP，20分鐘外送上門！瀏覽菜單和獨家優惠折扣.","image":null},{"theme":"food","keyword":"麻古茶坊 美食","title":"高雄輕軌2\/28前全線免費搭！新增大南環段9車站過年到壽山超方便 ...","url":"https:\/\/travel.ettoday.net\/article\/1900024.htm","description":" 電腦版 · 新聞焦點 主題旅遊 暢遊台灣 放眼海外 飯店旅館 交通資訊 美食地圖 優惠\n快訊 農遊票選 日本旅遊 專欄 ... 麻古茶坊「芋泥波波」第二彈放了布蕾 · 寫手名稱.","image":"https:\/\/cdn2.ettoday.net\/images\/5400\/d5400125.jpg"},{"theme":"food","keyword":"麻古茶坊 美食","title":"台中美食Archives – 剎有其食","url":"https:\/\/safood.tw\/categories\/taichung-food","description":" 通庵咖哩台中| 今天小剎來介紹台中審計新村美食，台北超人氣咖哩來台中插 ... 圓\n石、麻古茶坊、可不可熟成紅茶、MR.wish、萬波、甲文青、康青龍、別茶人、拾 ...","image":null},{"theme":"food","keyword":"麻古茶坊 美食","title":"麻古茶坊(板橋中山店)-門市儲備幹部","url":"https:\/\/www.518.com.tw\/job-y24mo1.html","description":" 麻古茶坊股份有限公司誠摯招募麻古茶坊(板橋中山店)-門市儲備幹部，1.門市營運\n管理、用人管理、商圈經營管理、人員教育訓練2.完整教育訓練,良好升遷管道,調酒\n ...","image":"https:\/\/statics.518.com.tw\/img\/index\/public\/og_image_bearworks_155x155.png"},{"theme":"food","keyword":"麻古茶坊 美食","title":"Foody 吃貨","url":"https:\/\/cs-cz.facebook.com\/foodytw\/videos\/2069706993344209\/","description":" 豐原必吃排骨酥麵到底哪家好吃!? 在地人也推薦的美食名單～ · Foody 吃貨 ... 麻古\n茶坊新推「芋泥波波布蕾」!♥(´∀` )人「大甲芋泥＋滑嫩布蕾」這組合太邪惡～.","image":"https:\/\/lookaside.fbsbx.com\/lookaside\/crawler\/media\/?media_id=2069706993344209&get_thumbnail=1"},{"theme":"food","keyword":"麻古茶坊 美食","title":"Foody 吃貨- 日本No.1泡芙「草莓捲捲千層」( д ) 酥脆口感草莓香 ...","url":"https:\/\/www.facebook.com\/foodytw\/videos\/%E6%97%A5%E6%9C%ACno1%E6%B3%A1%E8%8A%99%E8%8D%89%E8%8E%93%E6%8D%B2%E6%8D%B2%E5%8D%83%E5%B1%A4-%D0%B4-%E9%85%A5%E8%84%86%E5%8F%A3%E6%84%9F%E8%8D%89%E8%8E%93%E9%A6%99%E6%92%B2%E9%BC%BB\/2898505723805182\/","description":" 在地人也推薦的美食名單～… More - 感謝鹹菜日常Derek & Randy 授權更多高 ... \n麻古茶坊新推「芋泥波波布蕾」!♥(´∀` )人「大甲芋泥＋滑嫩布蕾」這組合太邪惡 ...","image":"https:\/\/lookaside.fbsbx.com\/lookaside\/crawler\/media\/?media_id=2898505723805182&get_thumbnail=1"},{"theme":"food","keyword":"麻古茶坊 美食","title":"麻古茶坊「芋泥波波布蕾」搶攻最強芋頭手搖飲，大甲芋頭","url":"https:\/\/www.walkerland.com.tw\/subject\/view\/285125?utm_source=fb&utm_medium=news%28E%29285125&utm_term=%E9%BA%BB%E5%8F%A4-WL-FB","description":" 讓網友一致好評「喝了一口就停不下來」的麻古茶坊，這次又推出超強芋頭手搖飲\n新品，用整杯滿滿的配料讓 ... 現在用手機就可以找到WalkerLand推薦的附近美食.","image":"https:\/\/www.walkerland.com.tw\/image\/subject\/2021\/01\/74afced303b157b56a8d465cb6aaccc7c85e4378.jpg"},{"theme":"food","keyword":"麻古茶坊 美食","title":"【全台】芋頭新品第二彈! 麻古茶坊「芋泥波波布蕾」邪惡上市滿料 ...","url":"https:\/\/www.foodytw.com\/article\/92354","description":" ▽麻古茶坊先前推出的新品「芋泥波波鮮奶」，以濃郁大甲芋泥＋小珍珠＋芋圓的\n邪惡組合已經讓芋頭控們嗨翻！不過，麻古茶坊沒有要放過大家的意思ＸＤ又加碼\n ...","image":"https:\/\/www.foodytw.com\/upload\/article_cover\/1200x630\/92354.jpg"},{"theme":"food","keyword":"布朗尼 美食","title":"台南美食彙整- 口袋吃吃五十咩","url":"https:\/\/etaiwan.blog\/category\/eat-taiwan\/tainan\/","description":" ... 用餐環境讓人放鬆自在地享用美食,冬天還有季節限定草莓三明治台南市東區|夏末 \n... 歡迎來到台南草莓的伸展舞台，爆料草莓冰\/雪花冰、草莓布朗尼、草莓飲料…","image":"http:\/\/img.etaiwan.blog\/uploads\/20170512135432_33-270x270.png"},{"theme":"food","keyword":"布朗尼 美食","title":"[商品] 7-11 草莓玫瑰花塔- cvs | PTT旅遊美食區","url":"https:\/\/ptttravelfood.com\/cvs\/M.1610809902.A.82B.html","description":" 1F推pttton: 布朗尼也在7-11買的嗎？買二送一？ 01\/16 23:17. 2F推qazqwe: 我覺得\n那個布朗尼不好吃欸是一個很廉價的巧克力味！ 01\/16 23:28. ‣ 返回cvs 看板 ...","image":null},{"theme":"food","keyword":"布朗尼 美食","title":"毛毛's 吃美食愛旅遊日誌 - 旅遊抹茶美食住宿食譜","url":"https:\/\/ladymoko.com\/","description":" 好吃清爽多層次的抹茶布朗尼芝麻塔Matcha Brownie Tarte食譜推薦！搭配抹茶、\n黑芝麻雙口味奶油乳酪cream cheese，真是好吃到不行，很抹、很濃郁的抹茶白 ...","image":"https:\/\/img.ladymoko.com\/uploads\/20160930195615_20.png"},{"theme":"food","keyword":"布朗尼 美食","title":"阿宏師涼麵王周邊『美食餐廳』| 精選TOP 15間熱門店家- 愛食記","url":"https:\/\/ifoodie.tw\/explore\/list?restaurant=6002c3c822613903e03943e9","description":" ... 日常經典x 日常野草| 日常聚落Daily Piazza：TAGather Goods x Daily Green, \nChance Cafe & Bar 勸世吧, 賴桑透抽蚵仔麵線, Mr.Brownie黑熊先生巧克力布朗尼,\n ...","image":"https:\/\/lh3.googleusercontent.com\/fkDf_tR8J4VR-jvblMHuQpfLAjCSkFmGN8IXYRc7nWKd6jEhcuLgA-tN8ihv49Y2_rJS5m0lZL2YivVU2dlEmOzlvy6vt6Q=s600"},{"theme":"food","keyword":"布朗尼 美食","title":"宅配美食- 睿睿の奇幻成長日記","url":"https:\/\/familytravel.tw\/category\/taiwan-food\/%E5%AE%85%E9%85%8D%E7%BE%8E%E9%A3%9F\/","description":" 大家都知道睿爸是一個很愛吃巧克力的男人，睿媽趁著這次白色情人節訂了睿爸\n最愛的特濃皇家布朗尼（心型）跟睿媽最愛的靜岡極濃抹茶生巧克力！ 起士公爵的\n ...","image":"https:\/\/familytravel.tw\/wp-content\/uploads\/2020\/08\/cropped-IMG_7351-scaled-1.jpg"},{"theme":"food","keyword":"布朗尼 美食","title":"三寸日光咖啡店","url":"https:\/\/www.facebook.com\/sunlight3333\/posts\/3694688957245508","description":" ... 一件雨衣🤣🤣🤣🤣 冷氣團什麼的根本a piece of cake🤷‍♂️ ——-今天甜點有——\n- +抹茶草莓千層+草莓波士頓+70%生巧克力塔+芝麻提拉米蘇+布朗尼+香蕉蛋糕.","image":"https:\/\/lookaside.fbsbx.com\/lookaside\/crawler\/media\/?media_id=3694688900578847"},{"theme":"food","keyword":"布朗尼 美食","title":"大溪70年老店-杏芳食品- 師傅不小心透露了乳酪球的秘密... #乳酪球 ...","url":"https:\/\/zh-tw.facebook.com\/shingfengpastry\/posts\/1025184477535096\/","description":" 師傅不小心透露了乳酪球的秘密... #乳酪球#布朗尼#蔓越莓乳酪球.","image":"https:\/\/scontent-atl3-2.xx.fbcdn.net\/v\/t45.1600-4\/cp0\/q90\/spS444\/c60.0.360.360a\/12520924_6038129015056_790947778_n.png.jpg?_nc_cat=109&ccb=2&_nc_sid=67cdda&_nc_ohc=MtQdxa39E0QAX_8ZJAn&_nc_ht=scontent-atl3-2.xx&oh=e79125f76bd6301e4f5d7641eb62b5df&oe=60299FB4"},{"theme":"food","keyword":"布朗尼 美食","title":"7-Eleven: 【#新品推介】身為朱古力狂迷，見到濃郁朱古力產品點都 ...","url":"https:\/\/www.groupbuya.com\/jetso\/267359","description":" 百邦濃厚朱古力布朗尼同濃厚牛奶朱古力布朗尼絕對滿足到你嘅朱古力慾望～特濃\n朱古力配上鬆軟嘅布朗尼，令你一試難忘！ 7-Eleven@2018年10月25日. 詳細; \n圖片 ...","image":"https:\/\/storage.googleapis.com\/i.groupbuya.com\/images\/promo\/59\/267359\/267359_n.jpg"},{"theme":"food","keyword":"布朗尼 美食","title":"休閒零嘴\/餅乾- 全家行動購","url":"https:\/\/mart.family.com.tw\/v2\/official\/SalePageCategory\/28341","description":" 【ＣＷ】布朗尼風味餅198g\/包. NT$259. NT$189 · 【ＣＷ】可可豆風味麻糬餅\n240g\/包. NT$259. NT$189 · 【宅間】紅罐什錦豆米果194g\/包. NT$350. NT$239.","image":null},{"theme":"food","keyword":"布朗尼 美食","title":"[商品] 7-11 草莓玫瑰花塔- 看板CVS | PTT美食旅遊區","url":"https:\/\/pttfoodtravel.com\/CVS\/1W0m8kWh","description":" 布朗尼也在7-11買的嗎？買二送一？ 01\/16 23:17, 1 F. ‣ 返回看板[ CVS ] 資訊 · ‣ \n更多Webden 的文章. 文章代碼(AID): #1W0m8kWh (CVS). CVS 近期熱門文章 ...","image":"https:\/\/i.imgur.com\/N9elG4L.jpg"},{"theme":"food","keyword":"布朗尼 美食","title":"翻白眼鬆餅BAR 菜單｜New Taipei City 推薦餐廳| foodpanda 外送","url":"https:\/\/www.foodpanda.com.tw\/chain\/cn0nc\/fan-bai-yan-song-bing-bar","description":" 翻白眼鬆餅BAR 在foodpanda點的到，更多New Taipei City 推薦美食，線上訂立即\n送，下載foodpanda APP，20分鐘外送 ... 想外送美食到你府上？ ... 不是布朗尼.","image":null},{"theme":"food","keyword":"布朗尼 美食","title":"台南美食地圖‧玩樂誌- 分享台南在地私房巷弄美食景點生活旅遊住宿資訊","url":"https:\/\/foodintainan.com.tw\/","description":" 以台南美食旅遊景點時事為主，包含巷弄裡的老台南美食、在地人吃的隱藏版台南\n美食、台南夜市必吃美食、台南旅遊景點美食。","image":"https:\/\/foodintainan.com.tw\/wp-content\/uploads\/20190913161256_75.jpg"},{"theme":"food","keyword":"布朗尼 美食","title":"台中｜桐生日式可麗餅軟軟ㄉ日式可麗餅最適合當下午茶甜點","url":"https:\/\/www.popdaily.com.tw\/forum\/food\/878017","description":" 布朗尼甜甜的口感搭配微苦的抹茶苦甜苦甜的搭配中和起來很適合聽到店員說抹茶\n冰淇淋是免費加ㄉ我和 @ning.foodie 即使在寒冬中也是加下去（加啦！哪次不加（\n ...","image":"https:\/\/www.popdaily.com.tw\/shaper\/u\/202101\/9efa515b-3774-469b-adb5-87f3e4984309.jpg?resize-w=1200&resize-h=630"},{"theme":"food","keyword":"布朗尼 美食","title":"甜而不膩又扎實！連男生都愛吃的美式布朗尼：「coco Brownies ...","url":"https:\/\/www.shoppingdesign.com.tw\/post\/view\/3328","description":" 平日供應多達15種口味，包括棉花糖、奧利歐餅乾、肉桂蘋果、花生醬、培根…，\n每個人絕對可以找到自己最愛那一款。","image":"https:\/\/bnextmedia.s3.hicloud.net.tw\/image\/album\/2018-09\/img-1537933596-66441.jpg"},{"theme":"food","keyword":"布朗尼 美食","title":"Chick-fil-A 一月送出免費的巧克力布朗尼(～1\/23止)","url":"https:\/\/www.sofunsd.com\/chick-fil-a-%E4%B8%80%E6%9C%88%E9%80%81%E5%87%BA%E5%85%8D%E8%B2%BB%E7%9A%84%E5%B7%A7%E5%85%8B%E5%8A%9B%E5%B8%83%E6%9C%97%E5%B0%BC%EF%BD%9E1-23%E6%AD%A2\/?amp","description":" Chick-fil-A在一月份開始贈送免費的巧克力布朗尼(chocolate fudge brownie) 給\n顧客，以包辦下午茶的點心概念來向顧客表示「感謝」。Chick-fil-A的會員可以在1\n ...","image":"https:\/\/i0.wp.com\/www.sofunsd.com\/wp-content\/uploads\/2021\/01\/Chocolate-Fudge-Brownie2.jpg?fit=1280%2C720&ssl=1"},{"theme":"food","keyword":"布朗尼 美食","title":"【台南美食】傳說中的嬌貴布丁!!!胖胖玻璃瓶綿密焦糖布丁限定販售 ...","url":"https:\/\/aliceeat.com\/nextdoor\/","description":" 這次來跟大家分享這家在IG上蠻受到大家歡迎《NEXT DOOR 嗝。壁》. 主要是英式\n司康系列、磅蛋糕系列、瑪芬系列、綿密焦糖布丁、義式提拉米蘇、布朗尼.","image":"https:\/\/aliceeat.com\/wp-content\/uploads\/20200719153433_51.jpg"},{"theme":"food","keyword":"中山站 美食","title":"台北_美食彙整- 老派少女| SK Daily・SARA","url":"https:\/\/sk-daily.com\/category\/taiwan-food\/taipei-food\/","description":" 下班後來到就在捷運信義安和站附近的「湘8老」湘菜料理餐廳，是彭園餐廳旗下新\n品牌！每一道功夫菜都展現湘菜料理的美味精髓，平價的湘菜料理餐廳推薦給 ...","image":"https:\/\/sk-daily.com\/wp-content\/uploads\/2020\/09\/resized-image-Promo-3.jpeg"},{"theme":"food","keyword":"中山站 美食","title":"「捷運：中山站」Parko Parco 義大利牛肚包中山店@ 陳凱莉～台北 ...","url":"https:\/\/blog.xuite.net\/kellychen6012003\/twblog1\/589415468","description":" 陳凱莉～台北人捷運美食、吃好吃巧、世界走透透. 웃Time is not reversible.When \ntime ... 202010172105「捷運：中山站」Parko Parco 義大利牛肚包中山店 ?中山.","image":"https:\/\/blog.xuite.net\/kellychen6012003\/twblog1\/589415468\/cover600.jpg"},{"theme":"food","keyword":"中山站 美食","title":"Maruko與美食有個約會","url":"https:\/\/maruko.tw\/","description":" Maruko(丸子)一個喜愛美食與日本旅遊的大孩子，我喜歡用照片記錄生活點滴與\n美好事物，更喜愛烹飪、分享料理。更多請看：關於我合作｜邀 ...","image":"https:\/\/maruko.tw\/wp-content\/uploads\/2020\/12\/IMG_0028.png"},{"theme":"food","keyword":"中山站 美食","title":"#按讚分享送美味必點涼拌菜#尖椒螺片木瓜螺營養豐富，食療功效高 ...","url":"https:\/\/www.facebook.com\/aoba1964\/posts\/10157307790152924","description":" 地址：台北市中山區中山北路一段105巷10號 ... 台北 #台北美食#台北餐廳 #台菜\n餐廳 #台灣美食 #台湾美食 #台菜 #中山美食 #捷運中山站 #捷運美食 #青葉 #台菜 ...","image":"https:\/\/lookaside.fbsbx.com\/lookaside\/crawler\/media\/?media_id=10157307790102924"},{"theme":"food","keyword":"中山站 美食","title":"痞客邦美食","url":"https:\/\/food.pixnet.net\/","description":" 布咕布咕美食小... 捲捲和土豆拿鐵 · PEKO のSimple ... 本日熱門文章. 福元胡椒餅｜\n華陰街必吃美食飄香20年以上！網友大呼「吃 ... 雪西食記|中山站美食|貓妝自家.","image":null},{"theme":"food","keyword":"中山站 美食","title":"Hera Cafe - . New Menu part 2 11\/11 Hera即將滿一年囉 ...","url":"https:\/\/pt-br.facebook.com\/heracafe.co\/posts\/new-menu-part-21111-hera%E5%8D%B3%E5%B0%87%E6%BB%BF%E4%B8%80%E5%B9%B4%E5%9B%89%E6%84%9F%E8%AC%9D%E9%80%99%E4%B8%80%E5%B9%B4%E5%A4%A7%E5%AE%B6%E7%9A%84%E9%97%9C%E6%87%B7%E5%A5%BD%E5%A4%9A%E7%86%9F%E5%AE%A2%E9%83%BD%E8%AE%8A%E6%9C%8B%E5%8F%8B%E8%8F%9C%E5%96%AE%E5%93%81%E9%A0%85%E4%B9%9F%E8%AA%BF%E6%95%B4%E5%A2%9E%E5%8A%A0%E4%BA%86%E4%B8%80%E4%BA%9B%E6%96%B0%E7%9A%84%E4%B8%80%E5%B9%B4%E9%82%84%E8%AB%8B%E5%A4%9A%E5%A4%9A%E6%8C%87%E6%95%99-1111-%E9%80%B1%E5%B9%B4%E6%85%B6%E6%B4%BB\/2291797731050557\/","description":" ... 手沖咖啡 #手作甜點 #台北咖啡 #中山站美食 #戚風蛋糕 #紅鶴 #不限時咖啡廳 #\n網美咖啡廳 #台灣美食 #赤峰街 #雪藏生乳酪 #客製化蛋糕 #週歲蛋糕 #Hera週年慶.","image":"https:\/\/lookaside.fbsbx.com\/lookaside\/crawler\/media\/?media_id=2291797731050557"},{"theme":"food","keyword":"中山站 美食","title":"#抹茶布丁開放台大公館店取貨囉抹茶控好友夢寐以求的中秋禮盒 ...","url":"https:\/\/es-la.facebook.com\/iwanticesomuch\/posts\/2001565566573861\/","description":" 好想吃冰 #好想吃冰かき氷 #中秋節快樂 #中秋美食 #枺茶布丁#抹茶控#台北美食 #\n台北 #中山美食 #捷運中山站#中山站美食#日式剉冰 #日式蔬食 #蔬食.","image":"https:\/\/lookaside.fbsbx.com\/lookaside\/crawler\/media\/?media_id=2001565566573861"},{"theme":"food","keyword":"中山站 美食","title":"大食女in Wonderland :: 痞客邦::","url":"https:\/\/joyaijia.pixnet.net\/blog","description":" [台北美食] 中山紅豆湯麻糬伯-手工麻糬、沒預訂買不到的粉粿！(附價位) 中山站\n美食\/台北甜點\/台北下午茶\/台北小吃 · Jan 05 2021 00:00 2 ...","image":null},{"theme":"food","keyword":"中山站 美食","title":"中山站那邊有個郵局從幾號出口會通到那間郵局呢?還有營業@ 10401 ...","url":"http:\/\/sex1014021.pixnet.net\/blog\/post\/72425542","description":" 中山站美食,中山站剪髮,中山站餐廳,捷運中山站,中山站下午茶,中山站好吃,中山站\n髮廊,中山站鬆餅,中山站義大利麵,中山站剪頭髮中山站,郵局,幾號出口,中山北路,\n台北 ...","image":null},{"theme":"food","keyword":"中山站 美食","title":"金大佛的奪門而出家網誌- 整個世界都是我的耍廢館","url":"https:\/\/yama.tw\/","description":" 麵屋千雲是朋友推薦給我的中山站宵夜，一家營業到凌晨三點的深夜美食，位於\n中山条通商圈、林森北路一帶，強打濃郁的雞白湯拉麵及沾麵。剛好上周入住台北\n ...","image":"https:\/\/yama.tw\/wp-content\/uploads\/20170430132853_85-270x270.png"},{"theme":"food","keyword":"中山站 美食","title":"中山站餐廳：La Bocca 義式手作披薩！台北義式披薩推薦","url":"https:\/\/www.mecocute.com\/pizza-la-bocca\/","description":" 台北捷運中山站附近美食餐廳「La Bocca 義式手作披薩」菜單提供正統道地義式\n披薩，不用飛義大利也能吃到經典義式披薩，喜歡吃披薩的人千萬不要錯過。","image":"https:\/\/live.staticflickr.com\/65535\/50836759371_9d54fede5a_b.jpg"},{"theme":"food","keyword":"中山站 美食","title":"【台北\/食記】晴光美食、中山國小站美食推薦！無限續咖哩醬、白飯 ...","url":"https:\/\/kitty13143005.pixnet.net\/blog\/post\/353342074-%E3%80%90%E5%8F%B0%E5%8C%97-%E9%A3%9F%E8%A8%98%E3%80%91%E6%99%B4%E5%85%89%E7%BE%8E%E9%A3%9F%E3%80%81%E4%B8%AD%E5%B1%B1%E5%9C%8B%E5%B0%8F%E7%AB%99%E7%BE%8E%E9%A3%9F%E6%8E%A8","description":" 繼續來推薦我熱愛的咖哩餐廳！這次想分享的是已經超級有名的「十巷咖哩」！ 十\n巷咖哩位在晴光市場，靠近中山國小站、中山商圈，而店家除了以平價、美味著稱\n ...","image":"https:\/\/pic.pimg.tw\/kitty13143005\/1610437158-1082231788-g_n.jpg"},{"theme":"food","keyword":"中山站 美食","title":"【新北美食】板橋巷弄新開幕平價大份量『角落utopia』漢堡專賣店 ...","url":"https:\/\/huablog.tw\/utopia\/","description":" 捷運中山站必吃韓式料理。正統道地韓國味！ 【台北美食】宜蘭礁溪超夯『白水\n豆花』來台北永康街啦！必點麥芽糖花生 ...","image":"https:\/\/img.huablog.tw\/uploads\/20210115013620_13.jpg"},{"theme":"food","keyword":"中山站 美食","title":"黑皮的旅遊筆記-","url":"https:\/\/happytravel.tw\/","description":" 南投伴手禮，宅配推薦『CONA'S CHOCOLATE... 2020.12.28. 台北中山站美食。\nGocha Bar果汁吧｜2020 ...","image":"https:\/\/img.happytravel.tw\/uploads\/20190227120733_88-270x270.png"},{"theme":"food","keyword":"中山站 美食","title":"請問從中山站要轉乘636公車去新莊,從幾號出口出來比較近? @ 《爭 ...","url":"http:\/\/toye44403.pixnet.net\/blog\/post\/60213064","description":" 中山站美食,中山站剪髮,中山站餐廳,捷運中山站,中山站下午茶,中山站好吃,中山站\n髮廊,中山站鬆餅,中山站義大利麵,中山站剪頭髮中山站,新莊,公車,樂生療養院,出口,\n ...","image":null},{"theme":"food","keyword":"中山站 美食","title":"新竹市東區美食推薦三河中川屋鰻魚飯","url":"https:\/\/www.walkerland.com.tw\/article\/view\/285085","description":" 【台北美食】三河中川屋鰻魚飯／中山捷運站～鰻魚飯專賣店，日本關西風道地\n鰻魚飯，魚嫩無腥味，魚刺都能吃下肚. 分享. 饅頭弟造訪三河中川 ...","image":"https:\/\/www.walkerland.com.tw\/image\/poi\/p109932\/m19129\/50e69388cb98c0347f0e1a64a14cef416a7249eb.jpg"},{"theme":"food","keyword":"中山站 美食","title":"台北市美食推薦Pizza La Bocca 義式手作披薩『不要錯過這間超好吃 ...","url":"https:\/\/ifoodie.tw\/blog\/6002ea6cbe6e2814c13d1b4e-%E4%B8%8D%E8%A6%81%E9%8C%AF%E9%81%8E%E9%80%99%E9%96%93%E8%B6%85%E5%A5%BD%E5%90%83%E6%8A%AB%E8%96%A9%EF%BC%81%E5%85%AB%E5%90%8B%E6%8A%AB%E8%96%A9%E5%85%A9%E7%99%BE%E5%85%83%E8%B5%B7","description":" 台北捷運中山站附近美食餐廳「La Bocca 義式手作披薩」菜單提供正統道地義式\n披薩，不用飛義大利也能吃到經典義式披薩，喜歡吃披薩的人千萬不要錯過。","image":"https:\/\/live.staticflickr.com\/65535\/50836759371_9d54fede5a_b.jpg"},{"theme":"food","keyword":"米其林 美食","title":"【2019米其林必比登推薦】藍家割包- 捷運公館站的台大排隊小吃 ...","url":"https:\/\/www.klook.com\/zh-TW\/activity\/20484-lan-jia-gua-bao-taipei\/","description":" 榮獲2019米其林必比登推薦的「藍家割包」來啦！沒有吃過藍家割包，別說你來過\n公館商圈。滑嫩到入口即化五花滷肉搭配鹹香的炒酸菜與帶有顆粒口感的花生粉，\n ...","image":"https:\/\/res.klook.com\/images\/fl_lossy.progressive,q_65\/c_fill,w_1200,h_630,f_auto\/w_80,x_15,y_15,g_south_west,l_klook_water\/activities\/ykjtor4veqhakuizgolo\/\/藍家割包-捷運公館站.jpg"},{"theme":"food","keyword":"米其林 美食","title":"剎有其食– 台中美食。日本旅遊。小剎廚房。團購美食超市","url":"https:\/\/safood.tw\/","description":" 你的美食好朋友，分享台中美食、國內旅遊、日本旅遊、生活密技以及親子育兒等\n情報，今年是經營網站第15年，歡迎跟我們一起吃喝玩樂過生活！","image":null},{"theme":"food","keyword":"米其林 美食","title":"【米其林年菜】過年圍爐摘星星！山海樓、大三元、欣葉台菜、點水 ...","url":"https:\/\/www.upmedia.mg\/news_info.php?SerialNo=104660","description":" 然而眾多的選項中，要如何端上桌就吸引大家的目光，選擇獲得米其林推薦餐廳就\n對了！不只美觀、美味，在星星的加持之下，更讓一家團聚的圍爐宴充滿星光閃耀\n。","image":"https:\/\/www.upmedia.mg\/upload\/article\/20210115184410432374.jpg"},{"theme":"food","keyword":"米其林 美食","title":"台北市信義區美食推薦添好運(台北信義店)『[台北美食]添好運台北 ...","url":"https:\/\/www.walkerland.com.tw\/article\/view\/285104","description":" [台北美食]添好運台北信義店\/米其林港點美味又便宜\/防疫有一套掃碼點餐真方便\/\n新春想要添好運就來添好運\/. 分享. elephant造訪添好運(台北信義店). 本次滿意度：\n ...","image":"https:\/\/www.walkerland.com.tw\/image\/poi\/p47536\/m74050\/670859e86de88e53b0b2cc4a9463d2f9ff8083ed.jpg"},{"theme":"food","keyword":"米其林 美食","title":"【中肯‧食記】雄記蔥抓餅．捷運公館站｜2020米其林必比登推薦美食 ...","url":"http:\/\/takeshi0312.pixnet.net\/blog\/post\/45003783","description":" 公館夜市米其林小吃．台大商圈排隊蔥抓餅．！ 0.","image":"https:\/\/live.staticflickr.com\/65535\/50817766536_5f5dcd54c4_b.jpg"},{"theme":"food","keyword":"米其林 美食","title":"Taster 美食加","url":"https:\/\/taster.life\/","description":" 這裡有很多愛吃的人，美食是我們最重要的身分認同。即時頭條、流行趨勢、娛樂\n情報、消費指南、專家觀點，通通報給你知，當然，主題都是吃。 Taster 是你最 ...","image":"https:\/\/taster.life\/wp-content\/uploads\/2018\/07\/540X281無中文.png"},{"theme":"food","keyword":"米其林 美食","title":"「美食外帶超方便 」 台中J-Mall店新增外帶窗口想在家享用米其林 ...","url":"https:\/\/www.facebook.com\/HawkerChan.Taiwan\/posts\/895118347310417\/","description":" 「美食外帶超方便 」 台中J-Mall店新增外帶窗口想在家享用米其林美食的你外帶也\n超方便❤ #了凡香港油雞飯麵#世界首家米其林小販 了凡（HOYII北車站店） ...","image":"https:\/\/external-iad3-1.xx.fbcdn.net\/safe_image.php?d=AQF0lcrHOjbbzVO3&w=400&h=400&url=https%3A%2F%2Fi.ytimg.com%2Fvi%2Fe0kUcFXfpmI%2Fmaxresdefault.jpg&cfs=1&_nc_cb=1&_nc_hash=AQE1kUDONwlyGv5K"},{"theme":"food","keyword":"米其林 美食","title":"澳洲法官：中餐不適合美食，米其林三星廚師卻不這麼認為- 每日頭條","url":"https:\/\/kknews.cc\/world\/r6ao2vn.html","description":" 食物具有政治性嗎？絕對。澳洲法官喬克·宗弗里洛最近強烈表示：「中餐不適合\n美食。」 更不幸的是，一位有亞洲血統的美食作家和另一位法官也點頭同意。","image":"https:\/\/i1.kknews.cc\/SIG=14k1u0s\/ctp-vzntr\/o7r4p451qo544s34o073nn790303nr04.jpg"},{"theme":"food","keyword":"米其林 美食","title":"米其林〈MUME〉冬季新菜愈來愈Fine！ - 工商時報","url":"https:\/\/ctee.com.tw\/lohas\/food\/401927.html","description":" 〈萄萄蝦\/枸杞\/雪莉酒〉是台北米其林一星餐廳〈MUME〉冬季菜單上的全新菜式，\n主廚Richie林泉設計的這道菜靈感來自中式「醉蝦」，做工細膩繁複、風味與口感 ...","image":"https:\/\/cteecors.azureedge.net\/wp-content\/uploads\/2021\/01\/13\/13-09603-003.jpg"},{"theme":"food","keyword":"米其林 美食","title":"米其林必比登推薦美食台北必吃鵝肉吉林路阿城鵝肉","url":"https:\/\/ifoodie.tw\/post\/60014839d6895d5bc9c67b26-%E7%B1%B3%E5%85%B6%E6%9E%97%E5%BF%85%E6%AF%94%E7%99%BB%E6%8E%A8%E8%96%A6%E7%BE%8E%E9%A3%9F-%E5%8F%B0%E5%8C%97%E5%BF%85%E5%90%83%E9%B5%9D%E8%82%89-%E5%90%89%E6%9E%97","description":" 吉林路美食真的不多如果要推薦我覺得阿城鵝肉一定榜上有名阿城鵝肉生意太好.","image":"https:\/\/lh3.googleusercontent.com\/AASVKAYpKkFuBgv5LfVsH8akqNrEYMTVSi4cNy6z96J781zhM9Ini6ZevKCwuxBxvcYnlsVzbMUqlxTIgJrkS1QiJ4IYwp27UiJEy0uWqx8=s600"},{"theme":"food","keyword":"米其林 美食","title":"【老饕嚴選】義大利版米其林- 2019 紅蝦評鑑：台灣站","url":"https:\/\/www.winentaste.com\/magazine\/food_pairing_tina_gambero_rosso","description":" Gambero Rosso 其實是知名義大利出版公司，從介紹在地食物與酒，進階到義大\n利酒與餐廳的評鑑指南，發揚光大而成為全球知名美食評鑑之一。 【老饕嚴選】\n義大 ...","image":"https:\/\/storage.googleapis.com\/winentaste-alcohol-quick-howl-assets\/images\/article\/monthly\/food_pairing_tina_gambero_rosso_01.jpg"},{"theme":"food","keyword":"米其林 美食","title":"方家雞肉飯 寧夏夜市2020米其林必比登推薦美食。像蒸蛋的嫰滷豆腐 ...","url":"https:\/\/winne33200.pixnet.net\/blog\/post\/556573790","description":" 方家雞肉飯位寧夏夜市裡頭，假日人潮更是洶湧，這天來到附近辦事並覓食，趁著\n還沒有客滿趕緊就座，雞肉飯一向都是很喜歡的食物其一，這家的嫰豆腐據說嫰得\n ...","image":"https:\/\/pic.pimg.tw\/winne33200\/1610520819-3538502982-g_l.jpg"},{"theme":"food","keyword":"米其林 美食","title":"#2020全新泰Fun集點樂點點換美食，成為我們的會員吧‼️ ... - NARA ...","url":"https:\/\/ar-ar.facebook.com\/NARATAIWAN\/posts\/2557728354356141\/","description":" 2020全新泰Fun集點樂點點換美食，成為我們的會員吧‼️ 2020\/01\/16 - 2021\/01\/\n15 只要加入NARA會員➡️ 下載會員APP 來店消費1元=1點，兌換美食自己選 【\n兌換品項】 2000點- 打拋豬壹份3500點- 腰果雞肉壹 ... 米其林 #泰式 #泰國菜","image":"https:\/\/lookaside.fbsbx.com\/lookaside\/crawler\/media\/?media_id=2557727854356191"},{"theme":"food","keyword":"米其林 美食","title":"ANIKO 艾妮可美味人生- 美食｜旅遊｜保養｜生活｜","url":"https:\/\/anikolife.com\/","description":" 台北台南兩地跑的雙棲生活！ 分享生活中美好的一切給你們.","image":"https:\/\/img.anikolife.com\/uploads\/20170702141313_39-270x270.png"},{"theme":"food","keyword":"米其林 美食","title":"【食間到】南機場美食推薦「無名麵店」24小時不打烊，乾麵一碗 ...","url":"https:\/\/www.bella.tw\/articles\/travel&foodies\/27584","description":" 號稱無雷夜市的「南機場夜市」隨便一家店都好吃，更暗藏超多米其林美食在此，\n今天的主角「無名麵店」就位在其中一條巷弄內，沒有醒目的招牌，也沒有文青\n風格 ...","image":"https:\/\/www.bella.tw\/images\/icon.png"},{"theme":"food","keyword":"米其林 美食","title":"新北伴手禮超商上架米其林主廚指導！侯友宜化身美食試吃員讚不絕口","url":"https:\/\/www.ftvnews.com.tw\/news\/detail\/2021114S04M1","description":" 新北市長侯友宜化身美食試吃員，推廣在地8個行政區的伴手禮，要在30家便利超\n商上架，侯友宜先幫消費者試吃，讚不絕口，邀請民眾到東北角、北海岸走走， ...","image":"https:\/\/cdn.ftvnews.com.tw\/manasystem\/FileData\/News\/5d97c0ba-aa3d-442f-9cbf-14628c321e0e.jpg"},{"theme":"food","keyword":"米其林 美食","title":"高雄美食- The Lookout bistro & bar 眺吧餐酒館x 米其林水準美式餐酒 ...","url":"https:\/\/ksdelicacy.pixnet.net\/blog\/post\/67649625","description":" 近捷運中央公園站的眺吧，在比歐緻居的14層樓，有米其林星級的主廚設計餐點，\n還有台南知名的TCRC量身打造的酒單，營業時間到凌晨兩點，從早午餐(限 ...","image":"https:\/\/pic.pimg.tw\/ksdelicacy\/1547304203-2435479921.jpg?v=1547304263"},{"theme":"food","keyword":"米其林 美食","title":"【曼谷好玩景點】2021到曼谷必做的十件事- 新手泰國曼谷自由行好簡單","url":"https:\/\/www.bring-you.info\/zh-tw\/things-to-do-in-bangkok","description":" ... 能莎朵水上市場、安帕瓦水上市場); 探索泰式文創設計(文創旅店、文創咖啡廳); \n大啖泰國道地美食(米其林餐廳、咖哩螃蟹); 曼谷購物好好買(Shopping Mall介紹) ...","image":"https:\/\/www.bring-you.info\/wp-content\/uploads\/2018\/02\/bangkok-6.jpg"},{"theme":"food","keyword":"捷運新埔站 美食","title":"【小虎食夢網】台北捷運美食地圖:: 痞客邦::","url":"http:\/\/www.foodtigertw.com\/blog","description":" 【苗栗-通霄】通霄神社+新埔車站. ... 【台北捷運美食】【市政府站美食】飯\nBAR2021年外帶年菜「七層絲路 ... 【台北捷運美食】【中山國小站美食】九華樓片\n皮鴨.少女之 ...","image":null},{"theme":"food","keyword":"捷運新埔站 美食","title":"TISS玩味食尚| 我是Tiss，分享我的旅遊、玩樂、美食、食譜、時尚 ...","url":"https:\/\/tisshuang.tw\/","description":" 我是Tiss，分享我的旅遊、玩樂、美食、食譜、時尚部落格。 Menu ... 板橋新埔站\n清粥小館｜每天都排隊的自助餐店｜超 ... Filed Under: 板橋美食, 捷運板橋站美食.","image":"https:\/\/tisshuang.tw\/wp-content\/uploads\/2017\/09\/1504852201-7c8c1773e57f1fda19410cdee7c2e230.jpg"},{"theme":"food","keyword":"捷運新埔站 美食","title":"【超商美食 7-11】阿發師x 芋頭瘦肉粥- Foody 吃貨","url":"https:\/\/www.foodytw.com\/review\/7793","description":" 【超商美食￭7-11】阿發師x 芋頭瘦肉粥 ... 訂閱電子報，美食消息不漏接 ... 《台北\n捷運-台北新埔站》叁食Three Food｜隱藏於板橋巷弄的早午餐，紅茶無限暢飲與\n寵物 ...","image":"https:\/\/www.foodytw.com\/upload\/review\/cover\/2021\/01\/7793.jpg"},{"theme":"food","keyword":"捷運新埔站 美食","title":"[食記] 板橋新埔隔壁早餐NextDoor早午餐可吃舒芙蕾- food | PTT旅遊 ...","url":"https:\/\/ptttravelfood.com\/food\/M.1610769121.A.559.html","description":" 餐廳名稱：隔壁早餐NextDoor 消費時間：2020年\/12月地址：新北市板橋區文化路\n一段188巷7弄11號(近捷運新埔站2號出口) 電話：0908 798 837 營業時間：週一- ...","image":null},{"theme":"food","keyword":"捷運新埔站 美食","title":"木柵平溪線(往十分)","url":"https:\/\/www.taiwantrip.com.tw\/Frontend\/Route\/Select_p?RouteID=R0020","description":" 關於好行 · 最新消息 · 遺失物專區 · 留言板 · 常見問題 · 回首頁 ... 台北捷運站各站\n詢問處購買北北基好玩卡交通暢遊一日券$180\/張，可一日之內不限次數搭乘台灣好\n行5條 ... 濱海奇基線、北投竹子湖線、木柵平溪線、黃金福隆線，及台北市與新\n北市捷運與公車(路線編碼4碼之公路客運不可使用)。 3. ... 知性之旅 美食購物 文化\n古蹟.","image":null},{"theme":"food","keyword":"捷運新埔站 美食","title":"【台北火鍋吃到飽】和牛涮日式鍋物放題(板橋文化店)，和牛火鍋\/炙燒 ...","url":"https:\/\/www.timelog.to\/a218683411","description":" 地址：新北市板橋區文化路一段280號2樓. 交通方式：捷運新埔站2號出口；公車站\n名「致理科技大學站」. 營業時間：週 ... 加入好友，更多美食&旅遊資訊不錯過：.","image":"https:\/\/p.timelog.to\/2\/w\/1\/16\/IXjF_800.jpg"},{"theme":"food","keyword":"捷運新埔站 美食","title":"台灣旅遊","url":"https:\/\/www.wiselyview.cc\/read-category\/wisely-taiwan-travel","description":" 裕民街夜市炒飯燴飯︱不加沙茶以醬油快炒風味，煎蔥蛋與三鮮燴飯必點～捷運新\n埔站美食 · 台灣夜市商圈小吃wisely 2020 年09 月23 日. 連二訪的【裕民街夜市 ...","image":"https:\/\/www.wiselyview.cc\/wp-content\/uploads\/2017\/12\/cropped-logo.png"},{"theme":"food","keyword":"捷運新埔站 美食","title":"Maruko與美食有個約會","url":"https:\/\/maruko.tw\/","description":" 前言鴨味仔炭火薑母鴨是位於萬華車站近龍山寺捷運站的週邊美食，用炭火燒的薑 \n... 前言久聞在板橋的新埔站附近有一家來自馬來西亞吉隆坡人開的萬得富爸爸肉骨\n ...","image":"https:\/\/maruko.tw\/wp-content\/uploads\/2020\/12\/IMG_0028.png"},{"theme":"food","keyword":"捷運新埔站 美食","title":"四號公園早午餐推薦。GOODY.O Cafe古迪歐。永和不限時咖啡廳 ...","url":"https:\/\/yabe2112.pixnet.net\/blog\/post\/219379745-%E5%9B%9B%E8%99%9F%E5%85%AC%E5%9C%92%E6%97%A9%E5%8D%88%E9%A4%90%E6%8E%A8%E8%96%A6%E3%80%82goody.o-cafe%E5%8F%A4%E8%BF%AA%E6%AD%90%E3%80%82%E6%B0%B8%E5%92%8C","description":" 新北市永和區安樂路218號⏰11:00-22:30 ☎️02 2927 7718. Facebook：Goody.\nO cafe 古迪歐. Instagram：＠goodyocafe 橘線中和新蘆線美食-捷運永安市場站","image":"https:\/\/pic.pimg.tw\/yabe2112\/1610777133-4211861581-g.jpg?v=1610777376"},{"theme":"food","keyword":"捷運新埔站 美食","title":"新北市板橋區美食推薦和牛涮日式鍋物放題板橋文化店『台北火鍋吃 ...","url":"https:\/\/ifoodie.tw\/post\/600293a7d6895d2daabd0851-%E5%8F%B0%E5%8C%97%E7%81%AB%E9%8D%8B%E5%90%83%E5%88%B0%E9%A3%BD%EF%BC%8C%E5%92%8C%E7%89%9B%E6%B6%AE%E6%97%A5%E5%BC%8F%E9%8D%8B%E7%89%A9%E6%94%BE%E9%A1%8C(%E6%9D%BF%E6%A9%8B","description":" 地址：新北市板橋區文化路一段280號2樓. 交通方式：捷運新埔站2號出口；公車站\n名「致理科技大學站」. 營業時間：週一～週四11:30～16:00 ；17:30～23:00 ；.","image":"https:\/\/lh3.googleusercontent.com\/pT9HaKkDl3aZRNe3Otuw_v7FykMZ5in8vfQv6Dpbabak_7PdPXFFyDmMcf4lDuy5LdmjhPmhlaGpvyY5X2CRCmbH4odwDlPkwByu7q42ECo=s600"},{"theme":"food","keyword":"捷運新埔站 美食","title":"【台北火鍋吃到飽】和牛涮日式鍋物放題(板橋文化店)，和牛火鍋\/炙燒 ...","url":"https:\/\/lolwarden.pixnet.net\/blog\/post\/225200561","description":" 地址：新北市板橋區文化路一段280號2樓. 交通方式：捷運新埔站2號出口；公車站\n名「致理科技大學站」 ... 最常在板橋走跳，發掘在地美食！ 偶爾也會跑其他外縣 ...","image":"https:\/\/live.staticflickr.com\/65535\/50816828453_2e834d71da_c.jpg"},{"theme":"food","keyword":"捷運新埔站 美食","title":"黃水晶的瘋台灣味","url":"https:\/\/fengtaiwanway.com\/","description":" 黃水晶的瘋台灣味~這裡記錄著台灣的旅遊美食、生活資訊、樂活攝影，每一場水晶\n都認真記錄、不愧青春。出發~且讓我們用青春記錄下這一場努力用生命實踐的夢 ...","image":"\/wp-content\/uploads\/2018\/01\/21167709_1776346659072709_2906156145794226922_o-1-avat-1.jpg"},{"theme":"food","keyword":"捷運新埔站 美食","title":"大食女in Wonderland :: 痞客邦::","url":"https:\/\/joyaijia.pixnet.net\/blog","description":" 新埔站美食. Jan 11 2021 ... (附價位) 中山站美食\/台北甜點\/台北下午茶\/台北小吃 ... \n營業到凌晨～(附這間咖啡menu) 大安站美食\/大安站咖啡廳\/台北咖啡廳\/台北下午茶.","image":null},{"theme":"food","keyword":"捷運新埔站 美食","title":"《COFFeee新埔店》捷運新埔站巷弄裡的咖啡店漢堡| 方格子","url":"https:\/\/vocus.cc\/foodslatte\/60028b68fd8978000155cd04","description":" 還記得那一年四處找尋漢堡的日子，特別喜歡沒事繞巷子，看看有沒有什麼新鮮的\n店家，一直以來就鮮少光顧重複的店，所以找新店家去品嚐，會是我很重要的覓食\n ...","image":"https:\/\/images.vocus.cc\/17989175-f534-4aa8-a8ce-53d4e1f760fd.jpg"},{"theme":"food","keyword":"萊爾富","title":"高頓粥 #超商美食 #台北美食 #全家 冬天天冷上班的時候都想吃熱熱的早餐但又懶-發胖板｜PopDaily 波波黛莉","url":"https:\/\/www.popdaily.com.tw\/forum\/food\/878005","description":"高頓粥 #超商美食 #台北美食 #全家 冬天天冷上班的時候都想吃熱熱的早餐 但又懶的提早起床煮或買早餐 逛超商的時候發現竟然有沖泡粥！ 沒有吃過就買來嚐鮮～ 跟泡麵一樣只要加熱水等2～3分鐘 就能馬上吃 方便、快速又能囤積在上班的地方 嚴選台灣米、無添加味精和防腐劑 口味有兩種 椒香牛肉\/濃郁豚骨 ","image":"https:\/\/www.popdaily.com.tw\/shaper\/u\/202101\/a543599c-0671-4c13-84ca-822e4e920d16.jpg?resize-w=800"},{"theme":"food","keyword":"萊爾富","title":"超商福袋開箱","url":"https:\/\/www.ptt.cc\/bbs\/CVS\/M.1610828636.A.940.html","description":null,"image":null},{"theme":"food","keyword":"台北咖啡廳","title":"📍黑洞珈啡店-發胖板｜PopDaily 波波黛莉","url":"https:\/\/www.popdaily.com.tw\/forum\/food\/877881","description":" 因為朋友很喜歡吃提拉米蘇，看到友人前陣子分享這家就帶她來，店雖然小小的但不會很擠很溫馨，老闆跟店員都很親切，我還蠻喜歡他們的座位都不太一樣，靠窗的沙發椅完全舒服😌 _ #熟の提拉米蘇 150$ #吐司盤 （雞肉）140$ #抹茶拿鐵 160$ #美式 110$ _ 熟の提拉米蘇 J個真的很推！一入","image":"https:\/\/www.popdaily.com.tw\/shaper\/u\/202101\/87f9ed51-0d4f-4777-863e-be94d39a50f3.jpg?resize-w=800"},{"theme":"food","keyword":"好市多","title":"我的好市多無限回購食品清單-發胖板｜PopDaily 波波黛莉","url":"https:\/\/www.popdaily.com.tw\/forum\/food\/876993","description":"以下分享一些我這次買的食物\n都不是什麼新鮮貨啦 \n大部分是我幾乎去都會補貨的\n也覺得滿方便又好吃的\n分享給大家參考囉","image":"https:\/\/www.popdaily.com.tw\/shaper\/u\/202101\/1adad60a-9875-460f-90a0-a4418f791465.jpg?resize-w=1200&resize-h=630"},{"theme":"food","keyword":"好市多","title":"[問題] 好市多的牛肉有種特別的味道？","url":"https:\/\/www.ptt.cc\/bbs\/cookclub\/M.1610811681.A.683.html","description":"小弟是烹飪新手\n一開始買牛肉都是在所在地區的早市購買\n因為同事推薦好市多的牛肉便宜又大碗\n所以今天馬上殺去好市多\n買了一條choice等級的嫩肩里肌\n","image":null},{"theme":"food","keyword":"星巴克","title":"富士山、不倒翁杯超可愛！「日本星巴克牛年限定款」和風傳統圖樣滿滿年味","url":"https:\/\/playing.ltn.com.tw\/article\/24438","description":"迎接2021年的到來，日本的星巴克一次推出多款新年限定杯，除了牛年的生肖杯之外，還有各種以日本傳統圖案為主題的各種杯款。有日本象徵的富士山、守護神殿的狛犬、吉祥的達摩、喜氣洋洋的七寶圖樣等等，每一種都超級吸睛想要全部都帶回家！","image":"https:\/\/img.ltn.com.tw\/Upload\/playing\/page\/2021\/01\/12\/210112-24438-19-v4qaN.jpg"},{"theme":"food","keyword":"星巴克","title":"2021全聯年菜推薦｜開箱好吃年菜組合！整套不超過4000元的神級美食：團圓套餐懶人包-發胖板｜PopDaily 波波黛莉","url":"https:\/\/www.popdaily.com.tw\/forum\/food\/876123","description":"全聯年菜推薦！一年一度的過年即將來臨，讓人期待的就是全家人聚在一起吃團圓飯的時光。好鄰居全聯年菜推薦給大家，集結名廚們主打堅強陣容的「至尊主廚功夫菜」讓大家不用到餐廳排隊就能在家裡輕鬆吃到名廚料理，吃好吃滿好過年！","image":"https:\/\/www.popdaily.com.tw\/shaper\/u\/202101\/25530fcc-0d0d-4db9-ba29-213f28277192.jpg?resize-w=1200&resize-h=630"},{"theme":"food","keyword":"星巴克","title":"麻古茶坊「芋泥波波布蕾」滿滿5層料！芋頭手搖＋布蕾，喝的甜點太療癒","url":"https:\/\/udn.com\/news\/story\/7186\/5178721?from=udn-catelistnews_ch2","description":"芋泥控現在就出發！憑藉芝芝芒果果粒、芝芝葡萄果粒每季引發搶喝潮的「麻古茶坊」，這回帶著更狂「喝的甜點」登場。麻古茶坊繼「芋泥波波鮮奶」後再升級，首創芋頭手搖搭布蕾組合「芋泥波波布蕾」，芋泥、鮮奶、珍珠","image":"https:\/\/pgw.udn.com.tw\/gw\/photo.php?u=https:\/\/uc.udn.com.tw\/photo\/2021\/01\/16\/1\/11215467.jpg&s=Y&x=0&y=0&sw=1280&sh=853&exp=3600"},{"theme":"food","keyword":"周姈姈","title":"眺望台北最美夜景！陽明山隱藏版咖啡廳　泡湯後吃限定牛奶鍋超罪惡","url":"https:\/\/travel.ettoday.net\/article\/1897967.htm","description":"來到陽明山，除了賞花、去擎天岡拍草原照之外，也千萬別忘記挑間咖啡廳坐坐！就有一間藏在溫泉度假村中的景觀咖啡廳，從早到晚的景色都不同，晚上能夠眺望絢爛的台北夜景，還能享用冬季限定的牛奶鍋，如果時間允許也..","image":"https:\/\/cdn2.ettoday.net\/images\/5394\/d5394457.jpg"},{"theme":"food","keyword":"麻古茶坊","title":"搶喝！麻古茶坊「芋泥波波」第二彈　狂咬珍珠、小芋圓還有濃郁布蕾","url":"https:\/\/travel.ettoday.net\/article\/1899495.htm","description":"是第二彈！以芝芝系列讓人欲罷不能的人氣手搖飲品牌「麻古茶坊」，繼上月推出罪惡「芋泥波波鮮奶」後，這次又打造全新芋頭飲品「芋泥波波布蕾」了，綿密的芋泥搭配Q彈珍珠、芋圓，最上層再鋪上滿滿香濃法式布蕾，整..","image":"https:\/\/cdn2.ettoday.net\/images\/5399\/d5399343.jpg"},{"theme":"food","keyword":"麻古茶坊","title":"21PLUS「199元炸雞腿桶」、拿坡里披薩免費換！快餐新優惠快收藏","url":"https:\/\/udn.com\/news\/story\/7193\/5178983?from=udn-catelistnews_ch2","description":"炸雞控、披薩迷站出來！除了最為常見的麥當勞、肯德基、必勝客等國際連鎖品牌，台灣其實也有「21風味館」以烤雞及炸雞積累忠實粉絲群；三商餐飲旗下「拿坡里」亦是人氣選項。今天為大家介紹這兩大快餐的限定優惠，","image":"https:\/\/pgw.udn.com.tw\/gw\/photo.php?u=https:\/\/uc.udn.com.tw\/photo\/2021\/01\/16\/1\/11216910.jpg&s=Y&x=0&y=0&sw=1280&sh=853&exp=3600"},{"theme":"food","keyword":"布朗尼","title":"［台北｜信義安和］-發胖板｜PopDaily 波波黛莉","url":"https:\/\/www.popdaily.com.tw\/forum\/food\/877771","description":"📍雞啃工廠chicken factory 🥄蜜汁雞排$70👍🏻 🥄起司雞排$70 🥄雞翅$25 🥄雞腿$40 🥄酥炸七里香$25 🥄甜不辣$25 🥄炸水餃$40 🥄月亮蝦餅$45 🥄雙色QQ地瓜球$25👍🏻 🥄芋泥球$25 🥄布朗尼$40👍🏻 🥄炸湯圓$30 🥄四季豆$30 🥄玉米筍$45 雞啃工廠位在通","image":"https:\/\/www.popdaily.com.tw\/shaper\/u\/202101\/76951dd1-4ae3-48ef-bf37-e65d98b24089.jpg?resize-w=800"},{"theme":"food","keyword":"布朗尼","title":"[商品] 7-11 草莓玫瑰花塔","url":"https:\/\/www.ptt.cc\/bbs\/CVS\/M.1610809902.A.82B.html","description":"【商品名稱\/價格】：草莓玫瑰花塔\/52元\n【便利商店\/廠商名稱】：7-11\n【規格\/內容物\/熱量】：\nhttps:\/\/i.imgur.com\/N9elG4L.jpg\n【評分】： 65\n","image":null},{"theme":"food","keyword":"中山站","title":"自家研製辛香料咖哩飯，辛香濃郁而不膩《The Wrice來時》-發胖板｜PopDaily 波波黛莉","url":"https:\/\/www.popdaily.com.tw\/forum\/food\/878206","description":"🍴台北中山-The Wrice 來時🍴 自家研製辛香料咖哩飯，辛香濃郁而不膩 「The Wrice 來時」是間非常特別的輕食餐館，提供的餐點主要分為冰品、飯食、飲品以及甜點，由於在這寒風凜冽的日子，這次我們就介紹飯食與甜點的部分吧！ 「The Wrice 來時」在飯食餐點上非常簡單，提供雞肉香料咖哩","image":"https:\/\/www.popdaily.com.tw\/shaper\/u\/202101\/12bb0eee-69ff-418b-907d-465192d6d673.jpg?resize-w=800"},{"theme":"food","keyword":"米其林","title":"orchid restaurant 蘭❤️-發胖板｜PopDaily 波波黛莉","url":"https:\/\/www.popdaily.com.tw\/forum\/food\/878254","description":"為了威靈頓牛肉派朝聖⠀ 國王派的外皮口感酥香紮實⠀ 內餡有厚厚的鴨肝和菲力牛排⠀ 好吃但個人覺得膩感有點重⠀ 這道主餐需兩個人同時點選(一人一半) ⠀ ⠀ 餐廳有著簡約卻氣派挑高的裝潢⠀ 最後的香草茶是現場剪葉子沖泡⠀ 口中不散的香氣令人印象深刻⠀ ⠀ 主餐前有八樣前菜⬇️⠀ 淡菜👉我的更換成烤鳳梨起","image":"https:\/\/www.popdaily.com.tw\/shaper\/u\/202101\/ad8d2b22-4280-4614-a43d-7f34cdc26cfd.jpg?resize-w=800"},{"theme":"food","keyword":"米其林","title":"[食記] 台北 燒鳥酉志 再訪","url":"https:\/\/www.ptt.cc\/bbs\/Food\/M.1610806310.A.5F2.html","description":"   餐廳名稱：酉志\n   消費時間：2020年\/12月\n   地址：台北市中山區中山北路一段135巷33-2號\n   營業時間：18:00~23:00 (周一休)\n圖文：https:\/\/thudadai.pixnet.net\/blog\/post\/69467098\n","image":null},{"theme":"food","keyword":"鍾奇峻","title":"爆塞8隻天使紅蝦！桃園痛風系豪華麵線　提前2天預訂才吃得到","url":"https:\/\/travel.ettoday.net\/article\/1893315.htm","description":"桃園有間新開幕麵線店，打卡就送軟嫩入味的麻辣鴨血，香Q大腸更是在地人大推，最扯的浮誇系豪華海陸麵線，多逹11種好料直接塞爆大碗公，8隻天使紅擺好擺滿誘人無比，多到要滿出來的好料，讓人直呼太誇張，沒提前..","image":"https:\/\/cdn2.ettoday.net\/images\/5381\/d5381224.jpg"},{"theme":"food","keyword":"傑尼","title":"台北・中山站｜Hoto Cafe：好吃的限量手作甜點・適合一人工作的咖啡廳-發胖板｜PopDaily 波波黛莉","url":"https:\/\/www.popdaily.com.tw\/forum\/food\/877720","description":"前提摘要 今天是自由接案平面設計師的小聚會，其實是要面交拿釀電影期刊的大學同學聚啦。滿慶幸在自由接案這條路上，還能有兩位厲害的大學同學相互討論\b和分享～聊一些接案眉眉角角。當然免不了還會抱怨一下雷客戶！但隨著年齡和經驗的增長，大家都很能自我消化了，很棒！這次要光顧的這家店，就是其中一位平面設計師有人","image":"https:\/\/www.popdaily.com.tw\/shaper\/u\/202101\/09b3d667-2a92-4f2b-9e87-371d9ec15bc7.jpg?resize-w=1200&resize-h=630"},{"theme":"food","keyword":"君君歐北","title":"社子島第一辣-發胖板｜PopDaily 波波黛莉","url":"https:\/\/www.popdaily.com.tw\/forum\/food\/877745","description":"#君君歐北呷 🔍 社子島第一辣 🔺 大腸麵線 $45 🔺 甜不辣 $40 這就是我學生時期的回憶啊!!!!!!!!半個士林人的君君 走跳士林 怎麼可能沒吃過 社子島第一辣 🌶️ 雖然他的地點算偏僻 依舊大排長龍 客席區永遠🈵️ 🤩 社子島第一辣 有名的是什麼 🌶️ 就是辣椒啊 他的辣椒共三種 讓我娓娓道來","image":"https:\/\/www.popdaily.com.tw\/shaper\/u\/202101\/6fc3fc2d-cea0-40fe-841e-a203f0b7732f.jpg?resize-w=800"},{"theme":"food","keyword":"拉麵","title":"8大片叉燒的金沢拉麵-發胖板｜PopDaily 波波黛莉","url":"https:\/\/www.popdaily.com.tw\/forum\/food\/878003","description":"今年冬天特別冷，來碗熱騰騰的日式拉麵令人暖胃又幸福。位於台北農安街上的金沢拉麵，仿造新宿巷弄中的拉麵店格局，位置僅約15-16位，有時候可是要等個幾輪呢！ 今天享用的是豚骨湯頭的叉燒拉麵，特色是花瓣般鋪滿一圈的叉燒肉，完全滿足你想大口吃麵大口吃肉的心願。 其豚骨湯頭與一般乳白色湯頭不同，看起來半透明","image":"https:\/\/www.popdaily.com.tw\/shaper\/u\/202101\/13039f01-d296-424b-adaf-8c85e7f4709c.jpg?resize-w=800"},{"theme":"food","keyword":"拉麵","title":"[食記] 台北 信義區│男子漢拉麵食堂 信義永春店","url":"https:\/\/www.ptt.cc\/bbs\/Food\/M.1610801428.A.A61.html","description":"餐廳名稱：男子漢拉麵食堂 信義永春店\n消費時間：2020年\/12月\n地址：台北市信義區虎林街132巷42號\n電話：02-2758-1516\n營業時間：星期一到星期五11：00–14：00│16：30–21：00\n","image":null},{"theme":"food","keyword":"台北","title":"【報名中】參加即贈8800元單一麥原酒　《夢幻講座》27萬原酒東方文華饗宴","url":"https:\/\/tw.appledaily.com\/supplement\/20210115\/FM67SAMGHRE5VH6MHT22JGM7PM\/","description":"《蘋果夢幻講座》 品酒│年度最華麗 27萬原酒食尚饗宴 點我報名參加 未經稀釋、維持原始橡木桶酒精強度的威士忌原酒，除了不易取得的珍稀性，加上獨一無二的風味及酒體個性，深受不少威士忌迷喜愛，《蘋果新聞網》看準原酒魅力，本月底攜手英蓋爾精品洋酒舉辦《夢幻講座》，針對莫麗斯（TH...","image":"https:\/\/tw.appledaily.com\/resizer\/PizRec7pVjEioiwQy2dax5Awmto=\/1920x1080\/filters:quality(100)\/d87urpdhi5rdo.cloudfront.net\/01-14-2021\/t_5906230b317f4c25857332f830c79e6e_name_t_c48d6235199b44d9bd800d05c1f8f05e_name_14012021_TSUP007_ok_v___6259__.jpg"},{"theme":"food","keyword":"台北","title":"實現甜蜜誓言！浪漫晚餐+美景　這4家飯店都有求婚必勝桌","url":"https:\/\/travel.ettoday.net\/article\/1899907.htm","description":"離2月14日西洋情人節不到1個月，許多人都會安排漫浪的情人節晚餐，如果在情人節求婚更是浪漫，《ETtoday新聞雲》整理4家飯店的必勝求婚桌，台北喜來登大飯店還推出經典No.9桌求婚必勝專案，除了浪漫..","image":"https:\/\/cdn2.ettoday.net\/images\/5399\/d5399863.jpg"},{"theme":"food","keyword":"台北","title":"［台北｜信義安和］-發胖板｜PopDaily 波波黛莉","url":"https:\/\/www.popdaily.com.tw\/forum\/food\/877771","description":"📍雞啃工廠chicken factory 🥄蜜汁雞排$70👍🏻 🥄起司雞排$70 🥄雞翅$25 🥄雞腿$40 🥄酥炸七里香$25 🥄甜不辣$25 🥄炸水餃$40 🥄月亮蝦餅$45 🥄雙色QQ地瓜球$25👍🏻 🥄芋泥球$25 🥄布朗尼$40👍🏻 🥄炸湯圓$30 🥄四季豆$30 🥄玉米筍$45 雞啃工廠位在通","image":"https:\/\/www.popdaily.com.tw\/shaper\/u\/202101\/76951dd1-4ae3-48ef-bf37-e65d98b24089.jpg?resize-w=800"},{"theme":"food","keyword":"台北","title":"[食記] 台北 平壽司 黑鮪魚 海膽 生蠔 葡萄蝦","url":"https:\/\/www.ptt.cc\/bbs\/Food\/M.1610812597.A.1BD.html","description":"   餐廳名稱：平壽司\n   消費時間：2020年11月\n   店家地址：台北市信義區仁愛路四段434號\n   店家電話：02 2758 0622\n   營業時間：12：00～14：30 \/ 18：00～21：30\n","image":null},{"theme":"food","keyword":"台北","title":"天母港點控的新選擇！港點推車「點8號」強勢進軍天母高島屋，預計2月上旬開幕搶攻天母最經典的港式點心。","url":"https:\/\/www.walkerland.com.tw\/subject\/view\/285131","description":"簡單港點、配上一壺熱茶，不管你是只想吃一點點，還是想要大吃特吃，「港式點心」都能滿足各種用餐需求。而以最經典、傳統的港點推車為主打的「點8號」，在國父紀念館、板橋、林口和台中都掀起港點控的關注。這次終於將首次進軍天母地區，選擇在老字號百貨「高島屋」插旗，用最經...","image":"https:\/\/www.walkerland.com.tw\/image\/subject\/2021\/01\/956283dc2329ee136e3df6f4e2be659ae824a5f9.jpg"},{"theme":"food","keyword":"捷運新埔站","title":"板橋新開幕火鍋，無收取服務費，還有泰國明果冰淇淋、飲料可無限享用!-發胖板｜PopDaily 波波黛莉","url":"https:\/\/www.popdaily.com.tw\/forum\/food\/877849","description":" 店名：焣苑鍋物JUYUAN HOT POT 地址：新北市板橋區民生路三段46號 交通方式：近捷運新埔站5號出口 營業時間：週一~週五11：30~22：30；週六日11：00~22：30 電話：02-22554123 ⚠️用餐時間為90分鐘，共鍋費$150 這幾天的低溫天氣，實在讓人好想吃個火鍋暖暖身","image":"https:\/\/www.popdaily.com.tw\/shaper\/u\/202101\/31b876f7-c35f-473a-94f2-811206e04472.jpg?resize-w=1200&resize-h=630"},{"theme":"food","keyword":"捷運新埔站","title":"[食記] 板橋新埔 隔壁早餐NextDoor早午餐可吃舒芙蕾","url":"https:\/\/www.ptt.cc\/bbs\/Food\/M.1610769121.A.559.html","description":"   餐廳名稱：隔壁早餐 NextDoor\n   消費時間：2020年\/12月\n   地址：新北市板橋區文化路一段188巷7弄11號\n         (近捷運新埔站2號出口)\n   電話：0908 798 837\n","image":null},{"theme":"food","keyword":"忠孝東路五段372巷","title":"永春捷運站旁新開咖啡店( 瑰夏咖啡 UNC COFFEE)-發胖板｜PopDaily 波波黛莉","url":"https:\/\/www.popdaily.com.tw\/forum\/food\/877860","description":"主題: 來吧檯和老闆聊聊天 這間咖啡店特別之處在於吧檯的隱蔽性 店內被拆分為兩個地方 外面總共有12個座位 裡面吧檯有3個座位 吧檯區等於是VIP席啊 跟老闆可以聊很多咖啡相關的話題 整個就是畫匣子打開就停不下來 或許可以在這裡找到屬於自己的第一杯好咖啡 店內老闆擁有烘豆證照 對客人也算是一個保障 ","image":"https:\/\/www.popdaily.com.tw\/shaper\/u\/202101\/c200b8d1-b334-4caa-a4be-a5c00b2d6927.jpg?resize-w=800"},{"theme":"food","keyword":"唐揚","title":"【台南】灶妃姬職人燒肉飯專賣-發胖板｜PopDaily 波波黛莉","url":"https:\/\/www.popdaily.com.tw\/forum\/food\/877838","description":"〰️ 身為牛肉魔人的我 四種肉都吃完不得不把這間的第一名給豬肉（個人喜好） #炙燒豬豬飯 小$85 大$100 豬肉的軟硬度適中 加上醬汁有夠下飯 我吃完還想再吃 #醬烤雞腿飯 $95 無大碗 雞腿剛開始吃很驚艷 原本已經是我的第一名了 可是飯還沒吃完就有一點點膩 maybe是我的菜太快吃完了 沒辦法","image":"https:\/\/www.popdaily.com.tw\/shaper\/u\/202101\/d7d413e7-2810-4233-8154-0f9a3438882b.jpg?resize-w=800"},{"theme":"food","keyword":"唐揚","title":"[食記] 桃園八德 巽品雞湯","url":"https:\/\/www.ptt.cc\/bbs\/Food\/M.1610821937.A.3B7.html","description":"　　餐廳名稱：巽品雞湯\n　　消費時間：2020年11、12月\n　　地址：334桃園市八德區興豐路714號\n　　電話：0979-606-086\n　　營業時間：週二至週日 17:00~00:30 (每周一店休)\n","image":null},{"theme":"food","keyword":"址","title":"├ 食記 ┤ 一番地 壽喜燒 ♥ 中山區 ♥ 大直Att ♥ 吃到飽 ♥ 鍋底可做素食-發胖板｜PopDaily 波波黛莉","url":"https:\/\/www.popdaily.com.tw\/forum\/food\/877759","description":"話說這篇食記又是二訪之後才寫好的XD 這家一番地短時間內我們來了2次，好像才隔個4~5天吧 第一次是晚上去吃，第二次是中午去吃，都有先訂位 但2次的感受真是天差地遠…我們先來上菜再來說感受~~~ ​中午$428、晚上$498，價格都要+10%服務費 而小孩超過80公分就要收$100 ​飲料選擇其實還","image":"https:\/\/www.popdaily.com.tw\/shaper\/u\/202101\/8e041f46-0261-4343-93ac-325c97af08e0.jpg?resize-w=1200&resize-h=630"},{"theme":"food","keyword":"址","title":"[揪團] 板橋悅市集","url":"https:\/\/www.ptt.cc\/bbs\/EatToDie\/M.1610777531.A.304.html","description":null,"image":null},{"theme":"food","keyword":"劍潭站","title":"✨🧡🍱 台北·士林 使用Prime級牛的牛丼🤤 現點現烤超人氣排隊丼飯-發胖板｜PopDaily 波波黛莉","url":"https:\/\/www.popdaily.com.tw\/forum\/food\/876916","description":"《#直火人燒肉丼飯屋 》台北·劍潭站 🔹 嫩烤板腱牛丼 $255 🔸蔥段嫩雞腿串丼 $235 - - - - - - - - - - - - - - - - - - - - - - - - - - 去士林夜市不知道吃什麼嗎？ 士林夜市附近超人氣的丼飯 每到晚餐時間總要排隊 內用免費續飯、味增湯和一盤","image":"https:\/\/www.popdaily.com.tw\/shaper\/u\/202101\/cd109864-c8d2-469d-994e-b06505944c08.jpg?resize-w=800"},{"theme":"food","keyword":"米米","title":"全家便利商店 鐵觀音霜淇淋 該不會只剩我沒吃過吧？-發胖板｜PopDaily 波波黛莉","url":"https:\/\/www.popdaily.com.tw\/forum\/food\/877064","description":"嗨大家，我是米米，環遊世界30國的旅遊記者三寶媽李筱維，今天 #跟著米米享受生活 要分享 #全家便利商店 #鐵觀音霜淇淋 🍦 全家便利商店網友票選最喜愛的霜淇淋口味之一 鐵觀音霜淇淋 🍦吃一口濃厚的茶香和清爽的微甜，瞬間療癒人心。 之前在在日本漫遊時，全家便利商店比7-11還容易遇到，每到景區總是有","image":"https:\/\/www.popdaily.com.tw\/shaper\/u\/202101\/c2a6a378-2923-47e0-b9d0-ddc6c62fdfe2.jpg?resize-w=800"},{"theme":"food","keyword":"米米","title":"[問題] 生米碰到水怎麼辦","url":"https:\/\/www.ptt.cc\/bbs\/cookclub\/M.1610780487.A.340.html","description":"今天剛好開一包新的米（2kg）\n結果沒注意量米米杯裡面有一點水就直接下去舀米\n雖然已經盡力把沾到水的米取出了，但還是很擔心\n2kg全煮成飯也吃不完（我一個人）\n又是貴貴日本新潟米壞掉丟掉也太可惜 QQ\n","image":null},{"theme":"food","keyword":"7-11","title":"超商開箱｜年節禮盒好選擇Kitty迷注意！期間限定Hello Kitty巧克力珍珠包7-11限時預購-發胖板｜PopDaily 波波黛莉","url":"https:\/\/www.popdaily.com.tw\/forum\/food\/878130","description":"Hello Kitty巧克力珍珠包 與三麗鷗授權聯名打造出Kitty包，採禮盒包裝，光是盒身就可愛到不行！可愛的畫上五個蘋果身高的KITTY，完全送禮自用都超滿意。 ","image":"https:\/\/www.popdaily.com.tw\/shaper\/u\/202101\/5cc4e96b-e307-42a6-bbbe-5f881a6c74a8.jpg?resize-w=1200&resize-h=630"},{"theme":"food","keyword":"7-11","title":"[問題] 悠遊卡在便利商店好用嗎？","url":"https:\/\/www.ptt.cc\/bbs\/CVS\/M.1610830487.A.CFF.html","description":"說真的，我沒有在用悠遊卡\n也很少在全家、7-11買東西\n不過前幾天在MobilePay板看到這個活動\nhttps:\/\/www.ptt.cc\/bbs\/MobilePay\/M.1610579812.A.A3C.html\n我就跑到全家去設定我的iphone跟悠遊卡\n","image":null},{"theme":"food","keyword":"黃士原","title":"雲林人有口福了　御頂集團新品牌「晶粵軒港式飲茶」插旗北港","url":"https:\/\/travel.ettoday.net\/article\/1899909.htm","description":"雲林北港喜愛粵菜港點的人有福了，品嚐正宗港式料理，不需要再跑外縣市！御頂餐飲集團看好國旅商機，於2020年12月開設新的港式飲茶品牌「晶粵軒」，首站插旗雲林北港，位置緊鄰雲林海線商業及信仰中心-朝天宮..","image":"https:\/\/cdn2.ettoday.net\/images\/5399\/d5399871.jpg"},{"theme":"food","keyword":"巴克","title":"食力爆發　美式餐廳進駐鐵鹿大街　麗寶Outlet招50家餐飲搶商機","url":"https:\/\/travel.ettoday.net\/article\/1900293.htm","description":"台中最新美食街「鐵鹿大街」去年底開幕，目前已有40家餐廳、伴手禮店進駐，其中「歐棒咖啡Cafe Oˊbon」看好台中車站每天約3萬人次也宣布搶進。另外，和億生活集團旗下摘星美食《添好運》、瓦城集團中式料理《時時香》、《十二月粥品》則趕在農曆年前插旗進駐麗寶Outlet Mall，開設中部Outlet首店。","image":"https:\/\/cdn2.ettoday.net\/images\/5400\/d5400940.jpg"},{"theme":"food","keyword":"巴克","title":"富士山、不倒翁杯超可愛！「日本星巴克牛年限定款」和風傳統圖樣滿滿年味","url":"https:\/\/playing.ltn.com.tw\/article\/24438","description":"迎接2021年的到來，日本的星巴克一次推出多款新年限定杯，除了牛年的生肖杯之外，還有各種以日本傳統圖案為主題的各種杯款。有日本象徵的富士山、守護神殿的狛犬、吉祥的達摩、喜氣洋洋的七寶圖樣等等，每一種都超級吸睛想要全部都帶回家！","image":"https:\/\/img.ltn.com.tw\/Upload\/playing\/page\/2021\/01\/12\/210112-24438-19-v4qaN.jpg"},{"theme":"food","keyword":"巴克","title":"2021全聯年菜推薦｜開箱好吃年菜組合！整套不超過4000元的神級美食：團圓套餐懶人包-發胖板｜PopDaily 波波黛莉","url":"https:\/\/www.popdaily.com.tw\/forum\/food\/876123","description":"全聯年菜推薦！一年一度的過年即將來臨，讓人期待的就是全家人聚在一起吃團圓飯的時光。好鄰居全聯年菜推薦給大家，集結名廚們主打堅強陣容的「至尊主廚功夫菜」讓大家不用到餐廳排隊就能在家裡輕鬆吃到名廚料理，吃好吃滿好過年！","image":"https:\/\/www.popdaily.com.tw\/shaper\/u\/202101\/25530fcc-0d0d-4db9-ba29-213f28277192.jpg?resize-w=1200&resize-h=630"},{"theme":"food","keyword":"巴克","title":"麻古茶坊「芋泥波波布蕾」滿滿5層料！芋頭手搖＋布蕾，喝的甜點太療癒","url":"https:\/\/udn.com\/news\/story\/7186\/5178721?from=udn-catelistnews_ch2","description":"芋泥控現在就出發！憑藉芝芝芒果果粒、芝芝葡萄果粒每季引發搶喝潮的「麻古茶坊」，這回帶著更狂「喝的甜點」登場。麻古茶坊繼「芋泥波波鮮奶」後再升級，首創芋頭手搖搭布蕾組合「芋泥波波布蕾」，芋泥、鮮奶、珍珠","image":"https:\/\/pgw.udn.com.tw\/gw\/photo.php?u=https:\/\/uc.udn.com.tw\/photo\/2021\/01\/16\/1\/11215467.jpg&s=Y&x=0&y=0&sw=1280&sh=853&exp=3600"},{"theme":"food","keyword":"zoe","title":"花蓮市區必吃美味推薦—黑點師魯肉飯，大口過癮鮮蚵仔魯肉飯-發胖板｜PopDaily 波波黛莉","url":"https:\/\/www.popdaily.com.tw\/forum\/food\/878353","description":"今天要帶大家介紹一間位在花蓮市區巷弄中的黑點師魯肉飯， 喜歡新鮮蚵仔的朋友絕對不能錯過的！ 就讓我們開始介紹吧！ 地址：970花蓮縣花蓮市新港街48號 電話： 03 833 2967 營業時間：星期一至日11:30~14:00、17:00~00:00 雖然營業時間是到14:00，但收客時間是13:4","image":"https:\/\/www.popdaily.com.tw\/shaper\/u\/202101\/af5be4fc-5159-4e96-9e98-2abac9a5b9a0.jpg?resize-w=1200&resize-h=630"},{"theme":"food","keyword":"法芙娜","title":"✨歷經72小時的熟成風味—法蘭騎士熟成蜜蛋糕·值得等待的美味✨-發胖板｜PopDaily 波波黛莉","url":"https:\/\/www.popdaily.com.tw\/forum\/food\/877941","description":"吃過熟成牛排、熟成紅茶還有半熟蜂蜜蛋糕，但這是第一次嘗試熟成蜜蛋糕，從小時候就一直很熱愛蜂蜜蛋糕那香香甜甜的滋味，身為台中人，我們全家首推的就是坂神本舖長崎蛋糕，每次都要排隊特別去買，但這次在Ig上滑到法蘭騎士熟成蜜蛋糕，整個被燒到🔥覺得一定要試吃看看，號稱以日本🇯🇵傳統手作工法製成，有別於市面上的一","image":"https:\/\/www.popdaily.com.tw\/shaper\/u\/202101\/eab21636-dd57-4e73-83a2-b784bfd0e14a.jpg?resize-w=800"},{"theme":"food","keyword":"霜淇淋","title":"［小石鍋］平價大份量火鍋-發胖板｜PopDaily 波波黛莉","url":"https:\/\/www.popdaily.com.tw\/forum\/food\/878179","description":"- ❤️奶香南瓜豬肉鍋 $190 ❤️孜然藥膳牛肉鍋 $155 - 冷冷的天氣就是要吃火鍋啦🍲 位於台中大墩11街～剛開幕四個多月 店內裝潢明亮乾淨！ 空間和位置舒適不會擁擠🤗 部分餐點可以做成素食（參考最後菜單） 醬料、白飯、飲料、冰淇淋全是吃到飽 完全適合全家大小一起吃！ 火鍋內超多料！整鍋滿滿的端","image":"https:\/\/www.popdaily.com.tw\/shaper\/u\/202101\/91122f03-894e-4aef-9e1e-480c40062702.jpg?resize-w=800"},{"theme":"food","keyword":"GOOGLE","title":"日本上班族都這樣吃!正統日系義式披薩燉飯 平價美味秒飛東京-發胖板｜PopDaily 波波黛莉","url":"https:\/\/www.popdaily.com.tw\/forum\/food\/877937","description":"作者： #佩吉王生活記事 常看日劇的朋友，就知道日本上班族下班後通常會約三五好友同事一同去居酒屋小酌，而在台灣類似場景就是餐酒館啦~ 位於台北板南線、捷運忠孝新生站三號出口旁的「JAPOLIジャポリ義大利餐酒館」，是日本JFC集團在海外第四家店。首間分店於2015年夏天開在忠孝東路四段，五年才開四店","image":"https:\/\/www.popdaily.com.tw\/shaper\/u\/202101\/30be70d1-bd4b-4dc8-897f-265b95fa7235.jpg?resize-w=1200&resize-h=630"},{"theme":"food","keyword":"GOOGLE","title":"[食記] 台北松山饒河夜市 阿根脆皮臭豆腐(小吃","url":"https:\/\/www.ptt.cc\/bbs\/Food\/M.1610727299.A.19D.html","description":"【阿根脆皮臭豆腐】\n電話：無\n地址：台北市松山區饒河街32號口攤位(夜市口靠塔悠路牌坊下)\n營業時間：17:00-23:00(饒河夜市營業時間應該是都跟著開)\n消費時間：2021年01月\n","image":null},{"theme":"food","keyword":"永春捷運站","title":"信義區咖啡-發胖板｜PopDaily 波波黛莉","url":"https:\/\/www.popdaily.com.tw\/forum\/food\/877850","description":"位於巷內鬧中取靜的地方，有一間小小的咖啡館誕生了 附近環境優美舒適，店內能感受到店主的小巧思 主要以單品手沖咖啡為主的咖啡店 在店內販售許多藝伎咖啡的品項 活動資訊 咖啡豆買三送一 購買一磅以上咖啡豆手沖咖啡現場免費試飲 內用同價位或以低價位 同一人第二杯50% 因內用座位不多 所以外帶咖啡會稍有優","image":"https:\/\/www.popdaily.com.tw\/shaper\/u\/202101\/1b6d5969-8b80-42fc-9a9e-361a464aa165.jpg?resize-w=800"},{"theme":"food","keyword":"永春捷運站","title":"[食記] 台北 信義區│男子漢拉麵食堂 信義永春店","url":"https:\/\/www.ptt.cc\/bbs\/Food\/M.1610801428.A.A61.html","description":"餐廳名稱：男子漢拉麵食堂 信義永春店\n消費時間：2020年\/12月\n地址：台北市信義區虎林街132巷42號\n電話：02-2758-1516\n營業時間：星期一到星期五11：00–14：00│16：30–21：00\n","image":null},{"theme":"food","keyword":"國父紀念館","title":"[食記] 台北 平壽司 黑鮪魚 海膽 生蠔 葡萄蝦","url":"https:\/\/www.ptt.cc\/bbs\/Food\/M.1610812597.A.1BD.html","description":"   餐廳名稱：平壽司\n   消費時間：2020年11月\n   店家地址：台北市信義區仁愛路四段434號\n   店家電話：02 2758 0622\n   營業時間：12：00～14：30 \/ 18：00～21：30\n","image":null},{"theme":"food","keyword":"國父紀念館","title":"天母港點控的新選擇！港點推車「點8號」強勢進軍天母高島屋，預計2月上旬開幕搶攻天母最經典的港式點心。","url":"https:\/\/www.walkerland.com.tw\/subject\/view\/285131","description":"簡單港點、配上一壺熱茶，不管你是只想吃一點點，還是想要大吃特吃，「港式點心」都能滿足各種用餐需求。而以最經典、傳統的港點推車為主打的「點8號」，在國父紀念館、板橋、林口和台中都掀起港點控的關注。這次終於將首次進軍天母地區，選擇在老字號百貨「高島屋」插旗，用最經...","image":"https:\/\/www.walkerland.com.tw\/image\/subject\/2021\/01\/956283dc2329ee136e3df6f4e2be659ae824a5f9.jpg"},{"theme":"food","keyword":"全聯","title":"2021全聯年菜推薦｜開箱好吃年菜組合！整套不超過4000元的神級美食：團圓套餐懶人包-發胖板｜PopDaily 波波黛莉","url":"https:\/\/www.popdaily.com.tw\/forum\/food\/876123","description":"全聯年菜推薦！一年一度的過年即將來臨，讓人期待的就是全家人聚在一起吃團圓飯的時光。好鄰居全聯年菜推薦給大家，集結名廚們主打堅強陣容的「至尊主廚功夫菜」讓大家不用到餐廳排隊就能在家裡輕鬆吃到名廚料理，吃好吃滿好過年！","image":"https:\/\/www.popdaily.com.tw\/shaper\/u\/202101\/25530fcc-0d0d-4db9-ba29-213f28277192.jpg?resize-w=1200&resize-h=630"},{"theme":"food","keyword":"全聯","title":"[商品] 7-11 中村經典生巧克力生乳捲","url":"https:\/\/www.ptt.cc\/bbs\/CVS\/M.1610727257.A.919.html","description":"【商品名稱\/價格】：中村經典巧克力生乳捲 $45\n【便利商店\/廠商名稱】：7-11\n【規格\/內容物\/熱量】：\nhttps:\/\/i.imgur.com\/kfV0MY2.jpg\n放個拳頭當比例尺\n","image":null},{"theme":"food","keyword":"全聯","title":"石岡燈會逛起來 | 石岡花漾藝術節 七大燈區超好拍 綠六廣場、情人木橋、東豐自行車道 (交通停車\/攻略地圖)","url":"https:\/\/safood.tw\/shigangdenghui","description":"台中石岡燈會「石岡花漾藝術節」開跑囉~ 從食水嵙休閒農業區的情人木橋、東豐自行車道、燈海連綿一直到綠六廣場 (主燈)，從現在起一直到2\/28 每天下午5點半開燈，陪你過年到元宵，七大燈區吸睛又好拍，快跟我們一起逛起來~ 石岡花漾藝術節 食水嵙溪石岡花漾藝術節 時間：2020\/12\/26~2021\/2\/28","image":"https:\/\/img.safood.tw\/uploads\/20210116020640_13.jpg"},{"theme":"food","keyword":"中清店","title":"茶六中清店 | 台中北屯美食 限定A5日本和牛套餐 烤好還要等3分鐘的和牛牛排 伯爵珍奶棒蛋糕","url":"https:\/\/safood.tw\/tea64","description":"茶六中清店 | 小剎來介紹台中北屯美食，「茶六中清店」開始試營運了，裝潢大氣且低調奢華，還有中清店限定的「A5日本和牛套餐」，吃得到5種部位的日本和牛，其中有一種烤好還要等3分鐘的和牛牛排真的超好吃，甜點「伯爵珍奶棒蛋糕」也很吸睛，大家快一起來看看吧~ 茶六中清店 在哪？ 茶六燒肉堂中清店","image":"https:\/\/img.safood.tw\/uploads\/20210116222647_38.jpg"},{"theme":"food","keyword":"台隆","title":"寒流促動暖商機　保暖商品業績順漲2至5成","url":"https:\/\/tw.appledaily.com\/supplement\/20210116\/NTTBTG64CFEQNJZYURCIBMNQIQ\/","description":"連續幾波寒流帶動防寒商品的買氣，中友百貨統計，1\/1~1\/10 全館業績較去年成長25%，除了電暖器、冬被熱賣之外，厚外套及戶外休閒品牌業績也大增，電暖器詢問度尤其高，甚至有多家品牌根本都來不及備貨，直呼好久沒見到這麼旺的買氣。百貨頂級寢飾品牌寬庭也預定19至23日，在永豐棧...","image":"https:\/\/tw.appledaily.com\/resizer\/i1wuWIk3gbaltzIo8iTXcXHcvEs=\/1478x1108\/filters:quality(100)\/cloudfront-ap-northeast-1.images.arcpublishing.com\/appledaily\/INKXNJGRDFEH7AJHWB3TAZSO6E.jpg"},{"theme":"food","keyword":"台隆","title":"台中日式生吐司夯店「一覺吐司」進駐台南！二店即起試營運　滿500贈手工果醬","url":"https:\/\/udn.com\/news\/story\/7186\/5178577?from=udn-catelistnews_ch2","description":"台南吐司控好消息！台中首家高級日式生吐司專賣店「一覺吐司Ichisatori Bakery」去年初登場備受好評，亦成新興排隊名店。如今全台第二間分店確定落腳台南南區西門路，即起開放試賣，試營運期間消費","image":"https:\/\/pgw.udn.com.tw\/gw\/photo.php?u=https:\/\/uc.udn.com.tw\/photo\/2021\/01\/16\/1\/11214849.jpg&s=Y&x=0&y=0&sw=1280&sh=853&exp=3600"},{"theme":"food","keyword":"google","title":"├ 食記 ┤ 一番地 壽喜燒 ♥ 中山區 ♥ 大直Att ♥ 吃到飽 ♥ 鍋底可做素食-發胖板｜PopDaily 波波黛莉","url":"https:\/\/www.popdaily.com.tw\/forum\/food\/877759","description":"話說這篇食記又是二訪之後才寫好的XD 這家一番地短時間內我們來了2次，好像才隔個4~5天吧 第一次是晚上去吃，第二次是中午去吃，都有先訂位 但2次的感受真是天差地遠…我們先來上菜再來說感受~~~ ​中午$428、晚上$498，價格都要+10%服務費 而小孩超過80公分就要收$100 ​飲料選擇其實還","image":"https:\/\/www.popdaily.com.tw\/shaper\/u\/202101\/8e041f46-0261-4343-93ac-325c97af08e0.jpg?resize-w=1200&resize-h=630"},{"theme":"food","keyword":"google","title":"石岡燈會逛起來 | 石岡花漾藝術節 七大燈區超好拍 綠六廣場、情人木橋、東豐自行車道 (交通停車\/攻略地圖)","url":"https:\/\/safood.tw\/shigangdenghui","description":"台中石岡燈會「石岡花漾藝術節」開跑囉~ 從食水嵙休閒農業區的情人木橋、東豐自行車道、燈海連綿一直到綠六廣場 (主燈)，從現在起一直到2\/28 每天下午5點半開燈，陪你過年到元宵，七大燈區吸睛又好拍，快跟我們一起逛起來~ 石岡花漾藝術節 食水嵙溪石岡花漾藝術節 時間：2020\/12\/26~2021\/2\/28","image":"https:\/\/img.safood.tw\/uploads\/20210116020640_13.jpg"},{"theme":"food","keyword":"孫崇軒","title":"東區18禁餐酒館獨家引進波蘭啤酒　消費滿額免費夾情趣用品","url":"https:\/\/tw.appledaily.com\/supplement\/20210116\/HFPJ5YCYENGSXFPJ4AMTQKBBUE\/","description":"位於北市東區巷弄內，以18禁為主題打造的「房間餐酒館the Room」，除了推廣情趣用品，也以驚世駭俗的創意打造用餐空間，如可躺在枕頭上喝酒的SM床、及情趣擺設外，以滷味及啤酒為主打的特色餐飲，也吸引許多人慕名朝聖，而業者近期除了推出情趣夾娃娃機外，也獨家由波蘭引進風味獨特的...","image":"https:\/\/tw.appledaily.com\/resizer\/HAdNWkUu1lSW-f2jnELr76wO-8I=\/2992x2000\/filters:quality(100)\/cloudfront-ap-northeast-1.images.arcpublishing.com\/appledaily\/5QMIZZEYTVBPHAON3FIVFLGEEI.jpg"},{"theme":"food","keyword":"中山","title":"吃吧｜中山站 老宅甜甜圈店也可以很日系「ABCD . A Better Coffee & Doughnut」-發胖板｜PopDaily 波波黛莉","url":"https:\/\/www.popdaily.com.tw\/forum\/food\/876990","description":"就在中山站1號出口 走約5-10分鐘 就可以到達的位置 雖然是隱身在巷弄 但光坐在店內不到半個鐘頭 就至少有5組來外帶 我想他好吃的程度 你們也可存起來了😛 雖然店名一直很想讓我接 ABCD 告嘎低😂😂😂 但整個店內風格 極簡又有點文青的風格 一直讓我想到東京的甜甜圈店 店內只有販售6種口味 但整的","image":"https:\/\/www.popdaily.com.tw\/shaper\/u\/202101\/8f7c28ff-8f25-499d-b1b4-d138680932c4.jpg?resize-w=800"},{"theme":"food","keyword":"中山","title":"[食記] 台北晶華酒店 晶華軒","url":"https:\/\/www.ptt.cc\/bbs\/Food\/M.1610728280.A.BD8.html","description":"無音樂圖文網誌版 https:\/\/wanwanr9.pixnet.net\/blog\/post\/353342914\n==\n   餐廳名稱：晶華酒店 晶華軒\n   消費時間：2021年\/1月\n   地址：台北市中山區中山北路二段39巷3號3樓\n","image":null},{"theme":"food","keyword":"金馬賓館","title":"Fw: [食記]  高雄 金馬賓館 經典炊飯+經典早午餐","url":"https:\/\/www.ptt.cc\/bbs\/Food\/M.1610757840.A.40B.html","description":"永添藝術｜金馬賓館當代美術館\n地址：高雄市鼓山區鼓山一路111號\n輕軌：C15壽山公園(金馬賓館當代美術館站)\n捷運：捷運鹽埕埔站 步行10分鐘\n電話：07-9721685\n","image":null},{"theme":"food","keyword":"綠六廣場","title":"石岡燈會逛起來 | 石岡花漾藝術節 七大燈區超好拍 綠六廣場、情人木橋、東豐自行車道 (交通停車\/攻略地圖)","url":"https:\/\/safood.tw\/shigangdenghui","description":"台中石岡燈會「石岡花漾藝術節」開跑囉~ 從食水嵙休閒農業區的情人木橋、東豐自行車道、燈海連綿一直到綠六廣場 (主燈)，從現在起一直到2\/28 每天下午5點半開燈，陪你過年到元宵，七大燈區吸睛又好拍，快跟我們一起逛起來~ 石岡花漾藝術節 食水嵙溪石岡花漾藝術節 時間：2020\/12\/26~2021\/2\/28","image":"https:\/\/img.safood.tw\/uploads\/20210116020640_13.jpg"},{"theme":"food","keyword":"Lorra","title":"疫下新旅遊模式　酒店狂人一年花40萬住本地酒店","url":"https:\/\/tw.appledaily.com\/supplement\/20210117\/72ZVUMKXVBFKFMMIJ7CFM2XUPI\/","description":"武漢肺炎爆發至今超過一年，大家的旅遊計劃都告吹，為一解旅行癮，不少人選擇到酒店住幾晚。愛旅遊的90後女生Lorra，更在短短一年間，住了超過100晚staycation，計算下來竟有整整三個多月晚上不在家。 請Lorra計算她2020年住過的酒店，最少住過26間，「有部份已很...","image":"https:\/\/tw.appledaily.com\/resizer\/gmZoqyaduJ9NNTWbOtArAuxcvaE=\/1920x1080\/filters:quality(100)\/d87urpdhi5rdo.cloudfront.net\/01-16-2021\/t_ab6e1136c6224e4db9c35e41415ae76f_name_20210109_sub332.png"},{"theme":"food","keyword":"陳正皋","title":"【曼樺本周運勢】6生肖職場受阻　氣噗噗嘆做人好難","url":"https:\/\/tw.appledaily.com\/supplement\/20210117\/O3ZOD4Q725DK3IJ7OJN2LSDYL4\/","description":"命理生肖專家曼樺老師揭曉本周(1\/17~1\/23)各生肖運勢，本周鼠、牛、虎、羊、雞、豬等生肖在職場上面臨各式阻礙，例如鼠爭取業務合作差點被騙；牛、羊因為工作沒按計劃進行，使你備感壓力，不禁感嘆做人比做事難；虎則是心不在焉，一心想著放假；而雞、豬則是人際關係影響專注度，還因此...","image":"https:\/\/tw.appledaily.com\/resizer\/-w6e48EHu42gjhXILEsJlTURnVs=\/4256x2394\/filters:quality(100)\/cloudfront-ap-northeast-1.images.arcpublishing.com\/appledaily\/F7EHOZDOOFBX5N3ZYEM34QVUOQ.jpg"},{"theme":"food","keyword":"曼樺","title":"【曼樺本周運勢】6生肖職場受阻　氣噗噗嘆做人好難","url":"https:\/\/tw.appledaily.com\/supplement\/20210117\/O3ZOD4Q725DK3IJ7OJN2LSDYL4\/","description":"命理生肖專家曼樺老師揭曉本周(1\/17~1\/23)各生肖運勢，本周鼠、牛、虎、羊、雞、豬等生肖在職場上面臨各式阻礙，例如鼠爭取業務合作差點被騙；牛、羊因為工作沒按計劃進行，使你備感壓力，不禁感嘆做人比做事難；虎則是心不在焉，一心想著放假；而雞、豬則是人際關係影響專注度，還因此...","image":"https:\/\/tw.appledaily.com\/resizer\/-w6e48EHu42gjhXILEsJlTURnVs=\/4256x2394\/filters:quality(100)\/cloudfront-ap-northeast-1.images.arcpublishing.com\/appledaily\/F7EHOZDOOFBX5N3ZYEM34QVUOQ.jpg"},{"theme":"food","keyword":"黃任膺","title":"寒流促動暖商機　保暖商品業績順漲2至5成","url":"https:\/\/tw.appledaily.com\/supplement\/20210116\/NTTBTG64CFEQNJZYURCIBMNQIQ\/","description":"連續幾波寒流帶動防寒商品的買氣，中友百貨統計，1\/1~1\/10 全館業績較去年成長25%，除了電暖器、冬被熱賣之外，厚外套及戶外休閒品牌業績也大增，電暖器詢問度尤其高，甚至有多家品牌根本都來不及備貨，直呼好久沒見到這麼旺的買氣。百貨頂級寢飾品牌寬庭也預定19至23日，在永豐棧...","image":"https:\/\/tw.appledaily.com\/resizer\/i1wuWIk3gbaltzIo8iTXcXHcvEs=\/1478x1108\/filters:quality(100)\/cloudfront-ap-northeast-1.images.arcpublishing.com\/appledaily\/INKXNJGRDFEH7AJHWB3TAZSO6E.jpg"},{"theme":"food","keyword":"陶禮君","title":"【讀果電子書】圍爐首選　《蘋果》評比2021最強年菜","url":"https:\/\/tw.appledaily.com\/supplement\/20210116\/K64VEC2H5VAL5PYDDZQH7UTP3A\/","description":"隨手滑長知識，解讀癮！ 《蘋果》電子書平台「讀果 」推出《團圓美食　2021年蘋果評比得獎年菜》，精選37道菜色，免費下載，讓你打開手機、電腦，滑指間隨時想看就看！ 礙於武漢肺炎疫情，大家過年減少出門吃大餐的機會，外帶年菜或許是個不錯的選擇，下月11日就是除夕，《蘋果》集結4...","image":"https:\/\/tw.appledaily.com\/resizer\/r-Xht1qUesk2wGLFzpn1Hj23mOM=\/5499x3093\/filters:quality(100)\/cloudfront-ap-northeast-1.images.arcpublishing.com\/appledaily\/WJNAXFPVMZEL3OJTLT56STWCMA.JPG"},{"theme":"food","keyword":"徐天麟","title":"【讀果電子書】圍爐首選　《蘋果》評比2021最強年菜","url":"https:\/\/tw.appledaily.com\/supplement\/20210116\/K64VEC2H5VAL5PYDDZQH7UTP3A\/","description":"隨手滑長知識，解讀癮！ 《蘋果》電子書平台「讀果 」推出《團圓美食　2021年蘋果評比得獎年菜》，精選37道菜色，免費下載，讓你打開手機、電腦，滑指間隨時想看就看！ 礙於武漢肺炎疫情，大家過年減少出門吃大餐的機會，外帶年菜或許是個不錯的選擇，下月11日就是除夕，《蘋果》集結4...","image":"https:\/\/tw.appledaily.com\/resizer\/r-Xht1qUesk2wGLFzpn1Hj23mOM=\/5499x3093\/filters:quality(100)\/cloudfront-ap-northeast-1.images.arcpublishing.com\/appledaily\/WJNAXFPVMZEL3OJTLT56STWCMA.JPG"},{"theme":"food","keyword":"張麗蓉","title":"【讀果電子書】圍爐首選　《蘋果》評比2021最強年菜","url":"https:\/\/tw.appledaily.com\/supplement\/20210116\/K64VEC2H5VAL5PYDDZQH7UTP3A\/","description":"隨手滑長知識，解讀癮！ 《蘋果》電子書平台「讀果 」推出《團圓美食　2021年蘋果評比得獎年菜》，精選37道菜色，免費下載，讓你打開手機、電腦，滑指間隨時想看就看！ 礙於武漢肺炎疫情，大家過年減少出門吃大餐的機會，外帶年菜或許是個不錯的選擇，下月11日就是除夕，《蘋果》集結4...","image":"https:\/\/tw.appledaily.com\/resizer\/r-Xht1qUesk2wGLFzpn1Hj23mOM=\/5499x3093\/filters:quality(100)\/cloudfront-ap-northeast-1.images.arcpublishing.com\/appledaily\/WJNAXFPVMZEL3OJTLT56STWCMA.JPG"},{"theme":"food","keyword":"Amanda","title":"【下周星情】天冷保命　獅子天蠍摩羯留意身體變化","url":"https:\/\/tw.appledaily.com\/supplement\/20210116\/BKA5WXFNMZDFJKCDCXARPL4HIY\/","description":"據星座專家Amanda解析的(1\/16~1\/22)一周星情，牡羊、金牛、射手、雙魚座特別留意健康運勢，若缺乏運動會讓身體有股沉重感，趁此時調整作息並適度運動，能讓身體不適得到大幅改善之外，也更加健康、心情因此開朗。而獅子、天蠍、摩羯則要注意天氣忽冷忽熱帶來的身體影響，像是坐久...","image":"https:\/\/tw.appledaily.com\/resizer\/WsDL745H1wxln_M556i3cZx6Hvw=\/4896x3264\/filters:quality(100)\/cloudfront-ap-northeast-1.images.arcpublishing.com\/appledaily\/PGZNDGNJEBA2JOCI4S64GB6RVA.jpg"},{"theme":"food","keyword":"文華東方酒店","title":"【報名中】參加即贈8800元單一麥原酒　《夢幻講座》27萬原酒東方文華饗宴","url":"https:\/\/tw.appledaily.com\/supplement\/20210115\/FM67SAMGHRE5VH6MHT22JGM7PM\/","description":"《蘋果夢幻講座》 品酒│年度最華麗 27萬原酒食尚饗宴 點我報名參加 未經稀釋、維持原始橡木桶酒精強度的威士忌原酒，除了不易取得的珍稀性，加上獨一無二的風味及酒體個性，深受不少威士忌迷喜愛，《蘋果新聞網》看準原酒魅力，本月底攜手英蓋爾精品洋酒舉辦《夢幻講座》，針對莫麗斯（TH...","image":"https:\/\/tw.appledaily.com\/resizer\/PizRec7pVjEioiwQy2dax5Awmto=\/1920x1080\/filters:quality(100)\/d87urpdhi5rdo.cloudfront.net\/01-14-2021\/t_5906230b317f4c25857332f830c79e6e_name_t_c48d6235199b44d9bd800d05c1f8f05e_name_14012021_TSUP007_ok_v___6259__.jpg"},{"theme":"food","keyword":"梁鳴輝","title":"【飲食教室】分辨真假白鱔！尖頭才是正版　大廚教兩道美味鱔料理","url":"https:\/\/tw.appledaily.com\/supplement\/20210116\/AHLNS3JLMFGIZKVNTVIRTFCNIM\/","description":"肥美嫩滑的白鱔是冬令的滋補良品，味道鮮甜，蒸、炸、烤、燜、火鍋樣樣皆宜，但到底如何挑選，市面上的白鱔又是否貨真價實，香港《蘋果》這集《飲食教室》一一為大家拆解。 香港市場海鮮舖「十分淡水」的負責人梁鳴輝指出， 現時市面出售的白鱔其實有兩種，一種是真正的白鱔，「白鱔的肉質爽口，...","image":"https:\/\/tw.appledaily.com\/resizer\/8kPvLvqqH_ZASsYq7pxS6kNp9Qs=\/1920x1080\/filters:quality(100)\/d87urpdhi5rdo.cloudfront.net\/01-14-2021\/t_3135f652679f4a59b72308014fc800ff_name___.jpg"},{"theme":"food","keyword":"利東街","title":"【美食的誕生】焦糖蘋果肉桂可麗餅　皮軟薄餡酸甜焦香","url":"https:\/\/tw.appledaily.com\/supplement\/20210116\/GRMSV3EDL5FHHOZ6ZGWVSFQRPA\/","description":"可麗餅(Crêpe)原產地位於法國西北部布列塔尼地區，特點在於餅皮又軟又薄，可以包裹不同餡料，喜歡鹹味的，可以選擇火腿或鮪魚；喜歡甜味的，可以挑選大量水果，加入綿滑的奶油，又是一道可以打卡的甜品。 發展至今，可麗餅既是街頭小食，又是能登上大雅之堂的餐廳甜品之一，受歡迎到令不少...","image":"https:\/\/tw.appledaily.com\/resizer\/2anyyJvLBa_4Blvt6fNM7ij5i3s=\/1920x1080\/filters:quality(100)\/d87urpdhi5rdo.cloudfront.net\/01-14-2021\/t_da61609edbcf4d698b50545c7fbb91c2_name___.jpg"},{"theme":"food","keyword":"Crêpe Delicious","title":"【美食的誕生】焦糖蘋果肉桂可麗餅　皮軟薄餡酸甜焦香","url":"https:\/\/tw.appledaily.com\/supplement\/20210116\/GRMSV3EDL5FHHOZ6ZGWVSFQRPA\/","description":"可麗餅(Crêpe)原產地位於法國西北部布列塔尼地區，特點在於餅皮又軟又薄，可以包裹不同餡料，喜歡鹹味的，可以選擇火腿或鮪魚；喜歡甜味的，可以挑選大量水果，加入綿滑的奶油，又是一道可以打卡的甜品。 發展至今，可麗餅既是街頭小食，又是能登上大雅之堂的餐廳甜品之一，受歡迎到令不少...","image":"https:\/\/tw.appledaily.com\/resizer\/2anyyJvLBa_4Blvt6fNM7ij5i3s=\/1920x1080\/filters:quality(100)\/d87urpdhi5rdo.cloudfront.net\/01-14-2021\/t_da61609edbcf4d698b50545c7fbb91c2_name___.jpg"},{"theme":"food","keyword":"G26","title":"【美食的誕生】焦糖蘋果肉桂可麗餅　皮軟薄餡酸甜焦香","url":"https:\/\/tw.appledaily.com\/supplement\/20210116\/GRMSV3EDL5FHHOZ6ZGWVSFQRPA\/","description":"可麗餅(Crêpe)原產地位於法國西北部布列塔尼地區，特點在於餅皮又軟又薄，可以包裹不同餡料，喜歡鹹味的，可以選擇火腿或鮪魚；喜歡甜味的，可以挑選大量水果，加入綿滑的奶油，又是一道可以打卡的甜品。 發展至今，可麗餅既是街頭小食，又是能登上大雅之堂的餐廳甜品之一，受歡迎到令不少...","image":"https:\/\/tw.appledaily.com\/resizer\/2anyyJvLBa_4Blvt6fNM7ij5i3s=\/1920x1080\/filters:quality(100)\/d87urpdhi5rdo.cloudfront.net\/01-14-2021\/t_da61609edbcf4d698b50545c7fbb91c2_name___.jpg"}]